Workbook

Sheet DATABANK
A1: Count | B1: Item Number | C1: POSITION | D1: Specialist | E1: Parentetical | F1: UNIT / SECTION | G1: CADRE | H1: 26 | I1: SALARY GRADE | J1: AUTHORIZED SALARY | K1: Level2 | L1: FILLED&UNFILLED | M1: LAST | N1: FIRST | O1: MIDDLE | P1: SUFFIX | Q1: DATE OF BIRTH | R1: DATE OF ORIGINAL APPOINTMENT | S1: ASSUMPTION | T1: LATEST PROMOTION | U1: CIVIL STATUS | V1: GENDER | W1: AGE | X1: AGE GROUP | Y1: PLACE OF BIRTH | Z1: No., Street, Subd./Village | AA1: Baranggay | AB1: City/Municipality | AC1: Province | AD1: Zip Code | AE1: EDUCATIONAL ATTAINMENT | AF1: PROGRAM/COURSE | AG1: ELIGIBILITY | AH1: LICENSE NO. | AI1: VALIDITY | AJ1: GSIS | AK1: PAG-IBIG | AL1: PHILHEALTH | AM1: TIN | AN1: MOBILE NO. | AO1: PHONE NO. | AP1: EMAIL ADDRESS
A2: 1 | B2: OSEC-DOHB-MDC2-29-2025 | C2: Medical Center Chief II | E2: Medical Center Chief | F2: Office of the Medical Center Chief | G2: Physician | H2: Medical Division | I2: 27 | J2: =LOOKUP(Table1[[#This Row],[SALARY GRADE]],{1,2,3,4,5,6,7,8,9,10,11,12,13,14,15,16,17,18,19,20,21,22,23,24,25,26,27,28,29,30,31,32,33},{14364,15522,16486,17506,18581,19716,20914,22423,24329,26917,31705,33947,36125,38764,42178,45694,49562,53818,59153,66052,73303,81796,91306,102603,116643,131807,148940,167129,187531,210718,300961,356237,449157}) -> 148940 | K2: 3rd | L2: =IF(Table1[[#This Row],[LAST]]="","Unfilled","Filled") -> Filled | M2: Rubiano | N2: Ruby Ephraim | O2: Morales | Q2: 24172 | R2: 42019 | S2: 45061 | T2: 45061 | U2: Married | V2: Male | W2: =DATEDIF(Q2,TODAY(),"Y") -> 60 | X2: =IF(ABS(Table1[[#This Row],[AGE]])>59,"60 and above",IF(ABS(Table1[[#This Row],[AGE]])>49,"50-59",IF(ABS(Table1[[#This Row],[AGE]])>39,"40-49",IF(ABS(Table1[[#This Row],[AGE]])>29,"30-39",IF(ABS(Table1[[#This Row],[AGE]])>19,"20-29",""))))) -> 60 and above | Y2: Samal, Bataan | Z2: #99 K 2nd | AA2: Kamuning | AB2: Quezon City | AC2: Metro Manila | AD2: 1103 | AE2: Doctor of Medicine | AF2: Medicine | AG2: RA 1080 | AH2: 0077906 | AI2: 46452 | AJ2: 2001913799 | AK2: 1211-8088-4348 | AL2: 0700-0120-7464 | AM2: 164-003-877 | AN2: 0926-671-5623 | AO2: N/A | AP2: rer.rubiano@gmail.com
A3: 2 | B3: OSEC-DOHB-COMPS2-30-2025 | C3: Chief of Medical professional Staff II | D3: Obstetrician | E3: CMPS | F3: Office of the Chief of Medical Professional Staff | G3: Physician | H3: Medical Division | I3: 26 | J3: =LOOKUP(Table1[[#This Row],[SALARY GRADE]],{1,2,3,4,5,6,7,8,9,10,11,12,13,14,15,16,17,18,19,20,21,22,23,24,25,26,27,28,29,30,31,32,33},{14364,15522,16486,17506,18581,19716,20914,22423,24329,26917,31705,33947,36125,38764,42178,45694,49562,53818,59153,66052,73303,81796,91306,102603,116643,131807,148940,167129,187531,210718,300961,356237,449157}) -> 131807 | K3: 3rd | L3: =IF(Table1[[#This Row],[LAST]]="","Unfilled","Filled") -> Filled | M3: Gabor | N3: Rebecca Ann | O3: Vasquez | Q3: 30144 | R3: 44363 | S3: 44363 | T3: 45505 | U3: Single | V3: Female | W3: =DATEDIF(Q3,TODAY(),"Y") -> 44 | X3: =IF(ABS(Table1[[#This Row],[AGE]])>59,"60 and above",IF(ABS(Table1[[#This Row],[AGE]])>49,"50-59",IF(ABS(Table1[[#This Row],[AGE]])>39,"40-49",IF(ABS(Table1[[#This Row],[AGE]])>29,"30-39",IF(ABS(Table1[[#This Row],[AGE]])>19,"20-29",""))))) -> 40-49 | Y3: Makati City | Z3: 115 Camino Real Rd., Pilar Village | AA3: Pilar | AB3: Las Piñas City | AC3: NCR | AD3: 1740 | AE3: Doctor of Medicine | AF3: Medicine | AG3: RA 1080 | AH3: 0110711 | AI3: 45850 | AJ3: 2004118248 | AK3: 1212-7910-9885 | AL3: 0800-0096-7290 | AM3: 219-078-812 | AN3: 0917-826-0712 | AO3: (02) 8818-1298 | AP3: rebeccaanngabormd@gmail.com
A4: 3 | B4: OSEC-DOHB-MDSP3-270008-2022 | C4: Medical Specialist III (Internal Medicine) | D4: Internist | E4: Medical Specialist III | F4: Internal Medicine Department | G4: Physician | H4: Medical Division | I4: 24 | J4: =LOOKUP(Table1[[#This Row],[SALARY GRADE]],{1,2,3,4,5,6,7,8,9,10,11,12,13,14,15,16,17,18,19,20,21,22,23,24,25,26,27,28,29,30,31,32,33},{14364,15522,16486,17506,18581,19716,20914,22423,24329,26917,31705,33947,36125,38764,42178,45694,49562,53818,59153,66052,73303,81796,91306,102603,116643,131807,148940,167129,187531,210718,300961,356237,449157}) -> 102603 | K4: 2nd | L4: =IF(Table1[[#This Row],[LAST]]="","Unfilled","Filled") -> Filled | M4: Demetria | N4: Jessie | O4: Datig | Q4: 28721 | R4: 44858 | S4: 44858 | T4: 44858 | U4: Married | V4: Male | W4: =DATEDIF(Q4,TODAY(),"Y") -> 47 | X4: =IF(ABS(Table1[[#This Row],[AGE]])>59,"60 and above",IF(ABS(Table1[[#This Row],[AGE]])>49,"50-59",IF(ABS(Table1[[#This Row],[AGE]])>39,"40-49",IF(ABS(Table1[[#This Row],[AGE]])>29,"30-39",IF(ABS(Table1[[#This Row],[AGE]])>19,"20-29",""))))) -> 40-49 | Y4: Leyte | Z4: B25 L20 P2 Baby's Breath St., Villa de Primarosa | AA4: Buhay na Tubig | AB4: Imus City | AC4: Cavite | AD4: 4103 | AE4: Doctor of Medicine | AF4: Medicine | AG4: RA 1080 | AH4: 0106098 | AI4: 46253 | AJ4: 2001127858 | AK4: 1210-0608-1771 | AL4: 0300-0227-2284 | AM4: 249-490-097 | AN4: 0925-688-8340 | AO4: (046) 476-9635 | AP4: jesdm3a@gmail.com
A5: 4 | B5: OSEC-DOHB-MDSP3-270009-2022 | C5: Medical Specialist III (Surgeon) | D5: Surgeon | E5: Medical Specialist III | F5: Surgery Department | G5: Physician | H5: Medical Division | I5: 24 | J5: =LOOKUP(Table1[[#This Row],[SALARY GRADE]],{1,2,3,4,5,6,7,8,9,10,11,12,13,14,15,16,17,18,19,20,21,22,23,24,25,26,27,28,29,30,31,32,33},{14364,15522,16486,17506,18581,19716,20914,22423,24329,26917,31705,33947,36125,38764,42178,45694,49562,53818,59153,66052,73303,81796,91306,102603,116643,131807,148940,167129,187531,210718,300961,356237,449157}) -> 102603 | K5: 2nd | L5: =IF(Table1[[#This Row],[LAST]]="","Unfilled","Filled") -> Filled | M5: Sabal | N5: Eliseo | O5: Bautista | P5: Jr. | Q5: 26382 | R5: 44907 | S5: 44907 | T5: 44907 | U5: Married | V5: Male | W5: =DATEDIF(Q5,TODAY(),"Y") -> 54 | X5: =IF(ABS(Table1[[#This Row],[AGE]])>59,"60 and above",IF(ABS(Table1[[#This Row],[AGE]])>49,"50-59",IF(ABS(Table1[[#This Row],[AGE]])>39,"40-49",IF(ABS(Table1[[#This Row],[AGE]])>29,"30-39",IF(ABS(Table1[[#This Row],[AGE]])>19,"20-29",""))))) -> 50-59 | Y5: California, USA | Z5: 663 Arcedera, San Antonio | AA5: 43 | AB5: Cavite City | AC5: Cavite | AD5: 4100 | AE5: Doctor of Medicine | AF5: Medicine | AG5: RA 1080 | AH5: 0090301 | AI5: 45740 | AJ5: 2001006475 | AK5: 1213-1329-9128 | AL5: 1300-0500-7833 | AM5: 215-487-799 | AN5: 0917-551-2270 | AO5: (046) 434-17533 | AP5: leejaymd@gmail.com
A6: 5 | B6: OSEC-DOHB-MDSP3-270010-2022 | C6: Medical Specialist III (Anesthesiologist) | D6: Anesthesiologist | E6: Medical Specialist III | F6: Anesthesiology Department | G6: Physician | H6: Medical Division | I6: 24 | J6: =LOOKUP(Table1[[#This Row],[SALARY GRADE]],{1,2,3,4,5,6,7,8,9,10,11,12,13,14,15,16,17,18,19,20,21,22,23,24,25,26,27,28,29,30,31,32,33},{14364,15522,16486,17506,18581,19716,20914,22423,24329,26917,31705,33947,36125,38764,42178,45694,49562,53818,59153,66052,73303,81796,91306,102603,116643,131807,148940,167129,187531,210718,300961,356237,449157}) -> 102603 | K6: 2nd | L6: =IF(Table1[[#This Row],[LAST]]="","Unfilled","Filled") -> Filled | M6: Esguerra | N6: Marc Wilmer | O6: Dela Cruz | Q6: 32209 | R6: 44851 | S6: 44851 | T6: 44851 | U6: Married | V6: Male | W6: =DATEDIF(Q6,TODAY(),"Y") -> 38 | X6: =IF(ABS(Table1[[#This Row],[AGE]])>59,"60 and above",IF(ABS(Table1[[#This Row],[AGE]])>49,"50-59",IF(ABS(Table1[[#This Row],[AGE]])>39,"40-49",IF(ABS(Table1[[#This Row],[AGE]])>29,"30-39",IF(ABS(Table1[[#This Row],[AGE]])>19,"20-29",""))))) -> 30-39 | Y6: Las Piñas City | Z6: B3 L2 Redbay Ave. Norfolk Ridge, Greenwoods | AA6: Sampaloc 3 | AB6: Dasmariñas City | AC6: Cavite | AD6: 4114 | AE6: Doctor of Medicine | AF6: Medicine | AG6: RA 1080 | AH6: 0127400 | AI6: 46206 | AJ6: 2004685518 | AK6: 1211-4378-4931 | AL6: 0200-0252-3966 | AM6: 457-755-367 | AN6: 0949-825-7967 | AO6: N/A | AP6: mawiesguerra787@gmail.com
A7: 6 | B7: OSEC-DOHB-MDSP3-270011-2022 | C7: Medical Specialist III (Pediatrician) | D7: Pediatrician | E7: Medical Specialist III | F7: Pediatrics Department | G7: Physician | H7: Medical Division | I7: 24 | J7: =LOOKUP(Table1[[#This Row],[SALARY GRADE]],{1,2,3,4,5,6,7,8,9,10,11,12,13,14,15,16,17,18,19,20,21,22,23,24,25,26,27,28,29,30,31,32,33},{14364,15522,16486,17506,18581,19716,20914,22423,24329,26917,31705,33947,36125,38764,42178,45694,49562,53818,59153,66052,73303,81796,91306,102603,116643,131807,148940,167129,187531,210718,300961,356237,449157}) -> 102603 | K7: 2nd | L7: =IF(Table1[[#This Row],[LAST]]="","Unfilled","Filled") -> Filled | M7: Co | N7: Icene Rose | O7: Sy | Q7: 32445 | R7: 44837 | S7: 44837 | T7: 44837 | U7: Married | V7: Female | W7: =DATEDIF(Q7,TODAY(),"Y") -> 37 | X7: =IF(ABS(Table1[[#This Row],[AGE]])>59,"60 and above",IF(ABS(Table1[[#This Row],[AGE]])>49,"50-59",IF(ABS(Table1[[#This Row],[AGE]])>39,"40-49",IF(ABS(Table1[[#This Row],[AGE]])>29,"30-39",IF(ABS(Table1[[#This Row],[AGE]])>19,"20-29",""))))) -> 30-39 | Y7: Quezon City | Z7: 3517 Pacific Regency Cityland | AA7: 719 | AB7: Malate | AC7: Manila | AE7: Doctor of Medicine | AF7: Medicine | AG7: RA 1080 | AH7: 0129259 | AI7: 46689 | AJ7: 2006160496 | AK7: 1213-0852-8116 | AL7: 1501-1845-4002 | AM7: 494-339-885 | AN7: 0917-132-7204 | AO7: (02) 8372-9556 | AP7: icenerosesy@gmail.com
A8: 7 | B8: OSEC-DOHB-MDSP3-270012-2022 | C8: Medical Specialist III (Pathologist) | D8: Pathologist | E8: Medical Specialist III | F8: Clinical and Anatomical Laboratory Department | G8: Physician | H8: Medical Division | I8: 24 | J8: =LOOKUP(Table1[[#This Row],[SALARY GRADE]],{1,2,3,4,5,6,7,8,9,10,11,12,13,14,15,16,17,18,19,20,21,22,23,24,25,26,27,28,29,30,31,32,33},{14364,15522,16486,17506,18581,19716,20914,22423,24329,26917,31705,33947,36125,38764,42178,45694,49562,53818,59153,66052,73303,81796,91306,102603,116643,131807,148940,167129,187531,210718,300961,356237,449157}) -> 102603 | K8: 2nd | L8: =IF(Table1[[#This Row],[LAST]]="","Unfilled","Filled") -> Filled | M8: Rosales | N8: Carole Zaidel | O8: Marudo | Q8: 32426 | R8: 44762 | S8: 45323 | T8: 45323 | U8: Single | V8: Female | W8: =DATEDIF(Q8,TODAY(),"Y") -> 37 | X8: =IF(ABS(Table1[[#This Row],[AGE]])>59,"60 and above",IF(ABS(Table1[[#This Row],[AGE]])>49,"50-59",IF(ABS(Table1[[#This Row],[AGE]])>39,"40-49",IF(ABS(Table1[[#This Row],[AGE]])>29,"30-39",IF(ABS(Table1[[#This Row],[AGE]])>19,"20-29",""))))) -> 30-39 | Y8: Batangas City | Z8: #519 Garnet Bldg., Rosewood Pointe, Acacia Estate | AA8: Ususan | AB8: Taguig City | AC8: Metro Manila | AD8: 1639 | AE8: Doctor of Medicine | AF8: Medicine | AG8: RA 1080 | AH8: 0134392 | AI8: 45940 | AJ8: 2005378321 | AK8: 1210-4849-5669 | AL8: 0205-0559-7703 | AM8: 275-580-443 | AN8: 0927-235-9111 | AO8: 784-3268 | AP8: czaidelmrosales@gmail.com
A9: 8 | B9: OSEC-DOHB-MDSP3-270013-2022 | C9: Medical Specialist III (ER) | D9: Emergency Med | E9: Medical Specialist III | F9: Emergency Medicine Department | G9: Physician | H9: Medical Division | I9: 24 | J9: =LOOKUP(Table1[[#This Row],[SALARY GRADE]],{1,2,3,4,5,6,7,8,9,10,11,12,13,14,15,16,17,18,19,20,21,22,23,24,25,26,27,28,29,30,31,32,33},{14364,15522,16486,17506,18581,19716,20914,22423,24329,26917,31705,33947,36125,38764,42178,45694,49562,53818,59153,66052,73303,81796,91306,102603,116643,131807,148940,167129,187531,210718,300961,356237,449157}) -> 102603 | K9: 2nd | L9: =IF(Table1[[#This Row],[LAST]]="","Unfilled","Filled") -> Filled | M9: Napuli | N9: Brylle | O9: Siva | Q9: 32280 | R9: 44966 | S9: 45302 | T9: 45302 | U9: Single | V9: Male | W9: =DATEDIF(Q9,TODAY(),"Y") -> 38 | X9: =IF(ABS(Table1[[#This Row],[AGE]])>59,"60 and above",IF(ABS(Table1[[#This Row],[AGE]])>49,"50-59",IF(ABS(Table1[[#This Row],[AGE]])>39,"40-49",IF(ABS(Table1[[#This Row],[AGE]])>29,"30-39",IF(ABS(Table1[[#This Row],[AGE]])>19,"20-29",""))))) -> 30-39 | Y9: Las Piñas City | Z9: 410 Topaz St., Perpetual Village IV | AA9: Panapaan VIII | AB9: Bacoor City | AC9: Cavite | AD9: 4102 | AE9: Doctor of Medicine | AF9: Medicine | AG9: RA 1080 | AH9: 0129029 | AI9: 46159 | AJ9: 2006264724 | AK9: 1213-1628-3544 | AL9: 0802-6285-3733 | AM9: 459-479-355 | AN9: 0908-626-4633 | AO9: N/A | AP9: napulibrylle@yahoo.com
A10: 9 | B10: OSEC-DOHB-MDSPT3-270001-2022 | C10: Medical Specialist III (Part-time) (Pediatric Intensivist) | D10: Pediatric Intensivist | E10: Medical Specialist III | F10: Pediatrics Department | G10: Physician | H10: Medical Division | I10: 24 | J10: =LOOKUP(Table1[[#This Row],[SALARY GRADE]],{1,2,3,4,5,6,7,8,9,10,11,12,13,14,15,16,17,18,19,20,21,22,23,24,25,26,27,28,29,30,31,32,33},{14364,15522,16486,17506,18581,19716,20914,22423,24329,26917,31705,33947,36125,38764,42178,45694,49562,53818,59153,66052,73303,81796,91306,102603,116643,131807,148940,167129,187531,210718,300961,356237,449157}) -> 102603 | K10: 2nd | L10: =IF(Table1[[#This Row],[LAST]]="","Unfilled","Filled") -> Filled | M10: Fabian | N10: Bethzaida Rachel | O10: Saputil | Q10: 30063 | R10: 45027 | S10: 45027 | T10: 45027 | U10: Single | V10: Female | W10: =DATEDIF(Q10,TODAY(),"Y") -> 44 | X10: =IF(ABS(Table1[[#This Row],[AGE]])>59,"60 and above",IF(ABS(Table1[[#This Row],[AGE]])>49,"50-59",IF(ABS(Table1[[#This Row],[AGE]])>39,"40-49",IF(ABS(Table1[[#This Row],[AGE]])>29,"30-39",IF(ABS(Table1[[#This Row],[AGE]])>19,"20-29",""))))) -> 40-49 | Y10: Metro Manila | Z10: Phase 9B Block 3B Lot 11 Daphne St., Greenwoods Village | AA10: Sampaloc 3 | AB10: Dasmariñas City | AC10: Cavite | AD10: 4114 | AE10: Doctor of Medicine | AF10: Medicine | AG10: RA 1080 | AH10: 0110816 | AI10: 45769 | AJ10: 2004285297 | AK10: 1210-1267-7170 | AL10: 0800-0097-7369 | AM10: 254-450-036 | AN10: 0917-584-4880 | AO10: N/A | AP10: bethzaidafabian@gmail.com
A11: 10 | B11: OSEC-DOHB-MDSPT3-270002-2022 | C11: Medical Specialist III (Part-time) (Neurologist) | D11: Neurologist | E11: Medical Specialist III | F11: Internal Medicine Department | G11: Physician | H11: Medical Division | I11: 24 | J11: =LOOKUP(Table1[[#This Row],[SALARY GRADE]],{1,2,3,4,5,6,7,8,9,10,11,12,13,14,15,16,17,18,19,20,21,22,23,24,25,26,27,28,29,30,31,32,33},{14364,15522,16486,17506,18581,19716,20914,22423,24329,26917,31705,33947,36125,38764,42178,45694,49562,53818,59153,66052,73303,81796,91306,102603,116643,131807,148940,167129,187531,210718,300961,356237,449157}) -> 102603 | K11: 2nd | L11: =IF(Table1[[#This Row],[LAST]]="","Unfilled","Filled") -> Filled | M11: Chua | N11: Ronald | O11: Dologuin | Q11: 32406 | R11: 46064 | S11: 46064 | T11: 46064 | U11: Single | V11: Male | W11: =DATEDIF(Q11,TODAY(),"Y") -> 37 | X11: =IF(ABS(Table1[[#This Row],[AGE]])>59,"60 and above",IF(ABS(Table1[[#This Row],[AGE]])>49,"50-59",IF(ABS(Table1[[#This Row],[AGE]])>39,"40-49",IF(ABS(Table1[[#This Row],[AGE]])>29,"30-39",IF(ABS(Table1[[#This Row],[AGE]])>19,"20-29",""))))) -> 30-39 | Y11: Manila | Z11: 1952 Ipil St. | AA11: Sta. Cruz | AB11: Manila City | AC11: Metro Manila | AD11: 1003 | AE11: Doctor of Medicine | AF11: Medicine | AG11: RA 1080 | AH11: 0127321 | AI11: 46285 | AJ11: 2004854373 | AK11: 1211-5943-6377 | AL11: 0102-5429-9567 | AM11: 461-105-367 | AN11: 0917-564-0437 | AO11: 8253-6911 | AP11: ronaldchua@gmail.com
A12: 11 | B12: OSEC-DOHB-MDSPT3-270003-2022 | C12: Medical Specialist III (Part-time) (IDS) | D12: Infectious Disease Specialist | E12: Medical Specialist III | F12: Internal Medicine Department | G12: Physician | H12: Medical Division | I12: 24 | J12: =LOOKUP(Table1[[#This Row],[SALARY GRADE]],{1,2,3,4,5,6,7,8,9,10,11,12,13,14,15,16,17,18,19,20,21,22,23,24,25,26,27,28,29,30,31,32,33},{14364,15522,16486,17506,18581,19716,20914,22423,24329,26917,31705,33947,36125,38764,42178,45694,49562,53818,59153,66052,73303,81796,91306,102603,116643,131807,148940,167129,187531,210718,300961,356237,449157}) -> 102603 | K12: 2nd | L12: =IF(Table1[[#This Row],[LAST]]="","Unfilled","Filled") -> Filled | M12: Mantaring | N12: Dan Meynard | O12: Lagbas | Q12: 33397 | R12: 45126 | S12: 45126 | T12: 45126 | U12: Single | V12: Male | W12: =DATEDIF(Q12,TODAY(),"Y") -> 35 | X12: =IF(ABS(Table1[[#This Row],[AGE]])>59,"60 and above",IF(ABS(Table1[[#This Row],[AGE]])>49,"50-59",IF(ABS(Table1[[#This Row],[AGE]])>39,"40-49",IF(ABS(Table1[[#This Row],[AGE]])>29,"30-39",IF(ABS(Table1[[#This Row],[AGE]])>19,"20-29",""))))) -> 30-39 | Y12: Al Khobar, KSA | Z12: Ph 3 Blk 9 Lot 2, Governor's Hills Subd. | AA12: Biclatan | AB12: General Trias City | AC12: Cavite | AD12: 4107 | AE12: Doctor of Medicine | AF12: Medicine | AG12: RA 1080 | AH12: 0134205 | AI12: 45816 | AJ12: 2006346341 | AK12: 1213-2189-7503 | AL12: 0102-6100-1115 | AM12: 337-134-221 | AN12: 0905-283-4736 | AO12: (046) 402-1617 | AP12: danmeynard.mantaring@gmail.com
A13: 12 | B13: OSEC-DOHB-MDSPT3-270004-2022 | C13: Medical Specialist III (Part-time) (Sonologist) | D13: Sonologist | E13: Medical Specialist III | F13: Obstetrics-Gynecology Department | G13: Physician | H13: Medical Division | I13: 24 | J13: =LOOKUP(Table1[[#This Row],[SALARY GRADE]],{1,2,3,4,5,6,7,8,9,10,11,12,13,14,15,16,17,18,19,20,21,22,23,24,25,26,27,28,29,30,31,32,33},{14364,15522,16486,17506,18581,19716,20914,22423,24329,26917,31705,33947,36125,38764,42178,45694,49562,53818,59153,66052,73303,81796,91306,102603,116643,131807,148940,167129,187531,210718,300961,356237,449157}) -> 102603 | K13: 2nd | L13: =IF(Table1[[#This Row],[LAST]]="","Unfilled","Filled") -> Filled | M13: Marcaida | N13: David | O13: Valdemoro | Q13: 26327 | R13: 45463 | S13: 45463 | T13: 45463 | U13: Single | V13: Male | W13: =DATEDIF(Q13,TODAY(),"Y") -> 54 | X13: =IF(ABS(Table1[[#This Row],[AGE]])>59,"60 and above",IF(ABS(Table1[[#This Row],[AGE]])>49,"50-59",IF(ABS(Table1[[#This Row],[AGE]])>39,"40-49",IF(ABS(Table1[[#This Row],[AGE]])>29,"30-39",IF(ABS(Table1[[#This Row],[AGE]])>19,"20-29",""))))) -> 50-59 | Y13: Aroroy, Masbate | Z13: 13 Carissa, Doña Manuela | AA13: Pamplona Tres | AB13: Las Piñas City | AC13: Metro Manila | AD13: 1740 | AE13: Doctor of Medicine | AF13: Medicine | AG13: RA 1080 | AH13: 090068 | AI13: 46416 | AJ13: 2001754190 | AK13: 1210-6704-2897 | AL13: 0202-5017-8698 | AM13: 205-436-533 | AN13: 0917-860-8090 | AO13: N/A | AP13: periphnymu@gmail.com
A14: 13 | B14: OSEC-DOHB-MDSPT3-270005-2021 | C14: Medical Specialist III (Part-time) (Pulmonolgist) | D14: Pulmonologist | E14: Medical Specialist III | F14: Internal Medicine Department | G14: Physician | H14: Medical Division | I14: 24 | J14: =LOOKUP(Table1[[#This Row],[SALARY GRADE]],{1,2,3,4,5,6,7,8,9,10,11,12,13,14,15,16,17,18,19,20,21,22,23,24,25,26,27,28,29,30,31,32,33},{14364,15522,16486,17506,18581,19716,20914,22423,24329,26917,31705,33947,36125,38764,42178,45694,49562,53818,59153,66052,73303,81796,91306,102603,116643,131807,148940,167129,187531,210718,300961,356237,449157}) -> 102603 | K14: 2nd | L14: =IF(Table1[[#This Row],[LAST]]="","Unfilled","Filled") -> Filled | M14: Estrella | N14: Noel | O14: Valdepeña | Q14: 27394 | R14: 45019 | S14: 45019 | T14: 45019 | U14: Single | V14: Male | W14: =DATEDIF(Q14,TODAY(),"Y") -> 51 | X14: =IF(ABS(Table1[[#This Row],[AGE]])>59,"60 and above",IF(ABS(Table1[[#This Row],[AGE]])>49,"50-59",IF(ABS(Table1[[#This Row],[AGE]])>39,"40-49",IF(ABS(Table1[[#This Row],[AGE]])>29,"30-39",IF(ABS(Table1[[#This Row],[AGE]])>19,"20-29",""))))) -> 50-59 | Y14: Torrijos, Marinduque | Z14: B17 L27-E Basilio Estanislao St., BF Resort Village | AA14: Talon Dos | AB14: Las Piñas City | AC14: Metro Manila | AD14: 1740 | AE14: Doctor of Medicine | AF14: Medicine | AG14: RA 1080 | AH14: 0094493 | AI14: 46022 | AJ14: 2006306691 | AK14: 0141-3003-5607 | AL14: 0802-5092-5925 | AM14: 217-710-251 | AN14: 0917-890-3195 | AO14: (02) 8874-8558 | AP14: noelestrella_md@yahoo.com
A15: 14 | B15: OSEC-DOHB-MDSPT3-270006-2021 | C15: Medical Specialist III (Part-time) (Cardiologist) | D15: Cardiologist | E15: Medical Specialist III | F15: Internal Medicine Department | G15: Physician | H15: Medical Division | I15: 24 | J15: =LOOKUP(Table1[[#This Row],[SALARY GRADE]],{1,2,3,4,5,6,7,8,9,10,11,12,13,14,15,16,17,18,19,20,21,22,23,24,25,26,27,28,29,30,31,32,33},{14364,15522,16486,17506,18581,19716,20914,22423,24329,26917,31705,33947,36125,38764,42178,45694,49562,53818,59153,66052,73303,81796,91306,102603,116643,131807,148940,167129,187531,210718,300961,356237,449157}) -> 102603 | K15: 2nd | L15: =IF(Table1[[#This Row],[LAST]]="","Unfilled","Filled") -> Filled | M15: Gutierrez | N15: Ian Lordeo | O15: Arcusa | Q15: 32550 | R15: 44691 | S15: 44691 | T15: 44691 | U15: Married | V15: Male | W15: =DATEDIF(Q15,TODAY(),"Y") -> 37 | X15: =IF(ABS(Table1[[#This Row],[AGE]])>59,"60 and above",IF(ABS(Table1[[#This Row],[AGE]])>49,"50-59",IF(ABS(Table1[[#This Row],[AGE]])>39,"40-49",IF(ABS(Table1[[#This Row],[AGE]])>29,"30-39",IF(ABS(Table1[[#This Row],[AGE]])>19,"20-29",""))))) -> 30-39 | Y15: Rosario, Cavite | Z15: 258 Duhat Rd., Justinville | AA15: Panapaan VII | AB15: Bacoor City | AC15: Cavite | AD15: 4102 | AE15: Doctor of Medicine | AF15: Medicine | AG15: RA 1080 | AH15: 0127426 | AI15: 46064 | AJ15: 2006083593 | AK15: 1213-0111-2094 | AL15: 0802-5830-8216 | AM15: 283-613-262 | AN15: 0917-529-9182 | AO15: 471-0557 | AP15: ian_lordeo_gutierrez@yahoo.com
A16: 15 | B16: OSEC-DOHB-MDSPT3-270007-2021 | C16: Medical Specialist III (Part-time) (Nephrologist) | D16: Nephrologist | E16: Medical Specialist III | F16: Internal Medicine Department | G16: Physician | H16: Medical Division | I16: 24 | J16: =LOOKUP(Table1[[#This Row],[SALARY GRADE]],{1,2,3,4,5,6,7,8,9,10,11,12,13,14,15,16,17,18,19,20,21,22,23,24,25,26,27,28,29,30,31,32,33},{14364,15522,16486,17506,18581,19716,20914,22423,24329,26917,31705,33947,36125,38764,42178,45694,49562,53818,59153,66052,73303,81796,91306,102603,116643,131807,148940,167129,187531,210718,300961,356237,449157}) -> 102603 | K16: 2nd | L16: =IF(Table1[[#This Row],[LAST]]="","Unfilled","Filled") -> Filled | M16: Garibay | N16: Mavis Athina | O16: Abuel | Q16: 32376 | R16: 44748 | S16: 44748 | T16: 44748 | U16: Single | V16: Female | W16: =DATEDIF(Q16,TODAY(),"Y") -> 37 | X16: =IF(ABS(Table1[[#This Row],[AGE]])>59,"60 and above",IF(ABS(Table1[[#This Row],[AGE]])>49,"50-59",IF(ABS(Table1[[#This Row],[AGE]])>39,"40-49",IF(ABS(Table1[[#This Row],[AGE]])>29,"30-39",IF(ABS(Table1[[#This Row],[AGE]])>19,"20-29",""))))) -> 30-39 | Y16: Angono, Rizal | Z16: Blk 4 Lot 6 Jade St. MS5 Village Lancaster | AA16: Navarro | AB16: General Trias City | AC16: Cavite | AD16: 4107 | AE16: Doctor of Medicine | AF16: Medicine | AG16: RA 1080 | AH16: 0127874 | AI16: 46255 | AJ16: 2004875794 | AK16: 1211-6739-8577 | AL16: 0302-5829-0441 | AM16: 469-230-086 | AN16: 0917-136-5399 | AO16: N/A | AP16: mavisgaribay@yahoo.com
A17: 16 | B17: OSEC-DOHB-MDSPT3-270008-2021 | C17: Medical Specialist III (Part-time) (Neonatologist) | D17: Neonatologist | E17: Medical Specialist III | F17: Pediatrics Department | G17: Physician | H17: Medical Division | I17: 24 | J17: =LOOKUP(Table1[[#This Row],[SALARY GRADE]],{1,2,3,4,5,6,7,8,9,10,11,12,13,14,15,16,17,18,19,20,21,22,23,24,25,26,27,28,29,30,31,32,33},{14364,15522,16486,17506,18581,19716,20914,22423,24329,26917,31705,33947,36125,38764,42178,45694,49562,53818,59153,66052,73303,81796,91306,102603,116643,131807,148940,167129,187531,210718,300961,356237,449157}) -> 102603 | K17: 2nd | L17: =IF(Table1[[#This Row],[LAST]]="","Unfilled","Filled") -> Filled | M17: Vicarez-Palogan | N17: Chelsea | O17: Gonzales | Q17: 32082 | R17: 44691 | S17: 44691 | T17: 44691 | U17: Married | V17: Female | W17: =DATEDIF(Q17,TODAY(),"Y") -> 38 | X17: =IF(ABS(Table1[[#This Row],[AGE]])>59,"60 and above",IF(ABS(Table1[[#This Row],[AGE]])>49,"50-59",IF(ABS(Table1[[#This Row],[AGE]])>39,"40-49",IF(ABS(Table1[[#This Row],[AGE]])>29,"30-39",IF(ABS(Table1[[#This Row],[AGE]])>19,"20-29",""))))) -> 30-39 | Y17: Manila | Z17: 26 Evangeline Reyes BF Resort | AA17: Talon Dos | AB17: Las Piñas City | AC17: NCR | AD17: 1747 | AE17: Doctor of Medicine | AF17: Medicine | AG17: RA 1080 | AH17: 0126199 | AI17: 46033 | AJ17: 2005217481 | AK17: 1212-02238-6406 | AL17: 0105-0495-3055 | AM17: 305-897-411 | AN17: 0917-536-2901 | AO17: N/A | AP17: chelseavicarez@yahoo.com
A18: 17 | B18: OSEC-DOHB-MDSP3-270023-2020 | C18: Medical Specialist III (Obstetrician) | D18: Obstetrician | E18: Medical Specialist III | F18: Obstetrics-Gynecology Department | G18: Physician | H18: Medical Division | I18: 24 | J18: =LOOKUP(Table1[[#This Row],[SALARY GRADE]],{1,2,3,4,5,6,7,8,9,10,11,12,13,14,15,16,17,18,19,20,21,22,23,24,25,26,27,28,29,30,31,32,33},{14364,15522,16486,17506,18581,19716,20914,22423,24329,26917,31705,33947,36125,38764,42178,45694,49562,53818,59153,66052,73303,81796,91306,102603,116643,131807,148940,167129,187531,210718,300961,356237,449157}) -> 102603 | K18: 2nd | L18: =IF(Table1[[#This Row],[LAST]]="","Unfilled","Filled") -> Filled | M18: Ibañez | N18: Maria Girlie | O18: Jeresano | Q18: 24976 | R18: 42353 | S18: 44743 | T18: 45566 | U18: Married | V18: Female | W18: =DATEDIF(Q18,TODAY(),"Y") -> 58 | X18: =IF(ABS(Table1[[#This Row],[AGE]])>59,"60 and above",IF(ABS(Table1[[#This Row],[AGE]])>49,"50-59",IF(ABS(Table1[[#This Row],[AGE]])>39,"40-49",IF(ABS(Table1[[#This Row],[AGE]])>29,"30-39",IF(ABS(Table1[[#This Row],[AGE]])>19,"20-29",""))))) -> 50-59 | Y18: Gubat, Sorsogon | Z18: #6 (Block 7 Lot 24) San Pablo St., Pacita Complex 1 | AA18: Pacita 1 | AB18: San Pedro | AC18: Laguna | AD18: 4023 | AE18: Doctor of Medicine | AF18: Medicine | AG18: RA 1080 | AH18: 0085063 | AI18: 45795 | AJ18: 2004815670 | AK18: 1210-9536-3456 | AL18: 1904-8000-3652 | AM18: 283-378-620 | AN18: 0917-890-8767 | AO18: N/A | AP18: betangirl@yahoo.com
A19: 18 | B19: OSEC-DOHB-DENT4-270035-2022 | C19: Dentist IV | E19: Dentist IV | F19: Dental Department | G19: Dentist | H19: Medical Division | I19: 23 | J19: =LOOKUP(Table1[[#This Row],[SALARY GRADE]],{1,2,3,4,5,6,7,8,9,10,11,12,13,14,15,16,17,18,19,20,21,22,23,24,25,26,27,28,29,30,31,32,33},{14364,15522,16486,17506,18581,19716,20914,22423,24329,26917,31705,33947,36125,38764,42178,45694,49562,53818,59153,66052,73303,81796,91306,102603,116643,131807,148940,167129,187531,210718,300961,356237,449157}) -> 91306 | K19: 2nd | L19: =IF(Table1[[#This Row],[LAST]]="","Unfilled","Filled") -> Filled | M19: Rivera | N19: Marilou | O19: Fajardo | Q19: 23998 | R19: 37280 | S19: 44363 | T19: 45687 | U19: Married | V19: Female | W19: =DATEDIF(Q19,TODAY(),"Y") -> 60 | X19: =IF(ABS(Table1[[#This Row],[AGE]])>59,"60 and above",IF(ABS(Table1[[#This Row],[AGE]])>49,"50-59",IF(ABS(Table1[[#This Row],[AGE]])>39,"40-49",IF(ABS(Table1[[#This Row],[AGE]])>29,"30-39",IF(ABS(Table1[[#This Row],[AGE]])>19,"20-29",""))))) -> 60 and above | Y19: Alfonso, Cavite | Z19: 4 Rizal | AA19: III | AB19: Alfonso | AC19: Cavite | AD19: 1742 | AE19: Doctor of Dental Medicine | AF19: Dentistry | AG19: RA 1080 | AH19: 0029093 | AI19: 45913 | AJ19: 2001243333 | AK19: 1030-0008-0261 | AL19: 0802-5016-6617 | AM19: 134-549-420 | AN19: 0917-551-1365 | AO19: N/A | AP19: malufajardorivera@yahoo.com.ph
A20: 19 | B20: OSEC-DOHB-MDOF4-270012-2022 | C20: Medical Officer IV | D20: Anesthesiologist | E20: Medical Officer IV | F20: Anesthesiology Department | G20: Physician | H20: Medical Division | I20: 23 | J20: =LOOKUP(Table1[[#This Row],[SALARY GRADE]],{1,2,3,4,5,6,7,8,9,10,11,12,13,14,15,16,17,18,19,20,21,22,23,24,25,26,27,28,29,30,31,32,33},{14364,15522,16486,17506,18581,19716,20914,22423,24329,26917,31705,33947,36125,38764,42178,45694,49562,53818,59153,66052,73303,81796,91306,102603,116643,131807,148940,167129,187531,210718,300961,356237,449157}) -> 91306 | K20: 2nd | L20: =IF(Table1[[#This Row],[LAST]]="","Unfilled","Filled") -> Filled | M20: Lope | N20: Diana Jane | O20: Casugod | Q20: 31747 | R20: 44851 | S20: 44851 | T20: 44851 | U20: Single | V20: Female | W20: =DATEDIF(Q20,TODAY(),"Y") -> 39 | X20: =IF(ABS(Table1[[#This Row],[AGE]])>59,"60 and above",IF(ABS(Table1[[#This Row],[AGE]])>49,"50-59",IF(ABS(Table1[[#This Row],[AGE]])>39,"40-49",IF(ABS(Table1[[#This Row],[AGE]])>29,"30-39",IF(ABS(Table1[[#This Row],[AGE]])>19,"20-29",""))))) -> 30-39 | Y20: Manila | Z20: No. 189 Doña Alicia Subd. | AA20: Ligas I | AB20: Bacoor City | AC20: Cavite | AD20: 4102 | AE20: Doctor of Medicine | AF20: Medicine | AG20: RA 1080 | AH20: 0128043 | AI20: 46034 | AJ20: 2005345316 | AK20: 1212-1991-3690 | AL20: 0802-5423-0859 | AM20: 319-784-022 | AN20: 0977-835-2006 | AO20: N/A | AP20: dianajane.lope@gmail.com
A21: 20 | B21: OSEC-DOHB-MDOF4-270018-2020 | C21: Medical Officer IV | D21: Pediatrician | E21: Medical Officer IV | F21: Pediatrics Department | G21: Physician | H21: Medical Division | I21: 23 | J21: =LOOKUP(Table1[[#This Row],[SALARY GRADE]],{1,2,3,4,5,6,7,8,9,10,11,12,13,14,15,16,17,18,19,20,21,22,23,24,25,26,27,28,29,30,31,32,33},{14364,15522,16486,17506,18581,19716,20914,22423,24329,26917,31705,33947,36125,38764,42178,45694,49562,53818,59153,66052,73303,81796,91306,102603,116643,131807,148940,167129,187531,210718,300961,356237,449157}) -> 91306 | K21: 2nd | L21: =IF(Table1[[#This Row],[LAST]]="","Unfilled","Filled") -> Filled | M21: Bañaga | N21: Mara Joanna | O21: Palarca | Q21: 32602 | R21: 46092 | S21: 46092 | T21: 46092 | U21: Single | V21: Female | W21: =DATEDIF(Q21,TODAY(),"Y") -> 37 | X21: =IF(ABS(Table1[[#This Row],[AGE]])>59,"60 and above",IF(ABS(Table1[[#This Row],[AGE]])>49,"50-59",IF(ABS(Table1[[#This Row],[AGE]])>39,"40-49",IF(ABS(Table1[[#This Row],[AGE]])>29,"30-39",IF(ABS(Table1[[#This Row],[AGE]])>19,"20-29",""))))) -> 30-39 | Y21: Manila | Z21: #1 Tickling St., Novaville Subd. | AA21: 170 | AB21: Caloocan City | AC21: Metro Manila | AD21: 1400 | AE21: Doctor of Medicine | AF21: Medicine | AG21: RA 1080 | AH21: 0139666 | AI21: 46116 | AJ21: 2005539158 | AK21: 1212-4256-1527 | AL21: 0302-6266-2566 | AM21: 353-614-057 | AN21: 0998-317-512 | AO21: N/A | AP21: mara.banaga@gmail.com
A22: 21 | B22: OSEC-DOHB-MDOF4-270019-2020 | C22: Medical Officer IV | D22: General Practitioner | E22: Medical Officer IV | F22: Office of the Chief of Allied Health Professional | G22: Physician | H22: Medical Division | I22: 23 | J22: =LOOKUP(Table1[[#This Row],[SALARY GRADE]],{1,2,3,4,5,6,7,8,9,10,11,12,13,14,15,16,17,18,19,20,21,22,23,24,25,26,27,28,29,30,31,32,33},{14364,15522,16486,17506,18581,19716,20914,22423,24329,26917,31705,33947,36125,38764,42178,45694,49562,53818,59153,66052,73303,81796,91306,102603,116643,131807,148940,167129,187531,210718,300961,356237,449157}) -> 91306 | K22: 2nd | L22: =IF(Table1[[#This Row],[LAST]]="","Unfilled","Filled") -> Filled | M22: Gabuten | N22: Ana Maria Elena | O22: Quiros | Q22: 26768 | R22: 38257 | S22: 44383 | T22: 44383 | U22: Single | V22: Female | W22: =DATEDIF(Q22,TODAY(),"Y") -> 53 | X22: =IF(ABS(Table1[[#This Row],[AGE]])>59,"60 and above",IF(ABS(Table1[[#This Row],[AGE]])>49,"50-59",IF(ABS(Table1[[#This Row],[AGE]])>39,"40-49",IF(ABS(Table1[[#This Row],[AGE]])>29,"30-39",IF(ABS(Table1[[#This Row],[AGE]])>19,"20-29",""))))) -> 50-59 | Y22: Pasay City | Z22: 12 Camia St., De Castro Subd. | AA22: Sta. Lucia | AB22: Pasig City | AC22: NCR | AD22: 1600 | AE22: Doctor of Medicine | AF22: Medicine | AG22: RA 1080 | AH22: 0097502 | AI22: 46126 | AJ22: 2001397754 | AK22: 1030-0009-5145 | AL22: 0800-0064-8098 | AM22: 225-249-606 | AN22: 0915-254-7744 | AO22: (02) 788-1720 | AP22: amegabu10@yahoo.com
A23: 22 | B23: OSEC-DOHB-MDOF4-270020-2020 | C23: Medical Officer IV | D23: Surgeon | E23: Medical Officer IV | F23: Surgery Department | G23: Physician | H23: Medical Division | I23: 23 | J23: =LOOKUP(Table1[[#This Row],[SALARY GRADE]],{1,2,3,4,5,6,7,8,9,10,11,12,13,14,15,16,17,18,19,20,21,22,23,24,25,26,27,28,29,30,31,32,33},{14364,15522,16486,17506,18581,19716,20914,22423,24329,26917,31705,33947,36125,38764,42178,45694,49562,53818,59153,66052,73303,81796,91306,102603,116643,131807,148940,167129,187531,210718,300961,356237,449157}) -> 91306 | K23: 2nd | L23: =IF(Table1[[#This Row],[LAST]]="","Unfilled","Filled") -> Filled | M23: Mendoza | N23: Hazel | O23: Alarcon | Q23: 32833 | R23: 44960 | S23: 44960 | T23: 44960 | U23: Single | V23: Female | W23: =DATEDIF(Q23,TODAY(),"Y") -> 36 | X23: =IF(ABS(Table1[[#This Row],[AGE]])>59,"60 and above",IF(ABS(Table1[[#This Row],[AGE]])>49,"50-59",IF(ABS(Table1[[#This Row],[AGE]])>39,"40-49",IF(ABS(Table1[[#This Row],[AGE]])>29,"30-39",IF(ABS(Table1[[#This Row],[AGE]])>19,"20-29",""))))) -> 30-39 | Y23: Quezon City | Z23: 150 Proverb Vina Village | AA23: Poblacion IV-D | AB23: Imus City | AC23: Cavite | AD23: 4103 | AE23: Doctor of Medicine | AF23: Medicine | AG23: RA 1080 | AH23: 0128427 | AI23: 46712 | AJ23: 2004703711 | AK23: 1211-8041-3237 | AL23: 2100-0019-7542 | AM23: 462-469-085 | AN23: 0917-829-2594 | AO23: N/A | AP23: dochazelmendoza@gmail.com
A24: 23 | B24: OSEC-DOHB-MDOF4-270021-2020 | C24: Medical Officer IV | D24: Internist | E24: Medical Officer IV | F24: Internal Medicine Department | G24: Physician | H24: Medical Division | I24: 23 | J24: =LOOKUP(Table1[[#This Row],[SALARY GRADE]],{1,2,3,4,5,6,7,8,9,10,11,12,13,14,15,16,17,18,19,20,21,22,23,24,25,26,27,28,29,30,31,32,33},{14364,15522,16486,17506,18581,19716,20914,22423,24329,26917,31705,33947,36125,38764,42178,45694,49562,53818,59153,66052,73303,81796,91306,102603,116643,131807,148940,167129,187531,210718,300961,356237,449157}) -> 91306 | K24: 2nd | L24: =IF(Table1[[#This Row],[LAST]]="","Unfilled","Filled") -> Filled | M24: Pereyra-Borlongan | N24: Maria Yña Eluisia | O24: Tomagan | Q24: 32091 | R24: 45019 | S24: 45019 | T24: 45474 | U24: Married | V24: Female | W24: =DATEDIF(Q24,TODAY(),"Y") -> 38 | X24: =IF(ABS(Table1[[#This Row],[AGE]])>59,"60 and above",IF(ABS(Table1[[#This Row],[AGE]])>49,"50-59",IF(ABS(Table1[[#This Row],[AGE]])>39,"40-49",IF(ABS(Table1[[#This Row],[AGE]])>29,"30-39",IF(ABS(Table1[[#This Row],[AGE]])>19,"20-29",""))))) -> 30-39 | Y24: Manila | Z24: Unit 1215 Astra Bldg., Pasig Blvd., Prisma Residences | AA24: Bagong Ilog | AB24: Pasig City | AC24: Metro Manila | AD24: 1600 | AE24: Doctor of Medicine | AF24: Medicine | AG24: RA 1080 | AH24: 0129486 | AI24: 46671 | AJ24: 2005559346 | AK24: 1211-6083-4915 | AL24: 0102-5429-9338 | AM24: 319-221-335 | AN24: 0968-854-6080 | AO24: N/A | AP24: ynapereyra@gmail.com
A25: 24 | B25: OSEC-DOHB-MDOF4-270022-2020 | C25: Medical Officer IV | D25: Emergency Med | E25: Medical Officer IV | F25: Emergency Medicine Department | G25: Physician | H25: Medical Division | I25: 23 | J25: =LOOKUP(Table1[[#This Row],[SALARY GRADE]],{1,2,3,4,5,6,7,8,9,10,11,12,13,14,15,16,17,18,19,20,21,22,23,24,25,26,27,28,29,30,31,32,33},{14364,15522,16486,17506,18581,19716,20914,22423,24329,26917,31705,33947,36125,38764,42178,45694,49562,53818,59153,66052,73303,81796,91306,102603,116643,131807,148940,167129,187531,210718,300961,356237,449157}) -> 91306 | K25: 2nd | L25: =IF(Table1[[#This Row],[LAST]]="","Unfilled","Filled") -> Filled | M25: Sarrosa | N25: Noel Angelo | O25: Solidor | Q25: 35362 | R25: 45540 | S25: 45540 | T25: 45540 | U25: Single | V25: Male | W25: =DATEDIF(Q25,TODAY(),"Y") -> 29 | X25: =IF(ABS(Table1[[#This Row],[AGE]])>59,"60 and above",IF(ABS(Table1[[#This Row],[AGE]])>49,"50-59",IF(ABS(Table1[[#This Row],[AGE]])>39,"40-49",IF(ABS(Table1[[#This Row],[AGE]])>29,"30-39",IF(ABS(Table1[[#This Row],[AGE]])>19,"20-29",""))))) -> 20-29 | Y25: Makati City | Z25: Block 70 Lot 6 Criselda Cecilio St., Classic I, BF Resort Village | AA25: Talon Dos | AB25: Las Piñas City | AC25: NCR | AD25: 1747 | AE25: Doctor of Medicine | AF25: Medicine | AG25: RA 1080 | AH25: 0150829 | AI25: 46319 | AJ25: 2005870559 | AK25: 1212-7664-7248 | AL25: 0125-0135-9457 | AM25: 501-164-235 | AN25: 0917-712-8054 | AO25: (02) 8873-4561 | AP25: noelsarrosa@gmail.com
A26: 25 | B26: OSEC-DOHB-MDSP2-270010-2022 | C26: Medical Specialist II (Internist) | D26: Internist | E26: Medical Specialist II | F26: Internal Medicine Department | G26: Physician | H26: Medical Division | I26: 23 | J26: =LOOKUP(Table1[[#This Row],[SALARY GRADE]],{1,2,3,4,5,6,7,8,9,10,11,12,13,14,15,16,17,18,19,20,21,22,23,24,25,26,27,28,29,30,31,32,33},{14364,15522,16486,17506,18581,19716,20914,22423,24329,26917,31705,33947,36125,38764,42178,45694,49562,53818,59153,66052,73303,81796,91306,102603,116643,131807,148940,167129,187531,210718,300961,356237,449157}) -> 91306 | K26: 2nd | L26: =IF(Table1[[#This Row],[LAST]]="","Unfilled","Filled") -> Filled | M26: Berenguer | N26: Joe Vincent | O26: Villa | Q26: 32099 | R26: 44363 | S26: 44363 | T26: 45306 | U26: Married | V26: Male | W26: =DATEDIF(Q26,TODAY(),"Y") -> 38 | X26: =IF(ABS(Table1[[#This Row],[AGE]])>59,"60 and above",IF(ABS(Table1[[#This Row],[AGE]])>49,"50-59",IF(ABS(Table1[[#This Row],[AGE]])>39,"40-49",IF(ABS(Table1[[#This Row],[AGE]])>29,"30-39",IF(ABS(Table1[[#This Row],[AGE]])>19,"20-29",""))))) -> 30-39 | Y26: Tacloban City, Leyte | Z26: B1 L7 Miller St., Southville Settings Nuvali | AA26: Canlubang | AB26: Calamba City | AC26: Laguna | AD26: 4028 | AE26: Doctor of Medicine | AF26: Medicine | AG26: RA 1080 | AH26: 0127917 | AI26: 46344 | AJ26: 2004652332 | AK26: 1211-3691-3428 | AL26: 0300-0276-6864 | AM26: 270-794-389 | AN26: 0917-117-6574 | AO26: N/A | AP26: joevincentberenguer@gmail.com
A27: 26 | B27: OSEC-DOHB-MDSP2-270011-2022 | C27: Medical Specialist II (Anesthesiologist) | D27: Anesthesiologist | E27: Medical Specialist II | F27: Anesthesiology Department | G27: Physician | H27: Medical Division | I27: 23 | J27: =LOOKUP(Table1[[#This Row],[SALARY GRADE]],{1,2,3,4,5,6,7,8,9,10,11,12,13,14,15,16,17,18,19,20,21,22,23,24,25,26,27,28,29,30,31,32,33},{14364,15522,16486,17506,18581,19716,20914,22423,24329,26917,31705,33947,36125,38764,42178,45694,49562,53818,59153,66052,73303,81796,91306,102603,116643,131807,148940,167129,187531,210718,300961,356237,449157}) -> 91306 | K27: 2nd | L27: =IF(Table1[[#This Row],[LAST]]="","Unfilled","Filled") -> Filled | M27: Garcia | N27: Yves Kristine | O27: Ginete | Q27: 33216 | R27: 45604 | S27: 45604 | T27: 45604 | U27: Single | V27: Female | W27: =DATEDIF(Q27,TODAY(),"Y") -> 35 | X27: =IF(ABS(Table1[[#This Row],[AGE]])>59,"60 and above",IF(ABS(Table1[[#This Row],[AGE]])>49,"50-59",IF(ABS(Table1[[#This Row],[AGE]])>39,"40-49",IF(ABS(Table1[[#This Row],[AGE]])>29,"30-39",IF(ABS(Table1[[#This Row],[AGE]])>19,"20-29",""))))) -> 30-39 | Y27: Quezon City | Z27: 3218 Manila Residence Bocobo, 1160, Jorge Bocobo St., Ermita | AA27: Brgy. 670 | AB27: Manila City | AC27: Metro Manila | AD27: 1000 | AE27: Doctor of Medicine | AF27: Medicine | AG27: RA 1080 | AH27: 0137208 | AI27: 46365 | AJ27: 2005577217 | AK27: 1212-4017-2424 | AL27: 0102-5746-7274 | AM27: 709-686-643 | AN27: 0926-740-0820 | AO27: N/A | AP27: yvesgarcia@gmail.com
A28: 27 | B28: OSEC-DOHB-MDSP2-270012-2020 | C28: Medical Specialist II (Radiologist) | D28: Radiologist | E28: Medical Specialist II | F28: Radiology Department | G28: Physician | H28: Medical Division | I28: 23 | J28: =LOOKUP(Table1[[#This Row],[SALARY GRADE]],{1,2,3,4,5,6,7,8,9,10,11,12,13,14,15,16,17,18,19,20,21,22,23,24,25,26,27,28,29,30,31,32,33},{14364,15522,16486,17506,18581,19716,20914,22423,24329,26917,31705,33947,36125,38764,42178,45694,49562,53818,59153,66052,73303,81796,91306,102603,116643,131807,148940,167129,187531,210718,300961,356237,449157}) -> 91306 | K28: 2nd | L28: =IF(Table1[[#This Row],[LAST]]="","Unfilled","Filled") -> Filled | M28: Gacutan | N28: Rico | O28: Vasquez | Q28: 26762 | R28: 42618 | S28: 44424 | T28: 44424 | U28: Married | V28: Male | W28: =DATEDIF(Q28,TODAY(),"Y") -> 53 | X28: =IF(ABS(Table1[[#This Row],[AGE]])>59,"60 and above",IF(ABS(Table1[[#This Row],[AGE]])>49,"50-59",IF(ABS(Table1[[#This Row],[AGE]])>39,"40-49",IF(ABS(Table1[[#This Row],[AGE]])>29,"30-39",IF(ABS(Table1[[#This Row],[AGE]])>19,"20-29",""))))) -> 50-59 | Y28: Balanga City, Bataan | Z28: B8 L10 Rainforest St., Sunnycrest Village | AA28: Salitran II | AB28: Dasmariñas City | AC28: Cavite | AD28: 4114 | AE28: Doctor of Medicine | AF28: Medicine | AG28: RA 1080 | AH28: 0091411 | AI28: 46120 | AJ28: 2001121167 | AK28: 0031-0619-9701 | AL28: 0300-0200-9761 | AM28: 204-658-622 | AN28: 0920-927-4763 | AO28: N/A | AP28: coricsmd@yahoo.com
A29: 28 | B29: OSEC-DOHB-MDSP2-270012-2022 | C29: Medical Specialist II (Surgeon) | D29: Surgeon | E29: Medical Specialist II | F29: Surgery Department | G29: Physician | H29: Medical Division | I29: 23 | J29: =LOOKUP(Table1[[#This Row],[SALARY GRADE]],{1,2,3,4,5,6,7,8,9,10,11,12,13,14,15,16,17,18,19,20,21,22,23,24,25,26,27,28,29,30,31,32,33},{14364,15522,16486,17506,18581,19716,20914,22423,24329,26917,31705,33947,36125,38764,42178,45694,49562,53818,59153,66052,73303,81796,91306,102603,116643,131807,148940,167129,187531,210718,300961,356237,449157}) -> 91306 | K29: 2nd | L29: =IF(Table1[[#This Row],[LAST]]="","Unfilled","Filled") -> Filled | M29: Balmores | N29: Bob | O29: Caranico | Q29: 32279 | R29: 45083 | S29: 45083 | T29: 45083 | U29: Married | V29: Male | W29: =DATEDIF(Q29,TODAY(),"Y") -> 38 | X29: =IF(ABS(Table1[[#This Row],[AGE]])>59,"60 and above",IF(ABS(Table1[[#This Row],[AGE]])>49,"50-59",IF(ABS(Table1[[#This Row],[AGE]])>39,"40-49",IF(ABS(Table1[[#This Row],[AGE]])>29,"30-39",IF(ABS(Table1[[#This Row],[AGE]])>19,"20-29",""))))) -> 30-39 | Y29: General Santos City | Z29: 24 Maganda JS Ville | AA29: Dulong Bayan | AB29: Bacoor City | AC29: Cavite | AD29: 4102 | AE29: Doctor of Medicine | AF29: Medicine | AG29: RA 1080 | AH29: 0127248 | AI29: 45793 | AJ29: 2006333495 | AK29: 1212-7075-6275 | AL29: 0202-5113-4597 | AM29: 251-101-824 | AN29: 0945-677-7061 | AO29: (046) 434-4680 | AP29: bcbalmores14@gmail.com
A30: 29 | B30: OSEC-DOHB-MDSP2-270013-2020 | C30: Medical Specialist II (Pediatrician) | D30: Pediatrician | E30: Medical Specialist II | F30: Pediatrics Department | G30: Physician | H30: Medical Division | I30: 23 | J30: =LOOKUP(Table1[[#This Row],[SALARY GRADE]],{1,2,3,4,5,6,7,8,9,10,11,12,13,14,15,16,17,18,19,20,21,22,23,24,25,26,27,28,29,30,31,32,33},{14364,15522,16486,17506,18581,19716,20914,22423,24329,26917,31705,33947,36125,38764,42178,45694,49562,53818,59153,66052,73303,81796,91306,102603,116643,131807,148940,167129,187531,210718,300961,356237,449157}) -> 91306 | K30: 2nd | L30: =IF(Table1[[#This Row],[LAST]]="","Unfilled","Filled") -> Filled | M30: Alfonso-Tebelin | N30: Roda | O30: Alfonso | Q30: 29831 | R30: 42401 | S30: 44383 | T30: 44383 | U30: Married | V30: Female | W30: =DATEDIF(Q30,TODAY(),"Y") -> 44 | X30: =IF(ABS(Table1[[#This Row],[AGE]])>59,"60 and above",IF(ABS(Table1[[#This Row],[AGE]])>49,"50-59",IF(ABS(Table1[[#This Row],[AGE]])>39,"40-49",IF(ABS(Table1[[#This Row],[AGE]])>29,"30-39",IF(ABS(Table1[[#This Row],[AGE]])>19,"20-29",""))))) -> 40-49 | Y30: Cavite City | Z30: 774 Crescini Ext., San Antonio | AA30: 49-M | AB30: Cavite City | AC30: Cavite | AD30: 4100 | AE30: Doctor of Medicine | AF30: Medicine | AG30: RA 1080 | AH30: 0111056 | AI30: 45902 | AJ30: 2004867482 | AK30: 1211-0250-0561 | AL30: 0802-5247-5870 | AM30: 221-602-851 | AN30: 0997-761-8145 | AO30: (046) 851-5258 | AP30: hapiroda@gmail.com
A31: 30 | B31: OSEC-DOHB-MDSP2-270013-2022 | C31: Medical Specialist II (Pathologist) | D31: Pathologist | E31: Medical Specialist II | F31: Obstetrics-Gynecology Department | G31: Physician | H31: Medical Division | I31: 23 | J31: =LOOKUP(Table1[[#This Row],[SALARY GRADE]],{1,2,3,4,5,6,7,8,9,10,11,12,13,14,15,16,17,18,19,20,21,22,23,24,25,26,27,28,29,30,31,32,33},{14364,15522,16486,17506,18581,19716,20914,22423,24329,26917,31705,33947,36125,38764,42178,45694,49562,53818,59153,66052,73303,81796,91306,102603,116643,131807,148940,167129,187531,210718,300961,356237,449157}) -> 91306 | K31: 2nd | L31: =IF(Table1[[#This Row],[LAST]]="","Unfilled","Filled") -> Filled | M31: Blanco | N31: Renzton | O31: Paras | Q31: 33783 | R31: 45523 | S31: 45523 | T31: 45523 | U31: Married | V31: Male | W31: =DATEDIF(Q31,TODAY(),"Y") -> 34 | X31: =IF(ABS(Table1[[#This Row],[AGE]])>59,"60 and above",IF(ABS(Table1[[#This Row],[AGE]])>49,"50-59",IF(ABS(Table1[[#This Row],[AGE]])>39,"40-49",IF(ABS(Table1[[#This Row],[AGE]])>29,"30-39",IF(ABS(Table1[[#This Row],[AGE]])>19,"20-29",""))))) -> 30-39 | Y31: Tanza, Cavite | Z31: 426 Tramo Kanluran St. | AA31: Halayhay | AB31: Tanza | AC31: Cavite | AD31: 4108 | AE31: Doctor of Medicine | AF31: Medicine | AG31: RA 1080 | AH31: 0138567 | AI31: 46201 | AJ31: 2005732172 | AK31: 1212-6440-7292 | AL31: 0825-0846-9949 | AM31: 273-253-736 | AN31: 0939-919-9315 | AO31: (046) 481-8745 | AP31: blancorenzton@gmail.com
A32: 31 | B32: OSEC-DOHB-MDSP2-270014-2022 | C32: Medical Specialist II (Obstretician) | D32: Obstetrician | E32: Medical Specialist II | F32: Obstetrics-Gynecology Department | G32: Physician | H32: Medical Division | I32: 23 | J32: =LOOKUP(Table1[[#This Row],[SALARY GRADE]],{1,2,3,4,5,6,7,8,9,10,11,12,13,14,15,16,17,18,19,20,21,22,23,24,25,26,27,28,29,30,31,32,33},{14364,15522,16486,17506,18581,19716,20914,22423,24329,26917,31705,33947,36125,38764,42178,45694,49562,53818,59153,66052,73303,81796,91306,102603,116643,131807,148940,167129,187531,210718,300961,356237,449157}) -> 91306 | K32: 2nd | L32: =IF(Table1[[#This Row],[LAST]]="","Unfilled","Filled") -> Filled | M32: Ramos-Atanacio | N32: Clarisa | O32: Murillo | Q32: 31539 | R32: 44950 | S32: 44950 | T32: 45301 | U32: Married | V32: Female | W32: =DATEDIF(Q32,TODAY(),"Y") -> 40 | X32: =IF(ABS(Table1[[#This Row],[AGE]])>59,"60 and above",IF(ABS(Table1[[#This Row],[AGE]])>49,"50-59",IF(ABS(Table1[[#This Row],[AGE]])>39,"40-49",IF(ABS(Table1[[#This Row],[AGE]])>29,"30-39",IF(ABS(Table1[[#This Row],[AGE]])>19,"20-29",""))))) -> 40-49 | Y32: Metro Manila | Z32: #16 Jerusalem St. BF Aratiles | AA32: BF Homes | AB32: Parañaque City | AC32: Manila | AD32: 1720 | AE32: Doctor of Medicine | AF32: Medicine | AG32: RA 1080 | AH32: 0134334 | AI32: 45784 | AJ32: 2005157235 | AK32: 1211-8827-1699 | AL32: 0105-0687-7127 | AM32: 275-508-750 | AN32: 0917-584-2686 | AO32: (02) 8644-2757 | AP32: clarisaramos86@gmail.com
A33: 32 | B33: OSEC-DOHB-MDSP2-270014-2020 | C33: Medical Specialist II (Internist) | D33: Internist | E33: Medical Specialist II | F33: Internal Medicine Department | G33: Physician | H33: Medical Division | I33: 23 | J33: =LOOKUP(Table1[[#This Row],[SALARY GRADE]],{1,2,3,4,5,6,7,8,9,10,11,12,13,14,15,16,17,18,19,20,21,22,23,24,25,26,27,28,29,30,31,32,33},{14364,15522,16486,17506,18581,19716,20914,22423,24329,26917,31705,33947,36125,38764,42178,45694,49562,53818,59153,66052,73303,81796,91306,102603,116643,131807,148940,167129,187531,210718,300961,356237,449157}) -> 91306 | K33: 2nd | L33: =IF(Table1[[#This Row],[LAST]]="","Unfilled","Filled") -> Filled | M33: Co | N33: Paul Bernard Bryant | O33: Ng | Q33: 29651 | R33: 44907 | S33: 44907 | T33: 44907 | U33: Married | V33: Male | W33: =DATEDIF(Q33,TODAY(),"Y") -> 45 | X33: =IF(ABS(Table1[[#This Row],[AGE]])>59,"60 and above",IF(ABS(Table1[[#This Row],[AGE]])>49,"50-59",IF(ABS(Table1[[#This Row],[AGE]])>39,"40-49",IF(ABS(Table1[[#This Row],[AGE]])>29,"30-39",IF(ABS(Table1[[#This Row],[AGE]])>19,"20-29",""))))) -> 40-49 | Y33: Manila | Z33: B5 L4 Phase 2, Sunshine Homes | AA33: Francisco de Castro | AB33: GMA | AC33: Cavite | AD33: 4117 | AE33: Doctor of Medicine | AF33: Medicine | AG33: RA 1080 | AH33: 0113425 | AI33: 46544 | AJ33: 2004172400 | AK33: 1211-1373-8037 | AL33: 1202-2255-8330 | AM33: 265-879-165 | AN33: 0969-211-0187 | AO33: N/A | AP33: pbbnco@gmail.com
A34: 33 | B34: OSEC-DOHB-MDSP2-270015-2020 | C34: Medical Specialist II (Anesthesiologist) | D34: Anesthesiologist | E34: Medical Specialist II | F34: Anesthesiology Department | G34: Physician | H34: Medical Division | I34: 23 | J34: =LOOKUP(Table1[[#This Row],[SALARY GRADE]],{1,2,3,4,5,6,7,8,9,10,11,12,13,14,15,16,17,18,19,20,21,22,23,24,25,26,27,28,29,30,31,32,33},{14364,15522,16486,17506,18581,19716,20914,22423,24329,26917,31705,33947,36125,38764,42178,45694,49562,53818,59153,66052,73303,81796,91306,102603,116643,131807,148940,167129,187531,210718,300961,356237,449157}) -> 91306 | K34: 2nd | L34: =IF(Table1[[#This Row],[LAST]]="","Unfilled","Filled") -> Filled | M34: Valenzuela | N34: Jona-Patricia | O34: Ravelo | Q34: 33076 | R34: 46113 | S34: 46113 | T34: 46113 | U34: Married | V34: Female | W34: =DATEDIF(Q34,TODAY(),"Y") -> 36 | X34: =IF(ABS(Table1[[#This Row],[AGE]])>59,"60 and above",IF(ABS(Table1[[#This Row],[AGE]])>49,"50-59",IF(ABS(Table1[[#This Row],[AGE]])>39,"40-49",IF(ABS(Table1[[#This Row],[AGE]])>29,"30-39",IF(ABS(Table1[[#This Row],[AGE]])>19,"20-29",""))))) -> 30-39 | Y34: Mandaluyong City, Metro Manila | Z34: 2628 Arellano Avenue | AA34: Brgy. 765, Sta. Ana | AB34: Manila City | AC34: Metro Manila | AD34: 1009 | AE34: Doctor of Medicine | AF34: Medicine | AG34: RA 1080 | AH34: 0144265 | AI34: 46590 | AJ34: N/A | AK34: 1210-2231-4651 | AL34: 0205-8033-9624 | AM34: 419-851-139 | AN34: 0927-217-0820 | AO34: N/A | AP34: jpfravelo@gmail.com
A35: 34 | B35: OSEC-DOHB-MDSP2-270016-2020 | C35: Medical Specialist II (Surgeon) | D35: Surgeon | E35: Medical Specialist II | F35: Surgery Department | G35: Physician | H35: Medical Division | I35: 23 | J35: =LOOKUP(Table1[[#This Row],[SALARY GRADE]],{1,2,3,4,5,6,7,8,9,10,11,12,13,14,15,16,17,18,19,20,21,22,23,24,25,26,27,28,29,30,31,32,33},{14364,15522,16486,17506,18581,19716,20914,22423,24329,26917,31705,33947,36125,38764,42178,45694,49562,53818,59153,66052,73303,81796,91306,102603,116643,131807,148940,167129,187531,210718,300961,356237,449157}) -> 91306 | K35: 2nd | L35: =IF(Table1[[#This Row],[LAST]]="","Unfilled","Filled") -> Filled | M35: Hernandez-Roa | N35: Gerlie | O35: Ocampo | Q35: 31595 | R35: 44960 | S35: 44960 | T35: 44960 | U35: Married | V35: Female | W35: =DATEDIF(Q35,TODAY(),"Y") -> 40 | X35: =IF(ABS(Table1[[#This Row],[AGE]])>59,"60 and above",IF(ABS(Table1[[#This Row],[AGE]])>49,"50-59",IF(ABS(Table1[[#This Row],[AGE]])>39,"40-49",IF(ABS(Table1[[#This Row],[AGE]])>29,"30-39",IF(ABS(Table1[[#This Row],[AGE]])>19,"20-29",""))))) -> 40-49 | Y35: Cavite City | Z35: 51 Antioch Remeville | AA35: Magdiwang | AB35: Noveleta | AC35: Cavite | AD35: 4105 | AE35: Doctor of Medicine | AF35: Medicine | AG35: RA 1080 | AH35: 0127428 | AI35: 46205 | AJ35: 2004921701 | AK35: 1211-8923-0589 | AL35: 0805-0834-5552 | AM35: 287-610-993 | AN35: 0968-366-5442 | AO35: N/A | AP35: gerlmd1216@gmail.com
A36: 35 | B36: OSEC-DOHB-MDSP2-270017-2020 | C36: Medical Specialist II (Obstretician) | D36: Obstetrician | E36: Medical Specialist II | F36: Obstetrics-Gynecology Department | G36: Physician | H36: Medical Division | I36: 23 | J36: =LOOKUP(Table1[[#This Row],[SALARY GRADE]],{1,2,3,4,5,6,7,8,9,10,11,12,13,14,15,16,17,18,19,20,21,22,23,24,25,26,27,28,29,30,31,32,33},{14364,15522,16486,17506,18581,19716,20914,22423,24329,26917,31705,33947,36125,38764,42178,45694,49562,53818,59153,66052,73303,81796,91306,102603,116643,131807,148940,167129,187531,210718,300961,356237,449157}) -> 91306 | K36: 2nd | L36: =IF(Table1[[#This Row],[LAST]]="","Unfilled","Filled") -> Filled | M36: Montaña | N36: Justine Erika | O36: Tan | Q36: 32560 | R36: 45701 | S36: 45701 | T36: 45701 | U36: Single | V36: Female | W36: =DATEDIF(Q36,TODAY(),"Y") -> 37 | X36: =IF(ABS(Table1[[#This Row],[AGE]])>59,"60 and above",IF(ABS(Table1[[#This Row],[AGE]])>49,"50-59",IF(ABS(Table1[[#This Row],[AGE]])>39,"40-49",IF(ABS(Table1[[#This Row],[AGE]])>29,"30-39",IF(ABS(Table1[[#This Row],[AGE]])>19,"20-29",""))))) -> 30-39 | Y36: Manila | Z36: Block 2 Lot 49 F. Chioco Granwood Villas | AA36: Holy Spirit | AB36: Quezon City | AC36: Metro Manila | AD36: 1127 | AE36: Doctor of Medicine | AF36: Medicine | AG36: RA 1080 | AH36: 0136002 | AI36: 46074 | AJ36: 2005343648 | AK36: 1212-1557-8448 | AL36: 0202-5656-2139 | AM36: 476-358-638 | AN36: 0917-624-9370 | AO36: 516-1603 | AP36: justineerikamontana0221@gmail.com
A37: 36 | B37: OSEC-DOHB-MDSP2-270015-2022 | C37: Medical Specialist II (OPD) | D37: Family Medicine | E37: Medical Specialist II | F37: Outpatient Department | G37: Physician | H37: Medical Division | I37: 23 | J37: =LOOKUP(Table1[[#This Row],[SALARY GRADE]],{1,2,3,4,5,6,7,8,9,10,11,12,13,14,15,16,17,18,19,20,21,22,23,24,25,26,27,28,29,30,31,32,33},{14364,15522,16486,17506,18581,19716,20914,22423,24329,26917,31705,33947,36125,38764,42178,45694,49562,53818,59153,66052,73303,81796,91306,102603,116643,131807,148940,167129,187531,210718,300961,356237,449157}) -> 91306 | K37: 2nd | L37: =IF(Table1[[#This Row],[LAST]]="","Unfilled","Filled") -> Filled | M37: Bingco | O37: Vice Supetran, Resigned
A38: 37 | B38: OSEC-DOHB-NUR6-270011-2020 | C38: Nurse VI | E38: Nurse VI | F38: Office of the Chief Nurse | G38: Nurse | H38: Nursing Division | I38: 22 | J38: =LOOKUP(Table1[[#This Row],[SALARY GRADE]],{1,2,3,4,5,6,7,8,9,10,11,12,13,14,15,16,17,18,19,20,21,22,23,24,25,26,27,28,29,30,31,32,33},{14364,15522,16486,17506,18581,19716,20914,22423,24329,26917,31705,33947,36125,38764,42178,45694,49562,53818,59153,66052,73303,81796,91306,102603,116643,131807,148940,167129,187531,210718,300961,356237,449157}) -> 81796 | K38: 2nd | L38: =IF(Table1[[#This Row],[LAST]]="","Unfilled","Filled") -> Filled | M38: Atmosfera | N38: Jonathan | O38: Trinidad | Q38: 30493 | R38: 39449 | S38: 44348 | T38: 46065 | U38: Married | V38: Male | W38: =DATEDIF(Q38,TODAY(),"Y") -> 43 | X38: =IF(ABS(Table1[[#This Row],[AGE]])>59,"60 and above",IF(ABS(Table1[[#This Row],[AGE]])>49,"50-59",IF(ABS(Table1[[#This Row],[AGE]])>39,"40-49",IF(ABS(Table1[[#This Row],[AGE]])>29,"30-39",IF(ABS(Table1[[#This Row],[AGE]])>19,"20-29",""))))) -> 40-49 | Y38: Dasmariñas City, Cavite | Z38: #3 Medina Ville | AA38: San Jose | AB38: Dasmariñas City | AC38: Cavite | AD38: 4114 | AE38: College Graduate | AF38: BS Nursing | AG38: RA 1080 | AH38: 0429365 | AI38: 45834 | AJ38: 2003464775 | AK38: 1030-0107-5387 | AL38: 0800-0111-6103 | AM38: 261-262-502 | AN38: 0999-575-3374 | AO38: N/A | AP38: atmosferajonathan@yahoo.com
A39: 38 | B39: OSEC-DOHB-SADOF-270010-2020 | C39: Supervising Administrative Officer | E39: Supervising Administrative Officer | F39: Office of the Supervising Administrative Officer | G39: Administrative Officer | H39: Hospital Operation and Patient Support Division | I39: 22 | J39: =LOOKUP(Table1[[#This Row],[SALARY GRADE]],{1,2,3,4,5,6,7,8,9,10,11,12,13,14,15,16,17,18,19,20,21,22,23,24,25,26,27,28,29,30,31,32,33},{14364,15522,16486,17506,18581,19716,20914,22423,24329,26917,31705,33947,36125,38764,42178,45694,49562,53818,59153,66052,73303,81796,91306,102603,116643,131807,148940,167129,187531,210718,300961,356237,449157}) -> 81796 | K39: 2nd | L39: =IF(Table1[[#This Row],[LAST]]="","Unfilled","Filled") -> Filled | M39: Gejon | N39: Allyn | O39: Matalubos | Q39: 27998 | R39: 37074 | S39: 38642 | T39: 44320 | U39: Married | V39: Female | W39: =DATEDIF(Q39,TODAY(),"Y") -> 49 | X39: =IF(ABS(Table1[[#This Row],[AGE]])>59,"60 and above",IF(ABS(Table1[[#This Row],[AGE]])>49,"50-59",IF(ABS(Table1[[#This Row],[AGE]])>39,"40-49",IF(ABS(Table1[[#This Row],[AGE]])>29,"30-39",IF(ABS(Table1[[#This Row],[AGE]])>19,"20-29",""))))) -> 40-49 | Y39: Pigcawayan, N. Cotabato | Z39: B N.17 L9 | AA39: Immanuel I | AB39: Dasmariñas City | AC39: Cavite | AD39: 4114 | AE39: Master's Degree | AF39: Master's in Management | AG39: CSC - Professional | AH39: N/A | AI39: N/A | AJ39: 2001157315 | AK39: 0080-8284-2007 | AL39: 1900-0608-1295 | AM39: 914-330-684 | AN39: 0905-573-0153 | AO39: N/A | AP39: agejon@yahoo.com
A40: 39 | B40: OSEC-DOHB-MDOF3-270003-2020 | C40: Medical Officer III (Pedia) | D40: Pediatrician | E40: Medical Officer III | F40: Pediatrics Department | G40: Physician | H40: Medical Division | I40: 21 | J40: =LOOKUP(Table1[[#This Row],[SALARY GRADE]],{1,2,3,4,5,6,7,8,9,10,11,12,13,14,15,16,17,18,19,20,21,22,23,24,25,26,27,28,29,30,31,32,33},{14364,15522,16486,17506,18581,19716,20914,22423,24329,26917,31705,33947,36125,38764,42178,45694,49562,53818,59153,66052,73303,81796,91306,102603,116643,131807,148940,167129,187531,210718,300961,356237,449157}) -> 73303 | K40: 2nd | L40: =IF(Table1[[#This Row],[LAST]]="","Unfilled","Filled") -> Filled | M40: Barron | N40: Emmanuel John | O40: Valenzuela | Q40: 32455 | R40: 45663 | S40: 45663 | T40: 45663 | U40: Single | V40: Male | W40: =DATEDIF(Q40,TODAY(),"Y") -> 37 | X40: =IF(ABS(Table1[[#This Row],[AGE]])>59,"60 and above",IF(ABS(Table1[[#This Row],[AGE]])>49,"50-59",IF(ABS(Table1[[#This Row],[AGE]])>39,"40-49",IF(ABS(Table1[[#This Row],[AGE]])>29,"30-39",IF(ABS(Table1[[#This Row],[AGE]])>19,"20-29",""))))) -> 30-39 | Y40: Lipa City, Batangas | Z40: Block 11, Lot 74 Via Mantua, Ponticelli 1 Subdivision | AA40: Molino III | AB40: Bacoor City | AC40: Cavite | AD40: 4102 | AE40: Doctor of Medicine | AF40: Medicine | AG40: RA 1080 | AH40: 0130601 | AI40: 46699 | AJ40: 2004973679 | AK40: 1211-8412-5957 | AL40: 0900-0094-9581 | AM40: 464-909-385 | AN40: 0933-826-2997 | AO40: N/A | AP40: barron_ej@yahoo.com
A41: 40 | B41: OSEC-DOHB-MDOF3-270004-2020 | C41: Medical Officer III (ER) | D41: Emergency Med | E41: Medical Officer III | F41: Emergency Medicine Department | G41: Physician | H41: Medical Division | I41: 21 | J41: =LOOKUP(Table1[[#This Row],[SALARY GRADE]],{1,2,3,4,5,6,7,8,9,10,11,12,13,14,15,16,17,18,19,20,21,22,23,24,25,26,27,28,29,30,31,32,33},{14364,15522,16486,17506,18581,19716,20914,22423,24329,26917,31705,33947,36125,38764,42178,45694,49562,53818,59153,66052,73303,81796,91306,102603,116643,131807,148940,167129,187531,210718,300961,356237,449157}) -> 73303 | K41: 2nd | L41: =IF(Table1[[#This Row],[LAST]]="","Unfilled","Filled") -> Filled | M41: Bugna | N41: Marvin Jino | O41: Salazar | Q41: 32440 | R41: 45420 | S41: 45420 | T41: 45420 | U41: Married | V41: Male | W41: =DATEDIF(Q41,TODAY(),"Y") -> 37 | X41: =IF(ABS(Table1[[#This Row],[AGE]])>59,"60 and above",IF(ABS(Table1[[#This Row],[AGE]])>49,"50-59",IF(ABS(Table1[[#This Row],[AGE]])>39,"40-49",IF(ABS(Table1[[#This Row],[AGE]])>29,"30-39",IF(ABS(Table1[[#This Row],[AGE]])>19,"20-29",""))))) -> 30-39 | Y41: Manila | Z41: 715 Zebrina, Calathea Place Condominium | AA41: San Antonio Valley I | AB41: Parañaque City | AC41: Metro Manila | AD41: 1715 | AE41: Doctor of Medicine | AF41: Medicine | AG41: RA 1080 | AH41: 0136172 | AI41: 46319 | AJ41: 2005940000 | AK41: 1212-9219-9838 | AL41: 1925-0012-4810 | AM41: 253-793-436 | AN41: 0917-843-7524 | AO41: N/A | AP41: jino.bugna@gmail.com
A42: 41 | B42: OSEC-DOHB-MDOF3-270005-2020 | C42: Medical Officer III (ER) | D42: Emergency Med | E42: Medical Officer III | F42: Emergency Medicine Department | G42: Physician | H42: Medical Division | I42: 21 | J42: =LOOKUP(Table1[[#This Row],[SALARY GRADE]],{1,2,3,4,5,6,7,8,9,10,11,12,13,14,15,16,17,18,19,20,21,22,23,24,25,26,27,28,29,30,31,32,33},{14364,15522,16486,17506,18581,19716,20914,22423,24329,26917,31705,33947,36125,38764,42178,45694,49562,53818,59153,66052,73303,81796,91306,102603,116643,131807,148940,167129,187531,210718,300961,356237,449157}) -> 73303 | K42: 2nd | L42: =IF(Table1[[#This Row],[LAST]]="","Unfilled","Filled") -> Filled | M42: Contreras | N42: Ryan Jed | O42: Aquino | Q42: 31775 | R42: 45083 | S42: 45083 | T42: 45083 | U42: Single | V42: Male | W42: =DATEDIF(Q42,TODAY(),"Y") -> 39 | X42: =IF(ABS(Table1[[#This Row],[AGE]])>59,"60 and above",IF(ABS(Table1[[#This Row],[AGE]])>49,"50-59",IF(ABS(Table1[[#This Row],[AGE]])>39,"40-49",IF(ABS(Table1[[#This Row],[AGE]])>29,"30-39",IF(ABS(Table1[[#This Row],[AGE]])>19,"20-29",""))))) -> 30-39 | Y42: Manila | Z42: Blk 27 Lot 21C Silver St, | AA42: Pilar Village | AB42: Las Piñas City | AC42: Metro Manila | AD42: 1740 | AE42: Doctor of Medicine | AF42: Medicine | AG42: RA 1080 | AH42: 0139924 | AI42: 46020 | AJ42: 2006333491 | AK42: 1213-2047-1609 | AL42: 0102-6298-0338 | AM42: 718-941-513 | AN42: 0977-820-4191 | AO42: N/A | AP42: rjedcontreras@yahoo.com
A43: 42 | B43: OSEC-DOHB-MDOF3-270006-2020 | C43: Medical Officer III | D43: Obstetrician | E43: Medical Officer III | F43: Obstetrics-Gynecology Department | G43: Physician | H43: Medical Division | I43: 21 | J43: =LOOKUP(Table1[[#This Row],[SALARY GRADE]],{1,2,3,4,5,6,7,8,9,10,11,12,13,14,15,16,17,18,19,20,21,22,23,24,25,26,27,28,29,30,31,32,33},{14364,15522,16486,17506,18581,19716,20914,22423,24329,26917,31705,33947,36125,38764,42178,45694,49562,53818,59153,66052,73303,81796,91306,102603,116643,131807,148940,167129,187531,210718,300961,356237,449157}) -> 73303 | K43: 2nd | L43: =IF(Table1[[#This Row],[LAST]]="","Unfilled","Filled") -> Filled | M43: Lu | N43: Maureen | O43: Alegre | Q43: 28746 | R43: 45568 | S43: 45568 | T43: 45568 | U43: Married | V43: Female | W43: =DATEDIF(Q43,TODAY(),"Y") -> 47 | X43: =IF(ABS(Table1[[#This Row],[AGE]])>59,"60 and above",IF(ABS(Table1[[#This Row],[AGE]])>49,"50-59",IF(ABS(Table1[[#This Row],[AGE]])>39,"40-49",IF(ABS(Table1[[#This Row],[AGE]])>29,"30-39",IF(ABS(Table1[[#This Row],[AGE]])>19,"20-29",""))))) -> 40-49 | Y43: Imus City, Cavite | Z43: Block 32 Lot 24, Clover St., Asian Leaf Subd. | AA43: San Francisco | AB43: General Trias City | AC43: Cavite | AD43: 4107 | AE43: Doctor of Medicine | AF43: Medicine | AG43: RA 1080 | AH43: 0106956 | AI43: 46643 | AJ43: 2006565804 | AK43: 1213-5142-0164 | AL43: 0802-5420-1719 | AM43: 245-983-976 | AN43: 0917-860-0978 | AO43: N/A | AP43: monengmd@yahoo.com
A44: 43 | B44: OSEC-DOHB-MDOF3-270007-2020 | C44: Medical Officer III (ER) | D44: Emergency Med | E44: Medical Officer III | F44: Emergency Medicine Department | G44: Physician | H44: Medical Division | I44: 21 | J44: =LOOKUP(Table1[[#This Row],[SALARY GRADE]],{1,2,3,4,5,6,7,8,9,10,11,12,13,14,15,16,17,18,19,20,21,22,23,24,25,26,27,28,29,30,31,32,33},{14364,15522,16486,17506,18581,19716,20914,22423,24329,26917,31705,33947,36125,38764,42178,45694,49562,53818,59153,66052,73303,81796,91306,102603,116643,131807,148940,167129,187531,210718,300961,356237,449157}) -> 73303 | K44: 2nd | L44: =IF(Table1[[#This Row],[LAST]]="","Unfilled","Filled") -> Filled | M44: Magallanes | N44: Ma. Joeylynn | O44: Veluz | Q44: 32396 | R44: 45149 | S44: 45149 | T44: 45149 | U44: Single | V44: Female | W44: =DATEDIF(Q44,TODAY(),"Y") -> 37 | X44: =IF(ABS(Table1[[#This Row],[AGE]])>59,"60 and above",IF(ABS(Table1[[#This Row],[AGE]])>49,"50-59",IF(ABS(Table1[[#This Row],[AGE]])>39,"40-49",IF(ABS(Table1[[#This Row],[AGE]])>29,"30-39",IF(ABS(Table1[[#This Row],[AGE]])>19,"20-29",""))))) -> 30-39 | Y44: Manila | Z44: Block 8 Lot 2, Gemini St., Cherry Homes 4 | AA44: Mambog II | AB44: Bacoor City | AC44: Cavite | AD44: 4102 | AE44: Doctor of Medicine | AF44: Medicine | AG44: RA 1080 | AH44: 0133955 | AI44: 45910 | AJ44: 2006360703 | AK44: 1213-2515-9616 | AL44: 0102-5548-1903 | AM44: 475-623-880 | AN44: 0927-962-9766 | AO44: (046) 4895-5272 | AP44: joeylynnmagallanes@gmail.com
A45: 44 | B45: OSEC-DOHB-MDOF3-270008-2020 | C45: Medical Officer III (IM) | D45: Internist | E45: Medical Officer III | F45: Internal Medicine Department | G45: Physician | H45: Medical Division | I45: 21 | J45: =LOOKUP(Table1[[#This Row],[SALARY GRADE]],{1,2,3,4,5,6,7,8,9,10,11,12,13,14,15,16,17,18,19,20,21,22,23,24,25,26,27,28,29,30,31,32,33},{14364,15522,16486,17506,18581,19716,20914,22423,24329,26917,31705,33947,36125,38764,42178,45694,49562,53818,59153,66052,73303,81796,91306,102603,116643,131807,148940,167129,187531,210718,300961,356237,449157}) -> 73303 | K45: 2nd | L45: =IF(Table1[[#This Row],[LAST]]="","Unfilled","Filled") -> Filled | M45: Ocomen | N45: Keitel Larraine | O45: Ferrer | Q45: 32353 | R45: 45659 | S45: 45659 | T45: 45659 | U45: Single | V45: Female | W45: =DATEDIF(Q45,TODAY(),"Y") -> 38 | X45: =IF(ABS(Table1[[#This Row],[AGE]])>59,"60 and above",IF(ABS(Table1[[#This Row],[AGE]])>49,"50-59",IF(ABS(Table1[[#This Row],[AGE]])>39,"40-49",IF(ABS(Table1[[#This Row],[AGE]])>29,"30-39",IF(ABS(Table1[[#This Row],[AGE]])>19,"20-29",""))))) -> 30-39 | Y45: Pasay City | Z45: Block 12 Lot 25 Cagliari, Ponticelli Hills | AA45: Molino IV | AB45: Bacoor City | AC45: Cavite | AD45: 4102 | AE45: Doctor of Medicine | AF45: Medicine | AG45: RA 1080 | AH45: 0135737 | AI45: 46232 | AJ45: 2005736067 | AK45: 1212-6527-7518 | AL45: 0102-6563-2888 | AM45: 501-309-060 | AN45: 0917-773-0729 | AO45: N/A | AP45: keitellarraineocomen@gmail.com
A46: 45 | B46: OSEC-DOHB-MDOF3-270009-2020 | C46: Medical Officer III (Pedia) | D46: Pediatrician | E46: Medical Officer III | F46: Pediatrics Department | G46: Physician | H46: Medical Division | I46: 21 | J46: =LOOKUP(Table1[[#This Row],[SALARY GRADE]],{1,2,3,4,5,6,7,8,9,10,11,12,13,14,15,16,17,18,19,20,21,22,23,24,25,26,27,28,29,30,31,32,33},{14364,15522,16486,17506,18581,19716,20914,22423,24329,26917,31705,33947,36125,38764,42178,45694,49562,53818,59153,66052,73303,81796,91306,102603,116643,131807,148940,167129,187531,210718,300961,356237,449157}) -> 73303 | K46: 2nd | L46: =IF(Table1[[#This Row],[LAST]]="","Unfilled","Filled") -> Filled | M46: Cortez | N46: Jazel Anne | O46: De Guzman | Q46: 33534 | R46: 45370 | S46: 45370 | T46: 45370 | U46: Single | V46: Female | W46: =DATEDIF(Q46,TODAY(),"Y") -> 34 | X46: =IF(ABS(Table1[[#This Row],[AGE]])>59,"60 and above",IF(ABS(Table1[[#This Row],[AGE]])>49,"50-59",IF(ABS(Table1[[#This Row],[AGE]])>39,"40-49",IF(ABS(Table1[[#This Row],[AGE]])>29,"30-39",IF(ABS(Table1[[#This Row],[AGE]])>19,"20-29",""))))) -> 30-39 | Y46: Manila | Z46: 1311 San Nicolas Yacal St. | AA46: 255 | AB46: Manila City | AC46: Metro Manila | AD46: 1014 | AE46: Doctor of Medicine | AF46: Medicine | AG46: RA 1080 | AH46: 0138715 | AI46: 46318 | AJ46: 2005367048 | AK46: 1210-3115-3314 | AL46: 0202-5569-2918 | AM46: 714-132-314 | AN46: 0932-870-0023 | AO46: 252-4095 | AP46: jazelanne.cortez@yahoo.com
A47: 46 | B47: OSEC-DOHB-MDOF3-270026-2022 | C47: Medical Officer III (Surgeon) | D47: Surgeon | E47: Medical Officer III | F47: Surgery Department | G47: Physician | H47: Medical Division | I47: 21 | J47: =LOOKUP(Table1[[#This Row],[SALARY GRADE]],{1,2,3,4,5,6,7,8,9,10,11,12,13,14,15,16,17,18,19,20,21,22,23,24,25,26,27,28,29,30,31,32,33},{14364,15522,16486,17506,18581,19716,20914,22423,24329,26917,31705,33947,36125,38764,42178,45694,49562,53818,59153,66052,73303,81796,91306,102603,116643,131807,148940,167129,187531,210718,300961,356237,449157}) -> 73303 | K47: 2nd | L47: =IF(Table1[[#This Row],[LAST]]="","Unfilled","Filled") -> Filled | M47: Castillo | N47: Norman | O47: Santiago | Q47: 28446 | R47: 45090 | S47: 45090 | T47: 45090 | U47: Married | V47: Male | W47: =DATEDIF(Q47,TODAY(),"Y") -> 48 | X47: =IF(ABS(Table1[[#This Row],[AGE]])>59,"60 and above",IF(ABS(Table1[[#This Row],[AGE]])>49,"50-59",IF(ABS(Table1[[#This Row],[AGE]])>39,"40-49",IF(ABS(Table1[[#This Row],[AGE]])>29,"30-39",IF(ABS(Table1[[#This Row],[AGE]])>19,"20-29",""))))) -> 40-49 | Y47: Pasay City | Z47: B10 L3 Max's Village | AA47: Molino IV | AB47: Bacoor City | AC47: Cavite | AD47: 4102 | AE47: Doctor of Medicine | AF47: Medicine | AG47: RA 1080 | AH47: 0112287 | AI47: 46708 | AJ47: 2003918876 | AK47: 1211-0510-7971 | AL47: 0802-5352-3666 | AM47: 209-395-244 | AN47: 0917-169-1117 | AO47: (046) 416-7708 | AP47: norman.castillo1117@gmail.com
A48: 47 | B48: OSEC-DOHB-MDOF3-270027-2022 | C48: Medical Officer III (Pedia) | D48: Pediatrician | E48: Medical Officer III | F48: Pediatrics Department | G48: Physician | H48: Medical Division | I48: 21 | J48: =LOOKUP(Table1[[#This Row],[SALARY GRADE]],{1,2,3,4,5,6,7,8,9,10,11,12,13,14,15,16,17,18,19,20,21,22,23,24,25,26,27,28,29,30,31,32,33},{14364,15522,16486,17506,18581,19716,20914,22423,24329,26917,31705,33947,36125,38764,42178,45694,49562,53818,59153,66052,73303,81796,91306,102603,116643,131807,148940,167129,187531,210718,300961,356237,449157}) -> 73303 | K48: 2nd | L48: =IF(Table1[[#This Row],[LAST]]="","Unfilled","Filled") -> Filled | M48: Cadiente | N48: Venessa Rose | O48: Cadizal | Q48: 30977 | R48: 44960 | S48: 44960 | T48: 44960 | U48: Single | V48: Female | W48: =DATEDIF(Q48,TODAY(),"Y") -> 41 | X48: =IF(ABS(Table1[[#This Row],[AGE]])>59,"60 and above",IF(ABS(Table1[[#This Row],[AGE]])>49,"50-59",IF(ABS(Table1[[#This Row],[AGE]])>39,"40-49",IF(ABS(Table1[[#This Row],[AGE]])>29,"30-39",IF(ABS(Table1[[#This Row],[AGE]])>19,"20-29",""))))) -> 40-49 | Y48: Quezon City | Z48: B2 L2 Tindalo St., Meadowood Exec. Village | AA48: Panapaan VIII | AB48: Bacoor City | AC48: Cavite | AD48: 4102 | AE48: Doctor of Medicine | AF48: Medicine | AG48: RA 1080 | AH48: 0129502 | AI48: 45932 | AJ48: 2006264722 | AK48: 1213-1121-6934 | AL48: 0202-7254-8014 | AM48: 235-406-620 | AN48: 0915-129-2296 | AO48: N/A | AP48: venessacadientemd@gmail.com
A49: 48 | B49: OSEC-DOHB-MDOF3-270028-2022 | C49: Medical Officer III (ER) | D49: Emergency Med | E49: Medical Officer III | F49: Emergency Medicine Department | G49: Physician | H49: Medical Division | I49: 21 | J49: =LOOKUP(Table1[[#This Row],[SALARY GRADE]],{1,2,3,4,5,6,7,8,9,10,11,12,13,14,15,16,17,18,19,20,21,22,23,24,25,26,27,28,29,30,31,32,33},{14364,15522,16486,17506,18581,19716,20914,22423,24329,26917,31705,33947,36125,38764,42178,45694,49562,53818,59153,66052,73303,81796,91306,102603,116643,131807,148940,167129,187531,210718,300961,356237,449157}) -> 73303 | K49: 2nd | L49: =IF(Table1[[#This Row],[LAST]]="","Unfilled","Filled") -> Filled | M49: Miranda-Galang | N49: Barbara Marie | O49: Jamela | Q49: 32003 | R49: 45446 | S49: 45446 | T49: 45446 | U49: Married | V49: Female | W49: =DATEDIF(Q49,TODAY(),"Y") -> 39 | X49: =IF(ABS(Table1[[#This Row],[AGE]])>59,"60 and above",IF(ABS(Table1[[#This Row],[AGE]])>49,"50-59",IF(ABS(Table1[[#This Row],[AGE]])>39,"40-49",IF(ABS(Table1[[#This Row],[AGE]])>29,"30-39",IF(ABS(Table1[[#This Row],[AGE]])>19,"20-29",""))))) -> 30-39 | Y49: Manila | Z49: #37 Saint Hilario St., St. Joseph Park Subd. | AA49: Pulang Lupas Dos | AB49: Las Piñas City | AC49: Metro Manila | AD49: 1742 | AE49: Doctor of Medicine | AF49: Medicine | AG49: RA 1080 | AH49: 0125998 | AI49: 45883 | AJ49: 2006497208 | AK49: 1212-1880-7569 | AL49: 0102-5290-9139 | AM49: 421-842-737 | AN49: 0917-357-1513 | AO49: N/A | AP49: bmjmiranda@gmail.com
A50: 49 | B50: OSEC-DOHB-MDOF3-270029-2022 | C50: Medical Officer III (ER) | D50: Emergency Med | E50: Medical Officer III | F50: Emergency Medicine Department | G50: Physician | H50: Medical Division | I50: 21 | J50: =LOOKUP(Table1[[#This Row],[SALARY GRADE]],{1,2,3,4,5,6,7,8,9,10,11,12,13,14,15,16,17,18,19,20,21,22,23,24,25,26,27,28,29,30,31,32,33},{14364,15522,16486,17506,18581,19716,20914,22423,24329,26917,31705,33947,36125,38764,42178,45694,49562,53818,59153,66052,73303,81796,91306,102603,116643,131807,148940,167129,187531,210718,300961,356237,449157}) -> 73303 | K50: 2nd | L50: =IF(Table1[[#This Row],[LAST]]="","Unfilled","Filled") -> Filled | M50: Nueva España | N50: Rubilyn | O50: Casugay | Q50: 29969 | R50: 45153 | S50: 45153 | T50: 45153 | U50: Single | V50: Female | W50: =DATEDIF(Q50,TODAY(),"Y") -> 44 | X50: =IF(ABS(Table1[[#This Row],[AGE]])>59,"60 and above",IF(ABS(Table1[[#This Row],[AGE]])>49,"50-59",IF(ABS(Table1[[#This Row],[AGE]])>39,"40-49",IF(ABS(Table1[[#This Row],[AGE]])>29,"30-39",IF(ABS(Table1[[#This Row],[AGE]])>19,"20-29",""))))) -> 40-49 | Y50: Rosario, Cavite | Z50: 391 Salcedo St. | AA50: Salcedo I | AB50: Noveleta | AC50: Cavite | AD50: 4105 | AE50: Doctor of Medicine | AF50: Medicine | AG50: RA 1080 | AH50: 0118081 | AI50: 45675 | AJ50: 2004319990 | AK50: 1210-8061-7589 | AL50: 0102-5220-6944 | AM50: 431-307-170 | AN50: 0916-333-1036 | AO50: N/A | AP50: rcnemd@gmail.com
A51: 50 | B51: OSEC-DOHB-MDOF3-270030-2022 | C51: Medical Officer III (OB) | D51: Obstetrician | E51: Medical Officer III | F51: Obstetrics-Gynecology Department | G51: Physician | H51: Medical Division | I51: 21 | J51: =LOOKUP(Table1[[#This Row],[SALARY GRADE]],{1,2,3,4,5,6,7,8,9,10,11,12,13,14,15,16,17,18,19,20,21,22,23,24,25,26,27,28,29,30,31,32,33},{14364,15522,16486,17506,18581,19716,20914,22423,24329,26917,31705,33947,36125,38764,42178,45694,49562,53818,59153,66052,73303,81796,91306,102603,116643,131807,148940,167129,187531,210718,300961,356237,449157}) -> 73303 | K51: 2nd | L51: =IF(Table1[[#This Row],[LAST]]="","Unfilled","Filled") -> Filled | M51: Arkoncel-Gonsalves | N51: Ma. Kristine Angela | O51: Oñate | Q51: 33270 | R51: 45446 | S51: 45446 | T51: 45446 | U51: Married | V51: Female | W51: =DATEDIF(Q51,TODAY(),"Y") -> 35 | X51: =IF(ABS(Table1[[#This Row],[AGE]])>59,"60 and above",IF(ABS(Table1[[#This Row],[AGE]])>49,"50-59",IF(ABS(Table1[[#This Row],[AGE]])>39,"40-49",IF(ABS(Table1[[#This Row],[AGE]])>29,"30-39",IF(ABS(Table1[[#This Row],[AGE]])>19,"20-29",""))))) -> 30-39 | Y51: Quezon City | Z51: 19 Ipo | AA51: Salvacion | AB51: Quezon City | AC51: Metro Manila | AD51: 1114 | AE51: Doctor of Medicine | AF51: Medicine | AG51: RA 1080 | AH51: 0138437 | AI51: 46054 | AJ51: 2005343451 | AK51: 1212-1434-8059 | AL51: 0302-5945-2496 | AM51: 273-861-971 | AN51: 0917-828-0201 | AO51: N/A | AP51: angela.arkoncel@gmail.com
A52: 51 | B52: OSEC-DOHB-MDOF3-270031-2022 | C52: Medical Officer III | D52: Anesthesiologist | E52: Medical Officer III | F52: Anesthesiology Department | G52: Physician | H52: Medical Division | I52: 21 | J52: =LOOKUP(Table1[[#This Row],[SALARY GRADE]],{1,2,3,4,5,6,7,8,9,10,11,12,13,14,15,16,17,18,19,20,21,22,23,24,25,26,27,28,29,30,31,32,33},{14364,15522,16486,17506,18581,19716,20914,22423,24329,26917,31705,33947,36125,38764,42178,45694,49562,53818,59153,66052,73303,81796,91306,102603,116643,131807,148940,167129,187531,210718,300961,356237,449157}) -> 73303 | K52: 2nd | L52: =IF(Table1[[#This Row],[LAST]]="","Unfilled","Filled") -> Filled | M52: Reyes | N52: Ma. Luz Carmencita | O52: Matias | Q52: 32964 | R52: 44960 | S52: 44960 | T52: 44960 | U52: Single | V52: Female | W52: =DATEDIF(Q52,TODAY(),"Y") -> 36 | X52: =IF(ABS(Table1[[#This Row],[AGE]])>59,"60 and above",IF(ABS(Table1[[#This Row],[AGE]])>49,"50-59",IF(ABS(Table1[[#This Row],[AGE]])>39,"40-49",IF(ABS(Table1[[#This Row],[AGE]])>29,"30-39",IF(ABS(Table1[[#This Row],[AGE]])>19,"20-29",""))))) -> 30-39 | Y52: Mandaluyong City | Z52: 2 Adelfa Doña Manuela 1 | AA52: Pamplona Tres | AB52: Las Piñas City | AC52: Cavite | AD52: 1740 | AE52: Doctor of Medicine | AF52: Medicine | AG52: RA 1080 | AH52: 0136497 | AI52: 46026 | AJ52: 2005438480 | AK52: 1212-3922-2793 | AL52: 0102-5946-6658 | AM52: 297-850-583 | AN52: 0917-880-0359 | AO52: (02) 8874-7623 | AP52: mlmcreyes@gmail.com
A53: 52 | B53: OSEC-DOHB-MDOF3-270032-2022 | C53: Medical Officer III (Surgeon) | D53: Surgeon | E53: Medical Officer III | F53: Surgery Department | G53: Physician | H53: Medical Division | I53: 21 | J53: =LOOKUP(Table1[[#This Row],[SALARY GRADE]],{1,2,3,4,5,6,7,8,9,10,11,12,13,14,15,16,17,18,19,20,21,22,23,24,25,26,27,28,29,30,31,32,33},{14364,15522,16486,17506,18581,19716,20914,22423,24329,26917,31705,33947,36125,38764,42178,45694,49562,53818,59153,66052,73303,81796,91306,102603,116643,131807,148940,167129,187531,210718,300961,356237,449157}) -> 73303 | K53: 2nd | L53: =IF(Table1[[#This Row],[LAST]]="","Unfilled","Filled") -> Filled | M53: De Guzman | N53: Patrick Edward | O53: Sabino | Q53: 32916 | R53: 45313 | S53: 45313 | T53: 45313 | U53: Married | V53: Male | W53: =DATEDIF(Q53,TODAY(),"Y") -> 36 | X53: =IF(ABS(Table1[[#This Row],[AGE]])>59,"60 and above",IF(ABS(Table1[[#This Row],[AGE]])>49,"50-59",IF(ABS(Table1[[#This Row],[AGE]])>39,"40-49",IF(ABS(Table1[[#This Row],[AGE]])>29,"30-39",IF(ABS(Table1[[#This Row],[AGE]])>19,"20-29",""))))) -> 30-39 | Y53: Manila | Z53: Block 8 Lot 2 Kaimito St., Phase 1 West Camella Springville | AA53: Molino III | AB53: Bacoor City | AC53: Cavite | AD53: 4102 | AE53: Doctor of Medicine | AF53: Medicine | AG53: RA 1080 | AH53: 0137221 | AI53: 46065 | AJ53: 2006423076 | AK53: 1212-1576-6440 | AL53: 0802-6122-2586 | AM53: 252-429-408 | AN53: 0917-123-6544 | AO53: (046) 970-9144 | AP53: pedeguzman7668@gmail.com
A54: 53 | B54: OSEC-DOHB-MDOF3-270033-2022 | C54: Medical Officer III (IM) | D54: Internist | E54: Medical Officer III | F54: Internal Medicine Department | G54: Physician | H54: Medical Division | I54: 21 | J54: =LOOKUP(Table1[[#This Row],[SALARY GRADE]],{1,2,3,4,5,6,7,8,9,10,11,12,13,14,15,16,17,18,19,20,21,22,23,24,25,26,27,28,29,30,31,32,33},{14364,15522,16486,17506,18581,19716,20914,22423,24329,26917,31705,33947,36125,38764,42178,45694,49562,53818,59153,66052,73303,81796,91306,102603,116643,131807,148940,167129,187531,210718,300961,356237,449157}) -> 73303 | K54: 2nd | L54: =IF(Table1[[#This Row],[LAST]]="","Unfilled","Filled") -> Filled | M54: De Leon | N54: Kevin | O54: Dulce | Q54: 33425 | R54: 45839 | S54: 45839 | T54: 45839 | U54: Single | V54: Male | W54: =DATEDIF(Q54,TODAY(),"Y") -> 35 | X54: =IF(ABS(Table1[[#This Row],[AGE]])>59,"60 and above",IF(ABS(Table1[[#This Row],[AGE]])>49,"50-59",IF(ABS(Table1[[#This Row],[AGE]])>39,"40-49",IF(ABS(Table1[[#This Row],[AGE]])>29,"30-39",IF(ABS(Table1[[#This Row],[AGE]])>19,"20-29",""))))) -> 30-39 | Y54: Cavite City | Z54: 253 | AA54: Bucal | AB54: Tanza | AC54: Cavite | AD54: 4108 | AE54: Doctor of Medicine | AF54: Medicine | AG54: RA 1080 | AH54: 0140995 | AI54: 46911 | AJ54: 2005759572 | AK54: 1210-2491-2327 | AL54: 0802-5447-5851 | AM54: 283-009-521 | AN54: 0917-143-1383 | AO54: (046) 437-8849 | AP54: kevin_dulce2006@gmail.com
A55: 54 | B55: OSEC-DOHB-MDOF3-270034-2022 | C55: Medical Officer III (Pedia) | D55: Pediatrician | E55: Medical Officer III | F55: Pediatrics Department | G55: Physician | H55: Medical Division | I55: 21 | J55: =LOOKUP(Table1[[#This Row],[SALARY GRADE]],{1,2,3,4,5,6,7,8,9,10,11,12,13,14,15,16,17,18,19,20,21,22,23,24,25,26,27,28,29,30,31,32,33},{14364,15522,16486,17506,18581,19716,20914,22423,24329,26917,31705,33947,36125,38764,42178,45694,49562,53818,59153,66052,73303,81796,91306,102603,116643,131807,148940,167129,187531,210718,300961,356237,449157}) -> 73303 | K55: 2nd | L55: =IF(Table1[[#This Row],[LAST]]="","Unfilled","Filled") -> Filled | M55: Martinez | N55: Franze Perry | O55: Caagbay | Q55: 33461 | R55: 45097 | S55: 45097 | T55: 45097 | U55: Single | V55: Female | W55: =DATEDIF(Q55,TODAY(),"Y") -> 35 | X55: =IF(ABS(Table1[[#This Row],[AGE]])>59,"60 and above",IF(ABS(Table1[[#This Row],[AGE]])>49,"50-59",IF(ABS(Table1[[#This Row],[AGE]])>39,"40-49",IF(ABS(Table1[[#This Row],[AGE]])>29,"30-39",IF(ABS(Table1[[#This Row],[AGE]])>19,"20-29",""))))) -> 30-39 | Y55: Manila | Z55: B4 L2D JP Laurel Ave., Pilar Exec. Village | AA55: Almanza Uno | AB55: Las Piñas City | AC55: Metro Manila | AD55: 1750 | AE55: Doctor of Medicine | AF55: Medicine | AG55: RA 1080 | AH55: 0143224 | AI55: 46699 | AJ55: 20055499175 | AK55: 1212-3984-3303 | AL55: 0202-6973-7558 | AM55: 709-897-161 | AN55: 0998-855-6039 | AO55: N/A | AP55: franzeperrymartinez@yahoo.com
A56: 55 | B56: OSEC-DOHB-NURS5-270025-2022 | C56: Nurse V | E56: Nurse V | F56: Office of the Chief Nurse | G56: Nurse | H56: Nursing Division | I56: 20 | J56: =LOOKUP(Table1[[#This Row],[SALARY GRADE]],{1,2,3,4,5,6,7,8,9,10,11,12,13,14,15,16,17,18,19,20,21,22,23,24,25,26,27,28,29,30,31,32,33},{14364,15522,16486,17506,18581,19716,20914,22423,24329,26917,31705,33947,36125,38764,42178,45694,49562,53818,59153,66052,73303,81796,91306,102603,116643,131807,148940,167129,187531,210718,300961,356237,449157}) -> 66052 | K56: 2nd | L56: =IF(Table1[[#This Row],[LAST]]="","Unfilled","Filled") -> Filled | M56: Samuel | N56: Ruffy | O56: Yap | Q56: 25504 | R56: 34715 | S56: 44363 | T56: 45124 | U56: Married | V56: Female | W56: =DATEDIF(Q56,TODAY(),"Y") -> 56 | X56: =IF(ABS(Table1[[#This Row],[AGE]])>59,"60 and above",IF(ABS(Table1[[#This Row],[AGE]])>49,"50-59",IF(ABS(Table1[[#This Row],[AGE]])>39,"40-49",IF(ABS(Table1[[#This Row],[AGE]])>29,"30-39",IF(ABS(Table1[[#This Row],[AGE]])>19,"20-29",""))))) -> 50-59 | Y56: Cavite City | Z56: 757 Tagumpay St. | AA56: San Antonio | AB56: Cavite City | AC56: Cavite | AD56: 4100 | AE56: College Graduate | AF56: BS Nursing | AG56: RA 1080 | AH56: 0202444 | AI56: 46323 | AJ56: 2001399490 | AK56: 1030-0006-6325 | AL56: 0800-0032-9634 | AM56: 178-955-128 | AN56: 0915-865-7898 | AO56: (046) 431-1257 | AP56: gngruffy@yahoo.com
A57: 56 | B57: OSEC-DOHB-A3-270122-2020 | C57: Accountant III | E57: Accountant III | F57: Accounting Section | G57: Accountant | H57: Hospital Operation and Patient Support Division | I57: 19 | J57: =LOOKUP(Table1[[#This Row],[SALARY GRADE]],{1,2,3,4,5,6,7,8,9,10,11,12,13,14,15,16,17,18,19,20,21,22,23,24,25,26,27,28,29,30,31,32,33},{14364,15522,16486,17506,18581,19716,20914,22423,24329,26917,31705,33947,36125,38764,42178,45694,49562,53818,59153,66052,73303,81796,91306,102603,116643,131807,148940,167129,187531,210718,300961,356237,449157}) -> 59153 | K57: 2nd | L57: =IF(Table1[[#This Row],[LAST]]="","Unfilled","Filled") -> Filled | M57: Bongcac | N57: Irene | O57: Genson | Q57: 31333 | R57: 43462 | S57: 44564 | T57: 44564 | U57: Married | V57: Female | W57: =DATEDIF(Q57,TODAY(),"Y") -> 40 | X57: =IF(ABS(Table1[[#This Row],[AGE]])>59,"60 and above",IF(ABS(Table1[[#This Row],[AGE]])>49,"50-59",IF(ABS(Table1[[#This Row],[AGE]])>39,"40-49",IF(ABS(Table1[[#This Row],[AGE]])>29,"30-39",IF(ABS(Table1[[#This Row],[AGE]])>19,"20-29",""))))) -> 40-49 | Y57: Carmen, Bohol | Z57: B6 L4 Dreamhomes Subd. | AA57: Tejero | AB57: General Trias City | AC57: Cavite | AD57: 4107 | AE57: College Graduate | AF57: BS Accountancy | AG57: RA 1080 | AH57: 0137120 | AI57: 46308 | AJ57: 2005568486 | AK57: 1210-9745-5776 | AL57: 0105-0762-6632 | AM57: 287-257-773 | AN57: 0925-313-1222 | AO57: N/A | AP57: gensoni@yahoo.com
A58: 57 | B58: OSEC-DOHB-ENG3-270002-2020 | C58: Engineer III | E58: Engineer III | F58: Engineering and Facilities Management | G58: Engineer | H58: Hospital Operation and Patient Support Division | I58: 19 | J58: =LOOKUP(Table1[[#This Row],[SALARY GRADE]],{1,2,3,4,5,6,7,8,9,10,11,12,13,14,15,16,17,18,19,20,21,22,23,24,25,26,27,28,29,30,31,32,33},{14364,15522,16486,17506,18581,19716,20914,22423,24329,26917,31705,33947,36125,38764,42178,45694,49562,53818,59153,66052,73303,81796,91306,102603,116643,131807,148940,167129,187531,210718,300961,356237,449157}) -> 59153 | K58: 2nd | L58: =IF(Table1[[#This Row],[LAST]]="","Unfilled","Filled") -> Filled | M58: Collado | N58: Arvin | O58: Gioglagon | Q58: 34478 | R58: 44319 | S58: 44319 | T58: 44319 | U58: Single | V58: Male | W58: =DATEDIF(Q58,TODAY(),"Y") -> 32 | X58: =IF(ABS(Table1[[#This Row],[AGE]])>59,"60 and above",IF(ABS(Table1[[#This Row],[AGE]])>49,"50-59",IF(ABS(Table1[[#This Row],[AGE]])>39,"40-49",IF(ABS(Table1[[#This Row],[AGE]])>29,"30-39",IF(ABS(Table1[[#This Row],[AGE]])>19,"20-29",""))))) -> 30-39 | Y58: San Juan, Metro Manila | Z58: P1 B24 L1, Cyberville Subd. | AA58: Santiago | AB58: General Trias City | AC58: Cavite | AD58: 4107 | AE58: College Graduate | AF58: BS Civil Engineering | AG58: RA 1080 | AH58: 0140176 | AI58: 45801 | AJ58: 2005911418 | AK58: 1211-6273-7780 | AL58: 0225-1682-1748 | AM58: 326-223-361 | AN58: 0916-771-5351 | AO58: N/A | AP58: arvincollado@yahoo.com
A59: 58 | B59: OSEC-DOHB-NURS4-270024-2022 | C59: Nurse IV | E59: Nurse IV | F59: Office of the Chief Nurse | G59: Nurse | H59: Nursing Division | I59: 19 | J59: =LOOKUP(Table1[[#This Row],[SALARY GRADE]],{1,2,3,4,5,6,7,8,9,10,11,12,13,14,15,16,17,18,19,20,21,22,23,24,25,26,27,28,29,30,31,32,33},{14364,15522,16486,17506,18581,19716,20914,22423,24329,26917,31705,33947,36125,38764,42178,45694,49562,53818,59153,66052,73303,81796,91306,102603,116643,131807,148940,167129,187531,210718,300961,356237,449157}) -> 59153 | K59: 2nd | L59: =IF(Table1[[#This Row],[LAST]]="","Unfilled","Filled") -> Filled | M59: Melchor | N59: Mia Rose | O59: Galanta | Q59: 32784 | R59: 43466 | S59: 44363 | T59: 45099 | U59: Married | V59: Female | W59: =DATEDIF(Q59,TODAY(),"Y") -> 36 | X59: =IF(ABS(Table1[[#This Row],[AGE]])>59,"60 and above",IF(ABS(Table1[[#This Row],[AGE]])>49,"50-59",IF(ABS(Table1[[#This Row],[AGE]])>39,"40-49",IF(ABS(Table1[[#This Row],[AGE]])>29,"30-39",IF(ABS(Table1[[#This Row],[AGE]])>19,"20-29",""))))) -> 30-39 | Y59: Caloocan City | Z59: Block P L20 RSG Gueventhomes | AA59: Panapaan I | AB59: Bacoor City | AC59: Cavite | AD59: 4102 | AE59: Master's Degree | AF59: BS Nursing | AG59: RA 1080 | AH59: 0821595 | AI59: 46298 | AJ59: 2005538707 | AK59: 1210-2741-5551 | AL59: 0105-1017-4048 | AM59: 403-689-833 | AN59: 0999-679-7134 | AO59: (046) 973-2993 | AP59: miaroseminianogalanta@yahoo.com
A60: 59 | B60: OSEC-DOHB-ADOF5-270017-2022 | C60: Administrative Officer V (Administrative Officer III) | E60: Administrative Officer V | F60: Health Information Management Section | G60: Administrative Officer | H60: Medical Division | I60: 18 | J60: =LOOKUP(Table1[[#This Row],[SALARY GRADE]],{1,2,3,4,5,6,7,8,9,10,11,12,13,14,15,16,17,18,19,20,21,22,23,24,25,26,27,28,29,30,31,32,33},{14364,15522,16486,17506,18581,19716,20914,22423,24329,26917,31705,33947,36125,38764,42178,45694,49562,53818,59153,66052,73303,81796,91306,102603,116643,131807,148940,167129,187531,210718,300961,356237,449157}) -> 53818 | K60: 2nd | L60: =IF(Table1[[#This Row],[LAST]]="","Unfilled","Filled") -> Filled | M60: Purugganan | N60: Eden Enriqueta | O60: Aragon | Q60: 25157 | R60: 44319 | S60: 44350 | T60: 45086 | U60: Single | V60: Female | W60: =DATEDIF(Q60,TODAY(),"Y") -> 57 | X60: =IF(ABS(Table1[[#This Row],[AGE]])>59,"60 and above",IF(ABS(Table1[[#This Row],[AGE]])>49,"50-59",IF(ABS(Table1[[#This Row],[AGE]])>39,"40-49",IF(ABS(Table1[[#This Row],[AGE]])>29,"30-39",IF(ABS(Table1[[#This Row],[AGE]])>19,"20-29",""))))) -> 50-59 | Y60: Quezon City | Z60: B3 L5 Sampaguita St., Camella Townhomes | AA60: Salinas II | AB60: Bacoor City | AC60: Cavite | AD60: 4102 | AE60: College Graduate | AF60: BS Commerce | AG60: CSC - Professional | AH60: N/A | AI60: N/A | AJ60: 2005911996 | AK60: 1040-0091-7993 | AL60: 0802-5192-8944 | AM60: 253-753-973 | AN60: 0917-494-8023 | AO60: (046) 456-5512 | AP60: epurugganan547@gmail.com
A61: 60 | B61: OSEC-DOHB-ADOF5-270018-2022 | C61: Administrative Officer V (Budget Officer III) | E61: Administrative Officer V | F61: Budget Section | G61: Administrative Officer | H61: Hospital Operation and Patient Support Division | I61: 18 | J61: =LOOKUP(Table1[[#This Row],[SALARY GRADE]],{1,2,3,4,5,6,7,8,9,10,11,12,13,14,15,16,17,18,19,20,21,22,23,24,25,26,27,28,29,30,31,32,33},{14364,15522,16486,17506,18581,19716,20914,22423,24329,26917,31705,33947,36125,38764,42178,45694,49562,53818,59153,66052,73303,81796,91306,102603,116643,131807,148940,167129,187531,210718,300961,356237,449157}) -> 53818 | K61: 2nd | L61: =IF(Table1[[#This Row],[LAST]]="","Unfilled","Filled") -> Filled | M61: Pioquinto-Santos | N61: Ivy | O61: Toreja | Q61: 32548 | R61: 44460 | S61: 44460 | T61: 45071 | U61: Married | V61: Female | W61: =DATEDIF(Q61,TODAY(),"Y") -> 37 | X61: =IF(ABS(Table1[[#This Row],[AGE]])>59,"60 and above",IF(ABS(Table1[[#This Row],[AGE]])>49,"50-59",IF(ABS(Table1[[#This Row],[AGE]])>39,"40-49",IF(ABS(Table1[[#This Row],[AGE]])>29,"30-39",IF(ABS(Table1[[#This Row],[AGE]])>19,"20-29",""))))) -> 30-39 | Y61: Batangas City | Z61: 10 Continental St., Greenview Subd. | AA61: Pamplona Tres | AB61: Las Piñas City | AC61: NCR | AD61: 1740 | AE61: College Graduate | AF61: BS Mathematics | AG61: CSC - Professional | AH61: N/A | AI61: N/A | AJ61: 2005960636 | AK61: 1210-1682-8934 | AL61: 0902-5264-3329 | AM61: 303-771-778 | AN61: 0927-552-3908 | AO61: N/A | AP61: ivypioquinto2013@gmail.com
A62: 61 | B62: OSEC-DOHB-ADOF5-270019-2022 | C62: Administrative Officer V (Cashier III) | E62: Administrative Officer V | F62: Cash Operations Section | G62: Administrative Officer | H62: Hospital Operation and Patient Support Division | I62: 18 | J62: =LOOKUP(Table1[[#This Row],[SALARY GRADE]],{1,2,3,4,5,6,7,8,9,10,11,12,13,14,15,16,17,18,19,20,21,22,23,24,25,26,27,28,29,30,31,32,33},{14364,15522,16486,17506,18581,19716,20914,22423,24329,26917,31705,33947,36125,38764,42178,45694,49562,53818,59153,66052,73303,81796,91306,102603,116643,131807,148940,167129,187531,210718,300961,356237,449157}) -> 53818 | K62: 2nd | L62: =IF(Table1[[#This Row],[LAST]]="","Unfilled","Filled") -> Filled | M62: Moraña | N62: Ruby | O62: Punongbayan | Q62: 25442 | R62: 35992 | S62: 44348 | T62: 45072 | U62: Married | V62: Female | W62: =DATEDIF(Q62,TODAY(),"Y") -> 56 | X62: =IF(ABS(Table1[[#This Row],[AGE]])>59,"60 and above",IF(ABS(Table1[[#This Row],[AGE]])>49,"50-59",IF(ABS(Table1[[#This Row],[AGE]])>39,"40-49",IF(ABS(Table1[[#This Row],[AGE]])>29,"30-39",IF(ABS(Table1[[#This Row],[AGE]])>19,"20-29",""))))) -> 50-59 | Y62: General Trias, Cavite | Z62: 231 Maria Cecilia | AA62: Mulawin | AB62: Tanza | AC62: Cavite | AD62: 4108 | AE62: College Graduate | AF62: BSBA Accounting | AG62: CSC - Professional | AH62: N/A | AI62: N/A | AJ62: 2001397720 | AK62: 1030-0009-0004 | AL62: 0800-0013-8014 | AM62: 123-218-628 | AN62: 0908-866-5672 | AO62: N/A | AP62: rubymorana27@gmail.com
A63: 62 | B63: OSEC-DOHB-ADOF5-270020-2022 | C63: Administrative Officer V (Supply Officer III) | E63: Administrative Officer V | F63: Materials Management Section | G63: Administrative Officer | H63: Hospital Operation and Patient Support Division | I63: 18 | J63: =LOOKUP(Table1[[#This Row],[SALARY GRADE]],{1,2,3,4,5,6,7,8,9,10,11,12,13,14,15,16,17,18,19,20,21,22,23,24,25,26,27,28,29,30,31,32,33},{14364,15522,16486,17506,18581,19716,20914,22423,24329,26917,31705,33947,36125,38764,42178,45694,49562,53818,59153,66052,73303,81796,91306,102603,116643,131807,148940,167129,187531,210718,300961,356237,449157}) -> 53818 | K63: 2nd | L63: =IF(Table1[[#This Row],[LAST]]="","Unfilled","Filled") -> Filled | M63: Niogan | N63: Leanard | O63: Romea | Q63: 35867 | R63: 44333 | S63: 44333 | T63: 45082 | U63: Single | V63: Male | W63: =DATEDIF(Q63,TODAY(),"Y") -> 28 | X63: =IF(ABS(Table1[[#This Row],[AGE]])>59,"60 and above",IF(ABS(Table1[[#This Row],[AGE]])>49,"50-59",IF(ABS(Table1[[#This Row],[AGE]])>39,"40-49",IF(ABS(Table1[[#This Row],[AGE]])>29,"30-39",IF(ABS(Table1[[#This Row],[AGE]])>19,"20-29",""))))) -> 20-29 | Y63: Trece Martires City, Cavite | Z63: Purok II | AA63: Aguado | AB63: Trece Martires City | AC63: Cavite | AD63: 4109 | AE63: College Graduate | AF63: BS AB Engineering | AG63: RA 1080 | AH63: 0010568 | AI63: 45729 | AJ63: 2005911991 | AK63: 1212-8379-1009 | AL63: 0802-6744-8349 | AM63: 497-085-220 | AN63: 0935-651-3427 | AO63: N/A | AP63: leanardniogan13@gmail.com
A64: 63 | B64: OSEC-DOHB-ADOF5-270021-2022 | C64: Administrative Officer V (Administrative Officer III) | E64: Administrative Officer V | F64: Procurement Section | G64: Administrative Officer | H64: Hospital Operation and Patient Support Division | I64: 18 | J64: =LOOKUP(Table1[[#This Row],[SALARY GRADE]],{1,2,3,4,5,6,7,8,9,10,11,12,13,14,15,16,17,18,19,20,21,22,23,24,25,26,27,28,29,30,31,32,33},{14364,15522,16486,17506,18581,19716,20914,22423,24329,26917,31705,33947,36125,38764,42178,45694,49562,53818,59153,66052,73303,81796,91306,102603,116643,131807,148940,167129,187531,210718,300961,356237,449157}) -> 53818 | K64: 2nd | L64: =IF(Table1[[#This Row],[LAST]]="","Unfilled","Filled") -> Filled | M64: Baccay | N64: Joel | O64: Mesias | Q64: 29744 | R64: 45156 | S64: 45156 | T64: 45156 | U64: Married | V64: Male | W64: =DATEDIF(Q64,TODAY(),"Y") -> 45 | X64: =IF(ABS(Table1[[#This Row],[AGE]])>59,"60 and above",IF(ABS(Table1[[#This Row],[AGE]])>49,"50-59",IF(ABS(Table1[[#This Row],[AGE]])>39,"40-49",IF(ABS(Table1[[#This Row],[AGE]])>29,"30-39",IF(ABS(Table1[[#This Row],[AGE]])>19,"20-29",""))))) -> 40-49 | Y64: Santiago, Isabela | Z64: Phase 8 Block 37 Lot 12 Wellington Place | AA64: Pascam II | AB64: General Trias City | AC64: Cavite | AD64: 4107 | AE64: College Graduate | AF64: BS Geodetic Engineering | AG64: CSC - Professional | AH64: N/A | AI64: N/A | AJ64: 2006360745 | AK64: 1211-2903-5720 | AL64: 1705-0144-6567 | AM64: 256-174-639 | AN64: 0977-025-0828 | AO64: N/A | AP64: jaguar0796@yahoo.com
A65: 64 | B65: OSEC-DOHB-ADOF5-270121-2020 | C65: Administrative Officer V (HRMO III) | E65: Administrative Officer V | F65: Human Resource Management Section | G65: Administrative Officer | H65: Hospital Operation and Patient Support Division | I65: 18 | J65: =LOOKUP(Table1[[#This Row],[SALARY GRADE]],{1,2,3,4,5,6,7,8,9,10,11,12,13,14,15,16,17,18,19,20,21,22,23,24,25,26,27,28,29,30,31,32,33},{14364,15522,16486,17506,18581,19716,20914,22423,24329,26917,31705,33947,36125,38764,42178,45694,49562,53818,59153,66052,73303,81796,91306,102603,116643,131807,148940,167129,187531,210718,300961,356237,449157}) -> 53818 | K65: 2nd | L65: =IF(Table1[[#This Row],[LAST]]="","Unfilled","Filled") -> Filled | M65: Bayas | N65: Wilma | O65: Panganiban | Q65: 22865 | R65: 40596 | S65: 44348 | T65: 44412 | U65: Married | V65: Female | W65: =DATEDIF(Q65,TODAY(),"Y") -> 64 | X65: =IF(ABS(Table1[[#This Row],[AGE]])>59,"60 and above",IF(ABS(Table1[[#This Row],[AGE]])>49,"50-59",IF(ABS(Table1[[#This Row],[AGE]])>39,"40-49",IF(ABS(Table1[[#This Row],[AGE]])>29,"30-39",IF(ABS(Table1[[#This Row],[AGE]])>19,"20-29",""))))) -> 60 and above | Y65: Taysan, Batangas | Z65: 147 Mahogany Ave. | AA65: Kaybagal South | AB65: Tagaytay City | AC65: Cavite | AD65: 4120 | AE65: Master's Degree | AF65: MM Hospital Administration | AG65: CSC - Professional | AH65: N/A | AI65: N/A | AJ65: 2000757758 | AK65: 0013-2173-0206 | AL65: 0800-0005-7200 | AM65: 161-188-260 | AN65: 0916-945-2473 | AO65: (046) 418-3644 | AP65: bayaswilma@gmail.com
A66: 65 | B66: OSEC-DOHB-MDTK3-270022-2022 | C66: Medical Technologist III | E66: Medical Technologist III | F66: Clinical and Anatomical Laboratory Department | G66: Medical Technologist | H66: Medical Division | I66: 18 | J66: =LOOKUP(Table1[[#This Row],[SALARY GRADE]],{1,2,3,4,5,6,7,8,9,10,11,12,13,14,15,16,17,18,19,20,21,22,23,24,25,26,27,28,29,30,31,32,33},{14364,15522,16486,17506,18581,19716,20914,22423,24329,26917,31705,33947,36125,38764,42178,45694,49562,53818,59153,66052,73303,81796,91306,102603,116643,131807,148940,167129,187531,210718,300961,356237,449157}) -> 53818 | K66: 2nd | L66: =IF(Table1[[#This Row],[LAST]]="","Unfilled","Filled") -> Filled | M66: Legara | N66: Princess | O66: Constantino | Q66: 29310 | R66: 44503 | S66: 44503 | T66: 45098 | U66: Married | V66: Female | W66: =DATEDIF(Q66,TODAY(),"Y") -> 46 | X66: =IF(ABS(Table1[[#This Row],[AGE]])>59,"60 and above",IF(ABS(Table1[[#This Row],[AGE]])>49,"50-59",IF(ABS(Table1[[#This Row],[AGE]])>39,"40-49",IF(ABS(Table1[[#This Row],[AGE]])>29,"30-39",IF(ABS(Table1[[#This Row],[AGE]])>19,"20-29",""))))) -> 40-49 | Y66: Manila | AA66: Mabolo III | AB66: Bacoor City | AC66: Cavite | AD66: 4102 | AE66: College Graduate | AF66: BS Medical Technology | AG66: RA 1080 | AH66: 0060289 | AI66: 45746 | AJ66: 2005997017 | AK66: 1060-0064-9731 | AL66: 0205-0429-9458 | AM66: 218-152-173 | AN66: 0917-556-0330 | AO66: N/A | AP66: pclegara@gmail.com
A67: 66 | B67: OSEC-DOHB-MDTK3-270023-2022 | C67: Medical Technologist III | E67: Medical Technologist III | F67: Clinical and Anatomical Laboratory Department | G67: Medical Technologist | H67: Medical Division | I67: 18 | J67: =LOOKUP(Table1[[#This Row],[SALARY GRADE]],{1,2,3,4,5,6,7,8,9,10,11,12,13,14,15,16,17,18,19,20,21,22,23,24,25,26,27,28,29,30,31,32,33},{14364,15522,16486,17506,18581,19716,20914,22423,24329,26917,31705,33947,36125,38764,42178,45694,49562,53818,59153,66052,73303,81796,91306,102603,116643,131807,148940,167129,187531,210718,300961,356237,449157}) -> 53818 | K67: 2nd | L67: =IF(Table1[[#This Row],[LAST]]="","Unfilled","Filled") -> Filled | M67: Santarin | N67: Nerissa | O67: Villanueva | Q67: 25890 | R67: 37264 | S67: 44363 | T67: 45098 | U67: Married | V67: Female | W67: =DATEDIF(Q67,TODAY(),"Y") -> 55 | X67: =IF(ABS(Table1[[#This Row],[AGE]])>59,"60 and above",IF(ABS(Table1[[#This Row],[AGE]])>49,"50-59",IF(ABS(Table1[[#This Row],[AGE]])>39,"40-49",IF(ABS(Table1[[#This Row],[AGE]])>29,"30-39",IF(ABS(Table1[[#This Row],[AGE]])>19,"20-29",""))))) -> 50-59 | Y67: Kawit, Cavite | Z67: 1023 Rosalia Village | AA67: Habay II | AB67: Bacoor City | AC67: Cavite | AD67: 4102 | AE67: College Graduate | AF67: BS Medical Technology | AG67: RA 1080 | AH67: 0027127 | AI67: 46709 | AJ67: 2001242643 | AK67: 1030-0008-5321 | AL67: 0802-5064-1781 | AM67: 182-039-133 | AN67: 0917-829-6776 | AO67: (046) 438-3315 | AP67: nev_santarin@yahoo.com
A68: 67 | B68: OSEC-DOHB-ND3-270001-2021 | C68: Nutritionist-Dietitian III | E68: Nutritionist-Dietitian III | F68: Nutrition and Dietetics Section | G68: Nutritionist-Dietitian | H68: Medical Division | I68: 18 | J68: =LOOKUP(Table1[[#This Row],[SALARY GRADE]],{1,2,3,4,5,6,7,8,9,10,11,12,13,14,15,16,17,18,19,20,21,22,23,24,25,26,27,28,29,30,31,32,33},{14364,15522,16486,17506,18581,19716,20914,22423,24329,26917,31705,33947,36125,38764,42178,45694,49562,53818,59153,66052,73303,81796,91306,102603,116643,131807,148940,167129,187531,210718,300961,356237,449157}) -> 53818 | K68: 2nd | L68: =IF(Table1[[#This Row],[LAST]]="","Unfilled","Filled") -> Filled | M68: Bayot | N68: Imee Rose | O68: Araña | Q68: 29189 | R68: 40634 | S68: 44504 | T68: 44504 | U68: Married | V68: Female | W68: =DATEDIF(Q68,TODAY(),"Y") -> 46 | X68: =IF(ABS(Table1[[#This Row],[AGE]])>59,"60 and above",IF(ABS(Table1[[#This Row],[AGE]])>49,"50-59",IF(ABS(Table1[[#This Row],[AGE]])>39,"40-49",IF(ABS(Table1[[#This Row],[AGE]])>29,"30-39",IF(ABS(Table1[[#This Row],[AGE]])>19,"20-29",""))))) -> 40-49 | Y68: Mlang, North Cotabato | Z68: B26 L13 P3C, Lavanya Subd. | AA68: Bacao I | AB68: General Trias City | AC68: Cavite | AD68: 4107 | AE68: College Graduate | AF68: BS Nutrition and Dietetics | AG68: RA 1080 | AH68: 0011193 | AI68: 45991 | AJ68: 2004118286 | AK68: 1890-0071-3023 | AL68: 1705-0072-4229 | AM68: 943-636-067 | AN68: 0947-449-3873 | AO68: N/A | AP68: IRBayot@gmail.com
A69: 68 | B69: OSEC-DOHB-PH3-270002-2021 | C69: Pharmacist III | E69: Pharmacist III | F69: Pharmacy Section | G69: Pharmacist | H69: Medical Division | I69: 18 | J69: =LOOKUP(Table1[[#This Row],[SALARY GRADE]],{1,2,3,4,5,6,7,8,9,10,11,12,13,14,15,16,17,18,19,20,21,22,23,24,25,26,27,28,29,30,31,32,33},{14364,15522,16486,17506,18581,19716,20914,22423,24329,26917,31705,33947,36125,38764,42178,45694,49562,53818,59153,66052,73303,81796,91306,102603,116643,131807,148940,167129,187531,210718,300961,356237,449157}) -> 53818 | K69: 2nd | L69: =IF(Table1[[#This Row],[LAST]]="","Unfilled","Filled") -> Filled | M69: Herrera | N69: Christopher Rey | O69: Garcia | Q69: 27687 | R69: 36648 | S69: 44504 | T69: 44504 | U69: Married | V69: Male | W69: =DATEDIF(Q69,TODAY(),"Y") -> 50 | X69: =IF(ABS(Table1[[#This Row],[AGE]])>59,"60 and above",IF(ABS(Table1[[#This Row],[AGE]])>49,"50-59",IF(ABS(Table1[[#This Row],[AGE]])>39,"40-49",IF(ABS(Table1[[#This Row],[AGE]])>29,"30-39",IF(ABS(Table1[[#This Row],[AGE]])>19,"20-29",""))))) -> 50-59 | Y69: Imus City, Cavite | Z69: 116 Cristo St., Holiday Village | AA69: Bayan Luma II | AB69: Imus City | AC69: Cavite | AD69: 4103 | AE69: Master's Degree | AF69: BS Pharamacy | AG69: RA 1080 | AH69: 0039413 | AI69: 46315 | AJ69: 2001397270 | AK69: 1030-0009-7532 | AL69: 1905-0800-0875 | AM69: 202-642-142 | AN69: 0932-553-9203 | AO69: (046) 471-9483 | AP69: christop_herrera@yahoo.com
A70: 69 | B70: OSEC-DOHB-RT3-270043-2022 | C70: Radiologic Technologist III | E70: Radiologic Technologist III | F70: Radiology Department | G70: Radiologic Technologist | H70: Medical Division | I70: 18 | J70: =LOOKUP(Table1[[#This Row],[SALARY GRADE]],{1,2,3,4,5,6,7,8,9,10,11,12,13,14,15,16,17,18,19,20,21,22,23,24,25,26,27,28,29,30,31,32,33},{14364,15522,16486,17506,18581,19716,20914,22423,24329,26917,31705,33947,36125,38764,42178,45694,49562,53818,59153,66052,73303,81796,91306,102603,116643,131807,148940,167129,187531,210718,300961,356237,449157}) -> 53818 | K70: 2nd | L70: =IF(Table1[[#This Row],[LAST]]="","Unfilled","Filled") -> Filled | M70: Tabing | N70: Dave AJ | O70: Jaleco vice Cabatian | Q70: 32546 | R70: 45537 | S70: 45840 | T70: 45840 | U70: Single | V70: Male | W70: =DATEDIF(Q70,TODAY(),"Y") -> 37 | X70: =IF(ABS(Table1[[#This Row],[AGE]])>59,"60 and above",IF(ABS(Table1[[#This Row],[AGE]])>49,"50-59",IF(ABS(Table1[[#This Row],[AGE]])>39,"40-49",IF(ABS(Table1[[#This Row],[AGE]])>29,"30-39",IF(ABS(Table1[[#This Row],[AGE]])>19,"20-29",""))))) -> 30-39 | Y70: Mandaluyong City | Z70: 458 (New 191) | AA70: Anabu 1-C | AB70: Imus City | AC70: Cavite | AD70: 4103 | AE70: College Graduate | AF70: BS Radiologic Technology | AG70: RA 1080 | AH70: 0007444 | AI70: 46425 | AJ70: 2006554346 | AK70: 1210-0998-1403 | AL70: 0805-1168-7997 | AM70: 224-993-116 | AN70: 0925-499-0709 | AO70: N/A | AP70: dave_tabing@yahoo.com
A71: 70 | B71: OSEC-DOHB-SOCWO3-270016-2022 | C71: Social Welfare Officer III | E71: Social Welfare Officer III | F71: Medical Social Service Section | G71: Social Welfare Officer | H71: Medical Division | I71: 18 | J71: =LOOKUP(Table1[[#This Row],[SALARY GRADE]],{1,2,3,4,5,6,7,8,9,10,11,12,13,14,15,16,17,18,19,20,21,22,23,24,25,26,27,28,29,30,31,32,33},{14364,15522,16486,17506,18581,19716,20914,22423,24329,26917,31705,33947,36125,38764,42178,45694,49562,53818,59153,66052,73303,81796,91306,102603,116643,131807,148940,167129,187531,210718,300961,356237,449157}) -> 53818 | K71: 2nd | L71: =IF(Table1[[#This Row],[LAST]]="","Unfilled","Filled") -> Filled | M71: Añano | N71: Angelica | O71: Bagares | Q71: 35588 | R71: 44333 | S71: 44333 | T71: 45110 | U71: Single | V71: Female | W71: =DATEDIF(Q71,TODAY(),"Y") -> 29 | X71: =IF(ABS(Table1[[#This Row],[AGE]])>59,"60 and above",IF(ABS(Table1[[#This Row],[AGE]])>49,"50-59",IF(ABS(Table1[[#This Row],[AGE]])>39,"40-49",IF(ABS(Table1[[#This Row],[AGE]])>29,"30-39",IF(ABS(Table1[[#This Row],[AGE]])>19,"20-29",""))))) -> 20-29 | Y71: Guiuan, Eastern Samar | Z71: B27 L28, Rovigo Courtyard, Golden Horizon | AA71: Hugo Perez | AB71: Trece Martires City | AC71: Cavite | AD71: 4109 | AE71: College Graduate | AF71: BS Social Work | AG71: RA 1080 | AH71: 0024974 | AI71: 46180 | AJ71: 2005911399 | AK71: 1212-1881-9236 | AL71: 0802-6357-2223 | AM71: 716-701-971 | AN71: 0935-855-9450 | AO71: N/A | AP71: angelicabagares@yahoo.com
A72: 71 | B72: OSEC-DOHB-DENT2-270115-2020 | C72: Dentist II | E72: Dentist II | F72: Dental Department | G72: Dentist | H72: Medical Division | I72: 17 | J72: =LOOKUP(Table1[[#This Row],[SALARY GRADE]],{1,2,3,4,5,6,7,8,9,10,11,12,13,14,15,16,17,18,19,20,21,22,23,24,25,26,27,28,29,30,31,32,33},{14364,15522,16486,17506,18581,19716,20914,22423,24329,26917,31705,33947,36125,38764,42178,45694,49562,53818,59153,66052,73303,81796,91306,102603,116643,131807,148940,167129,187531,210718,300961,356237,449157}) -> 49562 | K72: 2nd | L72: =IF(Table1[[#This Row],[LAST]]="","Unfilled","Filled") -> Unfilled | O72: Vice Rivera, Promotion
A73: 72 | B73: OSEC-DOHB-NURS3-270013-2022 | C73: Nurse III | E73: Nurse III | F73: Nursing Service | G73: Nurse | H73: Nursing Division | I73: 17 | J73: =LOOKUP(Table1[[#This Row],[SALARY GRADE]],{1,2,3,4,5,6,7,8,9,10,11,12,13,14,15,16,17,18,19,20,21,22,23,24,25,26,27,28,29,30,31,32,33},{14364,15522,16486,17506,18581,19716,20914,22423,24329,26917,31705,33947,36125,38764,42178,45694,49562,53818,59153,66052,73303,81796,91306,102603,116643,131807,148940,167129,187531,210718,300961,356237,449157}) -> 49562 | K73: 2nd | L73: =IF(Table1[[#This Row],[LAST]]="","Unfilled","Filled") -> Filled | M73: Angeles | N73: John Nichol | O73: Busa | Q73: 33039 | R73: 44334 | S73: 44334 | T73: 44844 | U73: Married | V73: Male | W73: =DATEDIF(Q73,TODAY(),"Y") -> 36 | X73: =IF(ABS(Table1[[#This Row],[AGE]])>59,"60 and above",IF(ABS(Table1[[#This Row],[AGE]])>49,"50-59",IF(ABS(Table1[[#This Row],[AGE]])>39,"40-49",IF(ABS(Table1[[#This Row],[AGE]])>29,"30-39",IF(ABS(Table1[[#This Row],[AGE]])>19,"20-29",""))))) -> 30-39 | Y73: Quezon City | Z73: P1 B10 L22, Veraville Townhomes Arcadia | AA73: Dulong Bayan | AB73: Bacoor City | AC73: Cavite | AD73: 4102 | AE73: Master's Degree | AF73: BS Nursing | AG73: RA 1080 | AH73: 078810 | AI73: 46188 | AJ73: 2005911397 | AK73: 1211-0774-8132 | AL73: 0802-5726-2743 | AM73: 269-648-623 | AN73: 0915-661-7672 | AO73: (046) 435-7791 | AP73: nico.angeles15@gmail.com
A74: 73 | B74: OSEC-DOHB-NURS3-270014-2022 | C74: Nurse III | E74: Nurse III | F74: Nursing Service | G74: Nurse | H74: Nursing Division | I74: 17 | J74: =LOOKUP(Table1[[#This Row],[SALARY GRADE]],{1,2,3,4,5,6,7,8,9,10,11,12,13,14,15,16,17,18,19,20,21,22,23,24,25,26,27,28,29,30,31,32,33},{14364,15522,16486,17506,18581,19716,20914,22423,24329,26917,31705,33947,36125,38764,42178,45694,49562,53818,59153,66052,73303,81796,91306,102603,116643,131807,148940,167129,187531,210718,300961,356237,449157}) -> 49562 | K74: 2nd | L74: =IF(Table1[[#This Row],[LAST]]="","Unfilled","Filled") -> Filled | M74: Capistrano | N74: Bryan John | O74: Cortes | Q74: 30965 | R74: 44336 | S74: 44336 | T74: 44844 | U74: Single | V74: Male | W74: =DATEDIF(Q74,TODAY(),"Y") -> 41 | X74: =IF(ABS(Table1[[#This Row],[AGE]])>59,"60 and above",IF(ABS(Table1[[#This Row],[AGE]])>49,"50-59",IF(ABS(Table1[[#This Row],[AGE]])>39,"40-49",IF(ABS(Table1[[#This Row],[AGE]])>29,"30-39",IF(ABS(Table1[[#This Row],[AGE]])>19,"20-29",""))))) -> 40-49 | Y74: Cavite City | Z74: 860 Inocencio St. | AA74: 58-A San Roque | AB74: Cavite City | AC74: Cavite | AD74: 4100 | AE74: College Graduate | AF74: BS Nursing | AG74: RA 1080 | AH74: 0403790 | AI74: 46670 | AJ74: 2004118497 | AK74: 1211-6834-9152 | AL74: 0800-0107-8457 | AM74: 282-059-539 | AN74: 0927-120-1134 | AO74: (046) 431-0747 | AP74: bryancapistrano@yahoo.com
A75: 74 | B75: OSEC-DOHB-NURS3-270015-2022 | C75: Nurse III | E75: Nurse III | F75: Nursing Service | G75: Nurse | H75: Nursing Division | I75: 17 | J75: =LOOKUP(Table1[[#This Row],[SALARY GRADE]],{1,2,3,4,5,6,7,8,9,10,11,12,13,14,15,16,17,18,19,20,21,22,23,24,25,26,27,28,29,30,31,32,33},{14364,15522,16486,17506,18581,19716,20914,22423,24329,26917,31705,33947,36125,38764,42178,45694,49562,53818,59153,66052,73303,81796,91306,102603,116643,131807,148940,167129,187531,210718,300961,356237,449157}) -> 49562 | K75: 2nd | L75: =IF(Table1[[#This Row],[LAST]]="","Unfilled","Filled") -> Filled | M75: Santos | N75: Marissa | O75: Moran | Q75: 33827 | R75: 44333 | S75: 44333 | T75: 44844 | U75: Single | V75: Female | W75: =DATEDIF(Q75,TODAY(),"Y") -> 34 | X75: =IF(ABS(Table1[[#This Row],[AGE]])>59,"60 and above",IF(ABS(Table1[[#This Row],[AGE]])>49,"50-59",IF(ABS(Table1[[#This Row],[AGE]])>39,"40-49",IF(ABS(Table1[[#This Row],[AGE]])>29,"30-39",IF(ABS(Table1[[#This Row],[AGE]])>19,"20-29",""))))) -> 30-39 | Y75: Beti Aritao, Nueva Vizcaya | Z75: B5 L37-39 Yakal St., Sagana Remville Homes | AA75: Habay II | AB75: Bacoor City | AC75: Cavite | AD75: 4102 | AE75: College Graduate | AF75: BS Nursing | AG75: RA 1080 | AH75: 0888723 | AI75: 46245 | AJ75: 2005911999 | AK75: 1211-2390-0641 | AL75: 0620-1092-7345 | AM75: 472-930-140 | AN75: 0926-369-7382 | AO75: N/A | AP75: santosmarissa28@yahoo.com
A76: 75 | B76: OSEC-DOHB-NUR3-270116-2020 | C76: Nurse III | E76: Nurse III | F76: Nursing Service | G76: Nurse | H76: Nursing Division | I76: 17 | J76: =LOOKUP(Table1[[#This Row],[SALARY GRADE]],{1,2,3,4,5,6,7,8,9,10,11,12,13,14,15,16,17,18,19,20,21,22,23,24,25,26,27,28,29,30,31,32,33},{14364,15522,16486,17506,18581,19716,20914,22423,24329,26917,31705,33947,36125,38764,42178,45694,49562,53818,59153,66052,73303,81796,91306,102603,116643,131807,148940,167129,187531,210718,300961,356237,449157}) -> 49562 | K76: 2nd | L76: =IF(Table1[[#This Row],[LAST]]="","Unfilled","Filled") -> Filled | M76: Caimol-Gabuten | N76: Charissa Mara | O76: Pabalinas | Q76: 32442 | R76: 44333 | S76: 44333 | T76: 45274 | U76: Married | V76: Female | W76: =DATEDIF(Q76,TODAY(),"Y") -> 37 | X76: =IF(ABS(Table1[[#This Row],[AGE]])>59,"60 and above",IF(ABS(Table1[[#This Row],[AGE]])>49,"50-59",IF(ABS(Table1[[#This Row],[AGE]])>39,"40-49",IF(ABS(Table1[[#This Row],[AGE]])>29,"30-39",IF(ABS(Table1[[#This Row],[AGE]])>19,"20-29",""))))) -> 30-39 | Y76: Kawit, Cavite | Z76: 181 Manggahan St. | AA76: Binkayan | AB76: Kawit | AC76: Cavite | AD76: 4104 | AE76: Master's Degree | AF76: BS Nursing | AG76: RA 1080 | AH76: 0743881 | AI76: 46686 | AJ76: 2005046466 | AK76: 1211-2712-1181 | AL76: 0202-6320-3381 | AM76: 169-808-918 | AN76: 0956-1204-856 | AO76: (046) 434-5643 | AP76: charissamara_caimol@yahoo.com
A77: 76 | B77: OSEC-DOHB-NUR3-270117-2020 | C77: Nurse III | E77: Nurse III | F77: Nursing Service | G77: Nurse | H77: Nursing Division | I77: 17 | J77: =LOOKUP(Table1[[#This Row],[SALARY GRADE]],{1,2,3,4,5,6,7,8,9,10,11,12,13,14,15,16,17,18,19,20,21,22,23,24,25,26,27,28,29,30,31,32,33},{14364,15522,16486,17506,18581,19716,20914,22423,24329,26917,31705,33947,36125,38764,42178,45694,49562,53818,59153,66052,73303,81796,91306,102603,116643,131807,148940,167129,187531,210718,300961,356237,449157}) -> 49562 | K77: 2nd | L77: =IF(Table1[[#This Row],[LAST]]="","Unfilled","Filled") -> Unfilled | O77: Vice Atmosfera, Promotion
A78: 77 | B78: OSEC-DOHB-NUR3-270118-2020 | C78: Nurse III | E78: Nurse III | F78: Nursing Service | G78: Nurse | H78: Nursing Division | I78: 17 | J78: =LOOKUP(Table1[[#This Row],[SALARY GRADE]],{1,2,3,4,5,6,7,8,9,10,11,12,13,14,15,16,17,18,19,20,21,22,23,24,25,26,27,28,29,30,31,32,33},{14364,15522,16486,17506,18581,19716,20914,22423,24329,26917,31705,33947,36125,38764,42178,45694,49562,53818,59153,66052,73303,81796,91306,102603,116643,131807,148940,167129,187531,210718,300961,356237,449157}) -> 49562 | K78: 2nd | L78: =IF(Table1[[#This Row],[LAST]]="","Unfilled","Filled") -> Filled | M78: Arpa | N78: Geraldine | O78: Crisostomo | Q78: 26258 | R78: 35814 | S78: 44363 | T78: 44363 | U78: Single | V78: Female | W78: =DATEDIF(Q78,TODAY(),"Y") -> 54 | X78: =IF(ABS(Table1[[#This Row],[AGE]])>59,"60 and above",IF(ABS(Table1[[#This Row],[AGE]])>49,"50-59",IF(ABS(Table1[[#This Row],[AGE]])>39,"40-49",IF(ABS(Table1[[#This Row],[AGE]])>29,"30-39",IF(ABS(Table1[[#This Row],[AGE]])>19,"20-29",""))))) -> 50-59 | Y78: Quezon City | Z78: B7 L59 P1 Arcadia Veraville | AA78: Dulong Bayan | AB78: Bacoor City | AC78: Cavite | AD78: 4102 | AE78: College Graduate | AF78: BS Nursing | AG78: RA 1080 | AH78: 0289857 | AI78: 46347 | AJ78: 2001397865 | AK78: 1030-0006-9355 | AL78: 1902-5622-5135 | AM78: 151-410-632 | AN78: 0915-558-8283 | AO78: (046) 343 4044 | AP78: ghee_arpa@yahoo.com
A79: 78 | B79: OSEC-DOHB-NUR3-270119-2020 | C79: Nurse III | E79: Nurse III | F79: Nursing Service | G79: Nurse | H79: Nursing Division | I79: 17 | J79: =LOOKUP(Table1[[#This Row],[SALARY GRADE]],{1,2,3,4,5,6,7,8,9,10,11,12,13,14,15,16,17,18,19,20,21,22,23,24,25,26,27,28,29,30,31,32,33},{14364,15522,16486,17506,18581,19716,20914,22423,24329,26917,31705,33947,36125,38764,42178,45694,49562,53818,59153,66052,73303,81796,91306,102603,116643,131807,148940,167129,187531,210718,300961,356237,449157}) -> 49562 | K79: 2nd | L79: =IF(Table1[[#This Row],[LAST]]="","Unfilled","Filled") -> Filled | M79: Felonia | N79: Strawberry | O79: Bautista | Q79: 32542 | R79: 44333 | S79: 44333 | T79: 44333 | U79: Married | V79: Female | W79: =DATEDIF(Q79,TODAY(),"Y") -> 37 | X79: =IF(ABS(Table1[[#This Row],[AGE]])>59,"60 and above",IF(ABS(Table1[[#This Row],[AGE]])>49,"50-59",IF(ABS(Table1[[#This Row],[AGE]])>39,"40-49",IF(ABS(Table1[[#This Row],[AGE]])>29,"30-39",IF(ABS(Table1[[#This Row],[AGE]])>19,"20-29",""))))) -> 30-39 | Y79: Carigara, Leyte | Z79: #306, 1st Reyville Subd. | AA79: Habay II | AB79: Bacoor City | AC79: Cavite | AD79: 4102 | AE79: College Graduate | AF79: BS Nursing | AG79: RA 1080 | AH79: 0632929 | AI79: 46056 | AJ79: 2004878943 | AK79: 1211-6481-0362 | AL79: 0800-0112-4300 | AM79: 479-188-850 | AN79: 0955-370-3738 | AO79: N/A | AP79: strawberryfelonia@gmail.com
A80: 79 | B80: OSEC-DOHB-NUR3-270120-2020 | C80: Nurse III | E80: Nurse III | F80: Nursing Service | G80: Nurse | H80: Nursing Division | I80: 17 | J80: =LOOKUP(Table1[[#This Row],[SALARY GRADE]],{1,2,3,4,5,6,7,8,9,10,11,12,13,14,15,16,17,18,19,20,21,22,23,24,25,26,27,28,29,30,31,32,33},{14364,15522,16486,17506,18581,19716,20914,22423,24329,26917,31705,33947,36125,38764,42178,45694,49562,53818,59153,66052,73303,81796,91306,102603,116643,131807,148940,167129,187531,210718,300961,356237,449157}) -> 49562 | K80: 2nd | L80: =IF(Table1[[#This Row],[LAST]]="","Unfilled","Filled") -> Filled | M80: Siazon | N80: Lolita | O80: Chuaseco | Q80: 26437 | R80: 44351 | S80: 44351 | T80: 45272 | U80: Married | V80: Female | W80: =DATEDIF(Q80,TODAY(),"Y") -> 54 | X80: =IF(ABS(Table1[[#This Row],[AGE]])>59,"60 and above",IF(ABS(Table1[[#This Row],[AGE]])>49,"50-59",IF(ABS(Table1[[#This Row],[AGE]])>39,"40-49",IF(ABS(Table1[[#This Row],[AGE]])>29,"30-39",IF(ABS(Table1[[#This Row],[AGE]])>19,"20-29",""))))) -> 50-59 | Y80: Manila | Z80: B10 L3 Marbella St. Maravilla | AA80: San Francisco | AB80: General Trias City | AC80: Cavite | AD80: 4107 | AE80: College Graduate | AF80: BS Nursing | AG80: RA 1080 | AH80: 0376694 | AI80: 46525 | AJ80: 2005933968 | AK80: 1505-0011-4683 | AL80: 1902-5819-4695 | AM80: 909-226-617 | AN80: 0938-044-4800 | AO80: N/A | AP80: N/A
A81: 80 | B81: OSEC-DOHB-A2-270041-2022 | C81: Accountant II | E81: Accountant II | F81: Accounting Section | G81: Accountant | H81: Hospital Operation and Patient Support Division | I81: 16 | J81: =LOOKUP(Table1[[#This Row],[SALARY GRADE]],{1,2,3,4,5,6,7,8,9,10,11,12,13,14,15,16,17,18,19,20,21,22,23,24,25,26,27,28,29,30,31,32,33},{14364,15522,16486,17506,18581,19716,20914,22423,24329,26917,31705,33947,36125,38764,42178,45694,49562,53818,59153,66052,73303,81796,91306,102603,116643,131807,148940,167129,187531,210718,300961,356237,449157}) -> 45694 | K81: 2nd | L81: =IF(Table1[[#This Row],[LAST]]="","Unfilled","Filled") -> Filled | M81: Mallillin | N81: Ericka Joy | O81: Lauzon | Q81: 35378 | R81: 46113 | S81: 46113 | T81: 46113 | U81: Single | V81: Female | W81: =DATEDIF(Q81,TODAY(),"Y") -> 29 | X81: =IF(ABS(Table1[[#This Row],[AGE]])>59,"60 and above",IF(ABS(Table1[[#This Row],[AGE]])>49,"50-59",IF(ABS(Table1[[#This Row],[AGE]])>39,"40-49",IF(ABS(Table1[[#This Row],[AGE]])>29,"30-39",IF(ABS(Table1[[#This Row],[AGE]])>19,"20-29",""))))) -> 20-29 | Y81: Dasmariñas City, Cavite | Z81: Block 3 Lot 5 Laurel, Villa Elisa Subdivision | AA81: Anabu 2-E | AB81: Imus City | AC81: Cavite | AD81: 4103 | AE81: College Graduate | AF81: BS Accountancy | AG81: RA 1080 | AH81: 0194929 | AI81: 47066 | AJ81: 2006098579 | AK81: 1212-3898-4682 | AL81: 0225-1817-0906 | AM81: 353-414-607 | AN81: 0919-098-1109 | AO81: N/A | AP81: erickamallillin@gmail.com
A82: 81 | B82: OSEC-DOHB-ENG2-270042-2022 | C82: Engineer II | E82: Engineer II | F82: Engineering and Facilities Management Section | G82: Engineer | H82: Hospital Operation and Patient Support Division | I82: 16 | J82: =LOOKUP(Table1[[#This Row],[SALARY GRADE]],{1,2,3,4,5,6,7,8,9,10,11,12,13,14,15,16,17,18,19,20,21,22,23,24,25,26,27,28,29,30,31,32,33},{14364,15522,16486,17506,18581,19716,20914,22423,24329,26917,31705,33947,36125,38764,42178,45694,49562,53818,59153,66052,73303,81796,91306,102603,116643,131807,148940,167129,187531,210718,300961,356237,449157}) -> 45694 | K82: 2nd | L82: =IF(Table1[[#This Row],[LAST]]="","Unfilled","Filled") -> Filled | M82: Lo | N82: James | O82: Arbiz | Q82: 28814 | R82: 45149 | S82: 45149 | T82: 45149 | U82: Married | V82: Male | W82: =DATEDIF(Q82,TODAY(),"Y") -> 47 | X82: =IF(ABS(Table1[[#This Row],[AGE]])>59,"60 and above",IF(ABS(Table1[[#This Row],[AGE]])>49,"50-59",IF(ABS(Table1[[#This Row],[AGE]])>39,"40-49",IF(ABS(Table1[[#This Row],[AGE]])>29,"30-39",IF(ABS(Table1[[#This Row],[AGE]])>19,"20-29",""))))) -> 40-49 | Y82: Borongan, Eastern Samar | Z82: Block 25 Lot 14 Anemone St., Villa Felicia Subd. | AA82: Bayanan | AB82: Bacoor City | AC82: Cavite | AD82: 4102 | AE82: College Graduate | AF82: BS Civil Engineering | AG82: RA 1080 | AH82: 0087228 | AI82: 46346 | AJ82: 2006360700 | AK82: 1210-0118-4992 | AL82: 1305-0041-3094 | AM82: 927-728-199 | AN82: 0968-746-6158 | AO82: (046) 230-0366 | AP82: jabre_0078@yahoo.com
A83: 82 | B83: OSEC-DOHB-NURS2-14-2025 | C83: Nurse II | E83: Nurse II | F83: Central Supply and Sterilization Unit | G83: Nurse | H83: Nursing Division | I83: 16 | J83: =LOOKUP(Table1[[#This Row],[SALARY GRADE]],{1,2,3,4,5,6,7,8,9,10,11,12,13,14,15,16,17,18,19,20,21,22,23,24,25,26,27,28,29,30,31,32,33},{14364,15522,16486,17506,18581,19716,20914,22423,24329,26917,31705,33947,36125,38764,42178,45694,49562,53818,59153,66052,73303,81796,91306,102603,116643,131807,148940,167129,187531,210718,300961,356237,449157}) -> 45694 | K83: 2nd | L83: =IF(Table1[[#This Row],[LAST]]="","Unfilled","Filled") -> Filled | M83: Paraoan | N83: Erlwin Genesis | O83: Alvez | Q83: 33307 | R83: 43452 | S83: 45537 | T83: 45889 | U83: Single | V83: Male | W83: =DATEDIF(Q83,TODAY(),"Y") -> 35 | X83: =IF(ABS(Table1[[#This Row],[AGE]])>59,"60 and above",IF(ABS(Table1[[#This Row],[AGE]])>49,"50-59",IF(ABS(Table1[[#This Row],[AGE]])>39,"40-49",IF(ABS(Table1[[#This Row],[AGE]])>29,"30-39",IF(ABS(Table1[[#This Row],[AGE]])>19,"20-29",""))))) -> 30-39 | Y83: Manila | Z83: Block 47 Lot 5 Almeria St., Hacienda La Joya Subd. | AA83: Buhay na Tubig | AB83: Imus City | AC83: Cavite | AD83: 4103 | AE83: College Graduate | AF83: BS Nursing | AG83: RA 1080 | AH83: 0872189 | AI83: 46091 | AJ83: 2005531877 | AK83: 1211-4238-9919 | AL83: 0202-6476-2473 | AM83: 453-609-457 | AN83: 0997-603-9964 | AO83: N/A | AP83: egparoanrn@gmail.com
A84: 83 | B84: OSEC-DOHB-NURS2-15-2025 | C84: Nurse II | E84: Nurse II | F84: Nursing Service | G84: Nurse | H84: Nursing Division | I84: 16 | J84: =LOOKUP(Table1[[#This Row],[SALARY GRADE]],{1,2,3,4,5,6,7,8,9,10,11,12,13,14,15,16,17,18,19,20,21,22,23,24,25,26,27,28,29,30,31,32,33},{14364,15522,16486,17506,18581,19716,20914,22423,24329,26917,31705,33947,36125,38764,42178,45694,49562,53818,59153,66052,73303,81796,91306,102603,116643,131807,148940,167129,187531,210718,300961,356237,449157}) -> 45694 | K84: 2nd | L84: =IF(Table1[[#This Row],[LAST]]="","Unfilled","Filled") -> Filled | M84: Manlutac | N84: Rose Ann | O84: Figueroa | Q84: 33012 | R84: 41609 | S84: 45261 | T84: 45888 | U84: Single | V84: Female | W84: =DATEDIF(Q84,TODAY(),"Y") -> 36 | X84: =IF(ABS(Table1[[#This Row],[AGE]])>59,"60 and above",IF(ABS(Table1[[#This Row],[AGE]])>49,"50-59",IF(ABS(Table1[[#This Row],[AGE]])>39,"40-49",IF(ABS(Table1[[#This Row],[AGE]])>29,"30-39",IF(ABS(Table1[[#This Row],[AGE]])>19,"20-29",""))))) -> 30-39 | Y84: Tanza, Cavite | Z84: 245 Palosapis St., St. Anthony Subd. | AA84: Baranggay 4 | AB84: Tanza | AC84: Cavite | AD84: 4108 | AE84: College Graduate | AF84: BS Nursing | AG84: RA 1080 | AH84: 0648273 | AI84: 45796 | AJ84: 2004353261 | AK84: 1210-8610-2229 | AL84: 0800-0102-6813 | AM84: 004-691-798 | AN84: 0917-303-9194 | AO84: N/A | AP84: manlutac.roseann@gmail.com
A85: 84 | B85: OSEC-DOHB-NURS2-16-2025 | C85: Nurse II | E85: Nurse II | F85: Nursing Service | G85: Nurse | H85: Nursing Division | I85: 16 | J85: =LOOKUP(Table1[[#This Row],[SALARY GRADE]],{1,2,3,4,5,6,7,8,9,10,11,12,13,14,15,16,17,18,19,20,21,22,23,24,25,26,27,28,29,30,31,32,33},{14364,15522,16486,17506,18581,19716,20914,22423,24329,26917,31705,33947,36125,38764,42178,45694,49562,53818,59153,66052,73303,81796,91306,102603,116643,131807,148940,167129,187531,210718,300961,356237,449157}) -> 45694 | K85: 2nd | L85: =IF(Table1[[#This Row],[LAST]]="","Unfilled","Filled") -> Filled | M85: Samoza | N85: John Paolo | O85: Magsino | Q85: 35977 | R85: 44949 | S85: 44949 | T85: 45888 | U85: Single | V85: Male | W85: =DATEDIF(Q85,TODAY(),"Y") -> 28 | X85: =IF(ABS(Table1[[#This Row],[AGE]])>59,"60 and above",IF(ABS(Table1[[#This Row],[AGE]])>49,"50-59",IF(ABS(Table1[[#This Row],[AGE]])>39,"40-49",IF(ABS(Table1[[#This Row],[AGE]])>29,"30-39",IF(ABS(Table1[[#This Row],[AGE]])>19,"20-29",""))))) -> 20-29 | Y85: Kalayaan, Kawit, Cavite | Z85: Block 1 Lot 22 Ph. 8, Spain St., ACM Woodstock Village | AA85: Alapan 1-A | AB85: Imus City | AC85: Cavite | AD85: 4104 | AE85: College Graduate | AF85: BS Nursing | AG85: RA 1080 | AH85: 0923582 | AI85: 46204 | AJ85: 2006264729 | AK85: 1212-6665-9450 | AL85: 0802-6688-6601 | AM85: 375-939-471 | AN85: 0919-093-7285 | AO85: N/A | AP85: jpaolo.samoza@gmai.com
A86: 85 | B86: OSEC-DOHB-NURS2-17-2025 | C86: Nurse II | E86: Nurse II | F86: Nursing Service | G86: Nurse | H86: Nursing Division | I86: 16 | J86: =LOOKUP(Table1[[#This Row],[SALARY GRADE]],{1,2,3,4,5,6,7,8,9,10,11,12,13,14,15,16,17,18,19,20,21,22,23,24,25,26,27,28,29,30,31,32,33},{14364,15522,16486,17506,18581,19716,20914,22423,24329,26917,31705,33947,36125,38764,42178,45694,49562,53818,59153,66052,73303,81796,91306,102603,116643,131807,148940,167129,187531,210718,300961,356237,449157}) -> 45694 | K86: 2nd | L86: =IF(Table1[[#This Row],[LAST]]="","Unfilled","Filled") -> Filled | M86: Aquino | N86: Jean Pierre | O86: Morales | Q86: 31972 | R86: 45383 | S86: 45383 | T86: 45888 | U86: Single | V86: Female | W86: =DATEDIF(Q86,TODAY(),"Y") -> 39 | X86: =IF(ABS(Table1[[#This Row],[AGE]])>59,"60 and above",IF(ABS(Table1[[#This Row],[AGE]])>49,"50-59",IF(ABS(Table1[[#This Row],[AGE]])>39,"40-49",IF(ABS(Table1[[#This Row],[AGE]])>29,"30-39",IF(ABS(Table1[[#This Row],[AGE]])>19,"20-29",""))))) -> 30-39 | Y86: Quezon City | Z86: Block 5 Lot 49 KS8, Kinbalu St. Lancaster New City | AA86: Navarro | AB86: General Trias City | AC86: Cavite | AD86: 4107 | AE86: College Graduate | AF86: BS Nursing | AG86: RA 1080 | AH86: 0631378 | AI86: 45852 | AJ86: 2006360713 | AK86: 1210-5830-9104 | AL86: 0305-0890-1018 | AM86: 298-706-697 | AN86: 0968-763-6697 | AO86: N/A | AP86: japi19@yahoo.com
A87: 86 | B87: OSEC-DOHB-NURS2-18-2025 | C87: Nurse II | E87: Nurse II | F87: Nursing Service | G87: Nurse | H87: Nursing Division | I87: 16 | J87: =LOOKUP(Table1[[#This Row],[SALARY GRADE]],{1,2,3,4,5,6,7,8,9,10,11,12,13,14,15,16,17,18,19,20,21,22,23,24,25,26,27,28,29,30,31,32,33},{14364,15522,16486,17506,18581,19716,20914,22423,24329,26917,31705,33947,36125,38764,42178,45694,49562,53818,59153,66052,73303,81796,91306,102603,116643,131807,148940,167129,187531,210718,300961,356237,449157}) -> 45694 | K87: 2nd | L87: =IF(Table1[[#This Row],[LAST]]="","Unfilled","Filled") -> Filled | M87: Encia | N87: Jessica Joy | O87: Miguel | Q87: 32860 | R87: 45084 | S87: 45084 | T87: 45888 | U87: Married | V87: Female | W87: =DATEDIF(Q87,TODAY(),"Y") -> 36 | X87: =IF(ABS(Table1[[#This Row],[AGE]])>59,"60 and above",IF(ABS(Table1[[#This Row],[AGE]])>49,"50-59",IF(ABS(Table1[[#This Row],[AGE]])>39,"40-49",IF(ABS(Table1[[#This Row],[AGE]])>29,"30-39",IF(ABS(Table1[[#This Row],[AGE]])>19,"20-29",""))))) -> 30-39 | Y87: Lubao, Pampanga | Z87: Block 3 Lot 4 Phase 1, Veraville Arcadia | AA87: Dulong Bayan | AB87: Bacoor City | AC87: Cavite | AD87: 4102 | AE87: College Graduate | AF87: BS Nursing | AG87: RA 1080 | AH87: 0677373 | AI87: 46374 | AJ87: 2006346109 | AK87: 1210-5964-3216 | AL87: 0202-5393-2717 | AM87: 400-300-174 | AN87: 0926-614-2420 | AO87: N/A | AP87: iamanurse18@gmail.com
A88: 87 | B88: OSEC-DOHB-NURS2-19-2025 | C88: Nurse II | E88: Nurse II | F88: Nursing Service | G88: Nurse | H88: Nursing Division | I88: 16 | J88: =LOOKUP(Table1[[#This Row],[SALARY GRADE]],{1,2,3,4,5,6,7,8,9,10,11,12,13,14,15,16,17,18,19,20,21,22,23,24,25,26,27,28,29,30,31,32,33},{14364,15522,16486,17506,18581,19716,20914,22423,24329,26917,31705,33947,36125,38764,42178,45694,49562,53818,59153,66052,73303,81796,91306,102603,116643,131807,148940,167129,187531,210718,300961,356237,449157}) -> 45694 | K88: 2nd | L88: =IF(Table1[[#This Row],[LAST]]="","Unfilled","Filled") -> Filled | M88: Crawford | N88: Kryssan | O88: Garcia | Q88: 33757 | R88: 45019 | S88: 45019 | T88: 45888 | U88: Married | V88: Female | W88: =DATEDIF(Q88,TODAY(),"Y") -> 34 | X88: =IF(ABS(Table1[[#This Row],[AGE]])>59,"60 and above",IF(ABS(Table1[[#This Row],[AGE]])>49,"50-59",IF(ABS(Table1[[#This Row],[AGE]])>39,"40-49",IF(ABS(Table1[[#This Row],[AGE]])>29,"30-39",IF(ABS(Table1[[#This Row],[AGE]])>19,"20-29",""))))) -> 30-39 | Y88: Noveleta, Cavite | Z88: 491 Ejercito | AA88: Brgy. 16 Martinez | AB88: Cavite City | AC88: Cavite | AD88: 4100 | AE88: College Graduate | AF88: BS Nursing | AG88: RA 1080 | AH88: 0928805 | AI88: 46424 | AJ88: 2006306693 | AK88: 1210-9860-2091 | AL88: 0105-1438-5705 | AM88: 422-504-701 | AN88: 0965-387-3903 | AO88: (046) 431-8112 | AP88: kryssan06@gmail.com
A89: 88 | B89: OSEC-DOHB-NURS2-20-2025 | C89: Nurse II | E89: Nurse II | F89: Nursing Service | G89: Nurse | H89: Nursing Division | I89: 16 | J89: =LOOKUP(Table1[[#This Row],[SALARY GRADE]],{1,2,3,4,5,6,7,8,9,10,11,12,13,14,15,16,17,18,19,20,21,22,23,24,25,26,27,28,29,30,31,32,33},{14364,15522,16486,17506,18581,19716,20914,22423,24329,26917,31705,33947,36125,38764,42178,45694,49562,53818,59153,66052,73303,81796,91306,102603,116643,131807,148940,167129,187531,210718,300961,356237,449157}) -> 45694 | K89: 2nd | L89: =IF(Table1[[#This Row],[LAST]]="","Unfilled","Filled") -> Filled | M89: Cargo | N89: Jerome | O89: Enrile | Q89: 32199 | R89: 44971 | S89: 44971 | T89: 45888 | U89: Married | V89: Male | W89: =DATEDIF(Q89,TODAY(),"Y") -> 38 | X89: =IF(ABS(Table1[[#This Row],[AGE]])>59,"60 and above",IF(ABS(Table1[[#This Row],[AGE]])>49,"50-59",IF(ABS(Table1[[#This Row],[AGE]])>39,"40-49",IF(ABS(Table1[[#This Row],[AGE]])>29,"30-39",IF(ABS(Table1[[#This Row],[AGE]])>19,"20-29",""))))) -> 30-39 | Y89: Manila | Z89: 41 A-Annex Camella Homes | AA89: Salinas IV | AB89: Bacoor City | AC89: Cavite | AD89: 4102 | AE89: College Graduate | AF89: BS Nursing | AG89: RA 1080 | AH89: 0594804 | AI89: 45714 | AJ89: 2006264741 | AK89: 1211-3275-3682 | AL89: 0802-2587-6905 | AM89: 341-643-794 | AN89: 0995-799-4359 | AO89: (046) 472-1322 | AP89: jeromenrilecargo@gmail.com
A90: 89 | B90: OSEC-DOHB-NURS2-270018-2022 | C90: Nurse II | E90: Nurse II | F90: Nursing Service | G90: Nurse | H90: Nursing Division | I90: 16 | J90: =LOOKUP(Table1[[#This Row],[SALARY GRADE]],{1,2,3,4,5,6,7,8,9,10,11,12,13,14,15,16,17,18,19,20,21,22,23,24,25,26,27,28,29,30,31,32,33},{14364,15522,16486,17506,18581,19716,20914,22423,24329,26917,31705,33947,36125,38764,42178,45694,49562,53818,59153,66052,73303,81796,91306,102603,116643,131807,148940,167129,187531,210718,300961,356237,449157}) -> 45694 | K90: 2nd | L90: =IF(Table1[[#This Row],[LAST]]="","Unfilled","Filled") -> Filled | M90: Bustos | N90: Jan-rael | O90: Dones | Q90: 33976 | R90: 44334 | S90: 44334 | T90: 44844 | U90: Married | V90: Male | W90: =DATEDIF(Q90,TODAY(),"Y") -> 33 | X90: =IF(ABS(Table1[[#This Row],[AGE]])>59,"60 and above",IF(ABS(Table1[[#This Row],[AGE]])>49,"50-59",IF(ABS(Table1[[#This Row],[AGE]])>39,"40-49",IF(ABS(Table1[[#This Row],[AGE]])>29,"30-39",IF(ABS(Table1[[#This Row],[AGE]])>19,"20-29",""))))) -> 30-39 | Y90: Cavite City | Z90: 25 | AA90: Tanzang Luma 5 | AB90: Imus City | AC90: Cavite | AD90: 4103 | AE90: College Graduate | AF90: BS Nursing | AG90: RA 1080 | AH90: 0810121 | AI90: 45664 | AJ90: 2005911415 | AK90: 1211-2147-7212 | AL90: 0802-5791-5933 | AM90: 454-073-202 | AN90: 0905-521-7780 | AO90: (046) 437-8043 | AP90: janraelbustos@gmail.com
A91: 90 | B91: OSEC-DOHB-NURS2-270019-2022 | C91: Nurse II | E91: Nurse II | F91: Nursing Service | G91: Nurse | H91: Nursing Division | I91: 16 | J91: =LOOKUP(Table1[[#This Row],[SALARY GRADE]],{1,2,3,4,5,6,7,8,9,10,11,12,13,14,15,16,17,18,19,20,21,22,23,24,25,26,27,28,29,30,31,32,33},{14364,15522,16486,17506,18581,19716,20914,22423,24329,26917,31705,33947,36125,38764,42178,45694,49562,53818,59153,66052,73303,81796,91306,102603,116643,131807,148940,167129,187531,210718,300961,356237,449157}) -> 45694 | K91: 2nd | L91: =IF(Table1[[#This Row],[LAST]]="","Unfilled","Filled") -> Filled | M91: Matic | N91: Marilou | O91: Lising | Q91: 29378 | R91: 45019 | S91: 45019 | T91: 45453 | U91: Single | V91: Female | W91: =DATEDIF(Q91,TODAY(),"Y") -> 46 | X91: =IF(ABS(Table1[[#This Row],[AGE]])>59,"60 and above",IF(ABS(Table1[[#This Row],[AGE]])>49,"50-59",IF(ABS(Table1[[#This Row],[AGE]])>39,"40-49",IF(ABS(Table1[[#This Row],[AGE]])>29,"30-39",IF(ABS(Table1[[#This Row],[AGE]])>19,"20-29",""))))) -> 40-49 | Y91: San Fernando, La Union | Z91: B10 L40 P1 Bonn St., Pallas Athena Executive Village | AA91: Anabu II-C | AB91: Imus City | AC91: Cavite | AD91: 4103 | AE91: College Graduate | AF91: BS Nursing | AG91: RA 1080 | AH91: 0823330 | AI91: 46179 | AJ91: 2006306639 | AK91: 1210-3452-7016 | AL91: 1905-0136-8338 | AM91: 207-364-089 | AN91: 0960-696-2685 | AO91: (046) 431-3007 | AP91: mariloumatic@gmail.com
A92: 91 | B92: OSEC-DOHB-NURS2-270020-2022 | C92: Nurse II | E92: Nurse II | F92: Nursing Service | G92: Nurse | H92: Nursing Division | I92: 16 | J92: =LOOKUP(Table1[[#This Row],[SALARY GRADE]],{1,2,3,4,5,6,7,8,9,10,11,12,13,14,15,16,17,18,19,20,21,22,23,24,25,26,27,28,29,30,31,32,33},{14364,15522,16486,17506,18581,19716,20914,22423,24329,26917,31705,33947,36125,38764,42178,45694,49562,53818,59153,66052,73303,81796,91306,102603,116643,131807,148940,167129,187531,210718,300961,356237,449157}) -> 45694 | K92: 2nd | L92: =IF(Table1[[#This Row],[LAST]]="","Unfilled","Filled") -> Filled | M92: Encarnacion | N92: Revin Anjulia | O92: Laderas | Q92: 33177 | R92: 44971 | S92: 44971 | T92: 45383 | U92: Married | V92: Female | W92: =DATEDIF(Q92,TODAY(),"Y") -> 35 | X92: =IF(ABS(Table1[[#This Row],[AGE]])>59,"60 and above",IF(ABS(Table1[[#This Row],[AGE]])>49,"50-59",IF(ABS(Table1[[#This Row],[AGE]])>39,"40-49",IF(ABS(Table1[[#This Row],[AGE]])>29,"30-39",IF(ABS(Table1[[#This Row],[AGE]])>19,"20-29",""))))) -> 30-39 | Y92: Cavite City | Z92: 182 | AA92: Tabon I | AB92: Kawit | AC92: Cavite | AD92: 4104 | AE92: College Graduate | AF92: BS Nursing | AG92: RA 1080 | AH92: 0787539 | AI92: 45961 | AJ92: 2006264720 | AK92: 1212-1677-1161 | AL92: 0105-1786-7115 | AM92: 313-500-518 | AN92: 0916-431-7095 | AO92: N/A | AP92: laderasrevin@yahoo.com
A93: 92 | B93: OSEC-DOHB-NURS2-270021-2022 | C93: Nurse II | E93: Nurse II | F93: Nursing Service | G93: Nurse | H93: Nursing Division | I93: 16 | J93: =LOOKUP(Table1[[#This Row],[SALARY GRADE]],{1,2,3,4,5,6,7,8,9,10,11,12,13,14,15,16,17,18,19,20,21,22,23,24,25,26,27,28,29,30,31,32,33},{14364,15522,16486,17506,18581,19716,20914,22423,24329,26917,31705,33947,36125,38764,42178,45694,49562,53818,59153,66052,73303,81796,91306,102603,116643,131807,148940,167129,187531,210718,300961,356237,449157}) -> 45694 | K93: 2nd | L93: =IF(Table1[[#This Row],[LAST]]="","Unfilled","Filled") -> Filled | M93: Omiles | N93: Lorenze | O93: Sayaman | Q93: 33156 | R93: 44334 | S93: 44334 | T93: 44844 | U93: Single | V93: Male | W93: =DATEDIF(Q93,TODAY(),"Y") -> 35 | X93: =IF(ABS(Table1[[#This Row],[AGE]])>59,"60 and above",IF(ABS(Table1[[#This Row],[AGE]])>49,"50-59",IF(ABS(Table1[[#This Row],[AGE]])>39,"40-49",IF(ABS(Table1[[#This Row],[AGE]])>29,"30-39",IF(ABS(Table1[[#This Row],[AGE]])>19,"20-29",""))))) -> 30-39 | Y93: Cavite City | Z93: Ipil St., Seaview | AA93: San Rafael II | AB93: Noveleta | AC93: Cavite | AD93: 4105 | AE93: College Graduate | AF93: BS Nursing | AG93: RA 1080 | AH93: 0722059 | AI93: 46305 | AJ93: 2005662334 | AK93: 1211-3520-5693 | AL93: 0802-5883-8193 | AM93: 443-617-969 | AN93: 0915-472-1145 | AO93: (046) 438-7216 | AP93: renzeomiles@gmail.com
A94: 93 | B94: OSEC-DOHB-NURS2-270022-2022 | C94: Nurse II | E94: Nurse II | F94: Nursing Service | G94: Nurse | H94: Nursing Division | I94: 16 | J94: =LOOKUP(Table1[[#This Row],[SALARY GRADE]],{1,2,3,4,5,6,7,8,9,10,11,12,13,14,15,16,17,18,19,20,21,22,23,24,25,26,27,28,29,30,31,32,33},{14364,15522,16486,17506,18581,19716,20914,22423,24329,26917,31705,33947,36125,38764,42178,45694,49562,53818,59153,66052,73303,81796,91306,102603,116643,131807,148940,167129,187531,210718,300961,356237,449157}) -> 45694 | K94: 2nd | L94: =IF(Table1[[#This Row],[LAST]]="","Unfilled","Filled") -> Filled | M94: Pabalinas | N94: Laarnie | O94: Temporaza | Q94: 32411 | R94: 44348 | S94: 44348 | T94: 44844 | U94: Married | V94: Female | W94: =DATEDIF(Q94,TODAY(),"Y") -> 37 | X94: =IF(ABS(Table1[[#This Row],[AGE]])>59,"60 and above",IF(ABS(Table1[[#This Row],[AGE]])>49,"50-59",IF(ABS(Table1[[#This Row],[AGE]])>39,"40-49",IF(ABS(Table1[[#This Row],[AGE]])>29,"30-39",IF(ABS(Table1[[#This Row],[AGE]])>19,"20-29",""))))) -> 30-39 | Y94: Tangalan, Aklan | Z94: B2 L11 Santan St., City Homes | AA94: Molino IV | AB94: Bacoor City | AC94: Cavite | AD94: 4102 | AE94: College Graduate | AF94: BS Nursing | AG94: RA 1080 | AH94: 0626820 | AI94: 46290 | AJ94: 2005670348 | AK94: 1210-0967-9568 | AL94: 0202-5373-7892 | AM94: 400-381-846 | AN94: 0926-478-0259 | AO94: N/A | AP94: laarnietemporaza@gmail.com
A95: 94 | B95: OSEC-DOHB-NURS2-270023-2022 | C95: Nurse II | E95: Nurse II | F95: Nursing Service | G95: Nurse | H95: Nursing Division | I95: 16 | J95: =LOOKUP(Table1[[#This Row],[SALARY GRADE]],{1,2,3,4,5,6,7,8,9,10,11,12,13,14,15,16,17,18,19,20,21,22,23,24,25,26,27,28,29,30,31,32,33},{14364,15522,16486,17506,18581,19716,20914,22423,24329,26917,31705,33947,36125,38764,42178,45694,49562,53818,59153,66052,73303,81796,91306,102603,116643,131807,148940,167129,187531,210718,300961,356237,449157}) -> 45694 | K95: 2nd | L95: Filled | M95: Abrigo | N95: Mae Hazel Jade | O95: Solis | Q95: 32118 | R95: 44336 | S95: 44336 | T95: 44949 | U95: Married | V95: Female | W95: =DATEDIF(Q95,TODAY(),"Y") -> 38 | X95: =IF(ABS(Table1[[#This Row],[AGE]])>59,"60 and above",IF(ABS(Table1[[#This Row],[AGE]])>49,"50-59",IF(ABS(Table1[[#This Row],[AGE]])>39,"40-49",IF(ABS(Table1[[#This Row],[AGE]])>29,"30-39",IF(ABS(Table1[[#This Row],[AGE]])>19,"20-29",""))))) -> 30-39 | Y95: Cavite City | Z95: 289 Dona Epifania St., Josephine Subd. | AA95: Panamitan | AB95: Kawit | AC95: Cavite | AD95: 4104 | AE95: College Graduate | AF95: BS Nursing | AG95: RA 1080 | AH95: 0733029 | AI95: 46728 | AJ95: 2005421317 | AK95: 1212-2829-6828 | AL95: 0805-1118-1856 | AM95: 279-624-810 | AN95: 0915-087-2567 | AO95: N/A | AP95: mjade_27@yahoo.com
A96: 95 | B96: OSEC-DOHB-NURS2-270024-2022 | C96: Nurse II | E96: Nurse II | F96: Nursing Service | G96: Nurse | H96: Nursing Division | I96: 16 | J96: =LOOKUP(Table1[[#This Row],[SALARY GRADE]],{1,2,3,4,5,6,7,8,9,10,11,12,13,14,15,16,17,18,19,20,21,22,23,24,25,26,27,28,29,30,31,32,33},{14364,15522,16486,17506,18581,19716,20914,22423,24329,26917,31705,33947,36125,38764,42178,45694,49562,53818,59153,66052,73303,81796,91306,102603,116643,131807,148940,167129,187531,210718,300961,356237,449157}) -> 45694 | K96: 2nd | L96: =IF(Table1[[#This Row],[LAST]]="","Unfilled","Filled") -> Filled | M96: Aragon | N96: Kristine | O96: Villegas | Q96: 31657 | R96: 44348 | S96: 44348 | T96: 44950 | U96: Single | V96: Female | W96: =DATEDIF(Q96,TODAY(),"Y") -> 39 | X96: =IF(ABS(Table1[[#This Row],[AGE]])>59,"60 and above",IF(ABS(Table1[[#This Row],[AGE]])>49,"50-59",IF(ABS(Table1[[#This Row],[AGE]])>39,"40-49",IF(ABS(Table1[[#This Row],[AGE]])>29,"30-39",IF(ABS(Table1[[#This Row],[AGE]])>19,"20-29",""))))) -> 30-39 | Y96: Las Piñas City | Z96: B4 L2 J. Abad Santos St., Cherryhomes Subd. | AA96: Mambog I | AB96: Bacoor City | AC96: Cavite | AD96: 4102 | AE96: College Graduate | AF96: BS Nursing | AG96: RA 1080 | AH96: 0521791 | AI96: 46632 | AJ96: 2005666507 | AK96: 1211-8534-9273 | AL96: 0802-6493-1669 | AM96: 728-099-008 | AN96: 0927-438-7330 | AO96: (046) 438-3442 | AP96: kvillegasaragon@gmail.com
A97: 96 | B97: OSEC-DOHB-NURS2-270025-2022 | C97: Nurse II | E97: Nurse II | F97: Nursing Service | G97: Nurse | H97: Nursing Division | I97: 16 | J97: =LOOKUP(Table1[[#This Row],[SALARY GRADE]],{1,2,3,4,5,6,7,8,9,10,11,12,13,14,15,16,17,18,19,20,21,22,23,24,25,26,27,28,29,30,31,32,33},{14364,15522,16486,17506,18581,19716,20914,22423,24329,26917,31705,33947,36125,38764,42178,45694,49562,53818,59153,66052,73303,81796,91306,102603,116643,131807,148940,167129,187531,210718,300961,356237,449157}) -> 45694 | K97: 2nd | L97: =IF(Table1[[#This Row],[LAST]]="","Unfilled","Filled") -> Filled | M97: Balmes-Bernardo | N97: Kimberly | O97: Mendoza | Q97: 33562 | R97: 44504 | S97: 44504 | T97: 44963 | U97: Married | V97: Female | W97: =DATEDIF(Q97,TODAY(),"Y") -> 34 | X97: =IF(ABS(Table1[[#This Row],[AGE]])>59,"60 and above",IF(ABS(Table1[[#This Row],[AGE]])>49,"50-59",IF(ABS(Table1[[#This Row],[AGE]])>39,"40-49",IF(ABS(Table1[[#This Row],[AGE]])>29,"30-39",IF(ABS(Table1[[#This Row],[AGE]])>19,"20-29",""))))) -> 30-39 | Y97: Lipa, Batangas | Z97: B3 L12 Josefina St., Baytown Village | AA97: Habay I | AB97: Bacoor City | AC97: Cavite | AD97: 4102 | AE97: College Graduate | AF97: BS Nursing | AG97: RA 1080 | AH97: 0791181 | AI97: 46346 | AJ97: 2005990730 | AK97: 1210-9220-2074 | AL97: 0802-5531-0503 | AM97: 437-895-944 | AN97: 0910-509-3921 | AO97: (046) 434-3644 | AP97: kim_shimmerinluv@yahoo.com.ph
A98: 97 | B98: OSEC-DOHB-NURS2-270026-2022 | C98: Nurse II | E98: Nurse II | F98: Nursing Service | G98: Nurse | H98: Nursing Division | I98: 16 | J98: =LOOKUP(Table1[[#This Row],[SALARY GRADE]],{1,2,3,4,5,6,7,8,9,10,11,12,13,14,15,16,17,18,19,20,21,22,23,24,25,26,27,28,29,30,31,32,33},{14364,15522,16486,17506,18581,19716,20914,22423,24329,26917,31705,33947,36125,38764,42178,45694,49562,53818,59153,66052,73303,81796,91306,102603,116643,131807,148940,167129,187531,210718,300961,356237,449157}) -> 45694 | K98: 2nd | L98: =IF(Table1[[#This Row],[LAST]]="","Unfilled","Filled") -> Filled | M98: Gervacio | N98: Kristina | O98: Santelices | Q98: 31755 | R98: 43466 | S98: 44363 | T98: 44949 | U98: Married | V98: Female | W98: =DATEDIF(Q98,TODAY(),"Y") -> 39 | X98: =IF(ABS(Table1[[#This Row],[AGE]])>59,"60 and above",IF(ABS(Table1[[#This Row],[AGE]])>49,"50-59",IF(ABS(Table1[[#This Row],[AGE]])>39,"40-49",IF(ABS(Table1[[#This Row],[AGE]])>29,"30-39",IF(ABS(Table1[[#This Row],[AGE]])>19,"20-29",""))))) -> 30-39 | Y98: Bacoor City, Cavite | Z98: 48 | AA98: Niog I | AB98: Bacoor City | AC98: Cavite | AD98: 4102 | AE98: College Graduate | AF98: BS Nursing | AG98: RA 1080 | AH98: 643600 | AI98: 46000 | AJ98: 2005532112 | AK98: 1210-9090-1538 | AL98: 0105-0895-2215 | AM98: 313-700-540 | AN98: 0977-257-0315 | AO98: N/A | AP98: kristinagervacio09@gmail.com
A99: 98 | B99: OSEC-DOHB-NURS2-270027-2022 | C99: Nurse II | E99: Nurse II | F99: Nursing Service | G99: Nurse | H99: Nursing Division | I99: 16 | J99: =LOOKUP(Table1[[#This Row],[SALARY GRADE]],{1,2,3,4,5,6,7,8,9,10,11,12,13,14,15,16,17,18,19,20,21,22,23,24,25,26,27,28,29,30,31,32,33},{14364,15522,16486,17506,18581,19716,20914,22423,24329,26917,31705,33947,36125,38764,42178,45694,49562,53818,59153,66052,73303,81796,91306,102603,116643,131807,148940,167129,187531,210718,300961,356237,449157}) -> 45694 | K99: 2nd | L99: =IF(Table1[[#This Row],[LAST]]="","Unfilled","Filled") -> Filled | M99: Vargas | N99: Camille | O99: Cabases | Q99: 33150 | R99: 44946 | S99: 44946 | T99: 45474 | U99: Single | V99: Female | W99: =DATEDIF(Q99,TODAY(),"Y") -> 35 | X99: =IF(ABS(Table1[[#This Row],[AGE]])>59,"60 and above",IF(ABS(Table1[[#This Row],[AGE]])>49,"50-59",IF(ABS(Table1[[#This Row],[AGE]])>39,"40-49",IF(ABS(Table1[[#This Row],[AGE]])>29,"30-39",IF(ABS(Table1[[#This Row],[AGE]])>19,"20-29",""))))) -> 30-39 | Y99: Rosario, Cavite | Z99: 05 Rosal St. Cuevas Subd. | AA99: Salcedo I | AB99: Noveleta | AC99: Cavite | AD99: 4015 | AE99: College Graduate | AF99: BS Nursing | AG99: RA 1080 | AH99: 0718618 | AI99: 46664 | AJ99: 2006264726 | AK99: 1210-2587-7482 | AL99: 0805-1205-2251 | AM99: 311-046-430 | AN99: 0939-310-1805 | AO99: (046) 438-1874 | AP99: camillevargas2000@gmail.com
A100: 99 | B100: OSEC-DOHB-NURS2-270028-2022 | C100: Nurse II | E100: Nurse II | F100: Nursing Service | G100: Nurse | H100: Nursing Division | I100: 16 | J100: =LOOKUP(Table1[[#This Row],[SALARY GRADE]],{1,2,3,4,5,6,7,8,9,10,11,12,13,14,15,16,17,18,19,20,21,22,23,24,25,26,27,28,29,30,31,32,33},{14364,15522,16486,17506,18581,19716,20914,22423,24329,26917,31705,33947,36125,38764,42178,45694,49562,53818,59153,66052,73303,81796,91306,102603,116643,131807,148940,167129,187531,210718,300961,356237,449157}) -> 45694 | K100: 2nd | L100: =IF(Table1[[#This Row],[LAST]]="","Unfilled","Filled") -> Filled | M100: Lorenzo | N100: Ghia Lariza | O100: Flores | Q100: 33440 | R100: 44636 | S100: 44636 | T100: 45078 | U100: Married | V100: Female | W100: =DATEDIF(Q100,TODAY(),"Y") -> 35 | X100: =IF(ABS(Table1[[#This Row],[AGE]])>59,"60 and above",IF(ABS(Table1[[#This Row],[AGE]])>49,"50-59",IF(ABS(Table1[[#This Row],[AGE]])>39,"40-49",IF(ABS(Table1[[#This Row],[AGE]])>29,"30-39",IF(ABS(Table1[[#This Row],[AGE]])>19,"20-29",""))))) -> 30-39 | Y100: Manila | Z100: B7 L39 P1 Main Rd., Villa Antonina Subd. | AA100: San Nicolas II | AB100: Bacoor City | AC100: Cavite | AD100: 4102 | AE100: College Graduate | AF100: BS Nursing | AG100: RA 1080 | AH100: 0761706 | AI100: 46589 | AJ100: 2006064855 | AK100: 1211-7639-2526 | AL100: 0802-5683-8110 | AM100: 478-185-001 | AN100: 0926-145-7343 | AO100: N/A | AP100: ghialorenzo123@gmail.com
...

Sheet DASHBOARD
V1: Republic of the Philippines
V2: Department of Health | AS2: Table 4. Distribution of Permanent Employees by Division Assignment and Age Group
V3: SOUTHERN TAGALOG REGIONAL HOSPITAL | AS3: as of June 5, 2024
V4: Brgy. Habay II, City of Bacoor, Cavite
V5: Tel No. (046) 884-2810 / (046)435-1071 / (046)435-0742
V6: Email: HRMS@strh.doh.gov.ph
B8: Table 1. Status of Plantilla Position by Division | X8: Table 2. Distribution of Permanent Employees by Level, Division Assignment and Sex
B9: as of | K9: =TODAY() -> 46252 | AB9: as of | AD9: =TODAY() -> 46252
B22: Table 3. Distribution of Permanent Employees by CADRE
B23: as of | U23: =TODAY() -> 46252
B51: Prepared by: | Z51: Noted by:
B54: CEPRIANO EDUARDO J. MALAYA, MMHoA | Z54: WILMA P. BAYAS, MMHoA
B55: Administrative Assistant II | Z55: Administrative Officer V / HRMO III | AZ55: 7
B57: Table 4. Distribution of Permanent Employees by Position
B58: as of | U58: =TODAY() -> 46252
B100: Prepared by: | Z100: Noted by:
B104: CEPRIANO EDUARDO J. MALAYA, MMHoA | Z104: WILMA P. BAYAS, MMHoA
B105: Administrative Assistant II | Z105: Administrative Officer V / HRMO III
B148: Prepared by: | Z148: Noted by:
B153: CEPRIANO EDUARDO J. MALAYA, MMHoA | Z153: WILMA P. BAYAS, MMHoA
B154: Administrative Assistant II | Z154: Administrative Officer V / HRMO III

Sheet FormulaSheet
A4: Divisions | B4: Position | D4: Total | N4: Divisions | O4: Level | P4: SEX | R4: Total | T4: Divisions | U4: Level | X4: SEX | Z4: Total
B5: Filled | C5: Unfilled | O5: 1st | P5: Male | Q5: Female | U5: 1st | V5: 2nd | W5: 3rd | X5: Male | Y5: Female
A6: Hospital Operation and Patient Support Division | B6: =COUNTIFS(Table1[26],FormulaSheet!$A6,Table1[FILLED&UNFILLED],FormulaSheet!$B5) -> 52 | C6: =COUNTIFS(Table1[26],FormulaSheet!$A6,Table1[FILLED&UNFILLED],FormulaSheet!$C5) -> 2 | D6: =SUM(B6:C6) -> 54 | N6: Hospital Operation and Patient Support Division | O6: =COUNTIFS(Table1[26],FormulaSheet!N6,Table1[Level2],FormulaSheet!O5) -> 33 | P6: =COUNTIFS(Table1[26],FormulaSheet!N6,Table1[GENDER],FormulaSheet!P5,Table1[Level2],FormulaSheet!O5) -> 16 | Q6: =COUNTIFS(Table1[26],FormulaSheet!N6,Table1[GENDER],FormulaSheet!Q5,Table1[Level2],FormulaSheet!O5) -> 15 | R6: =SUM(P6:Q6) -> 31 | T6: Hospital Operation and Patient Support Division | U6: =O6 -> 33 | V6: =O14 -> 21 | W6: 0 | X6: =P6+P14 -> 23 | Y6: =Q6+Q14 -> 29 | Z6: =SUM(X6:Y6) -> 52
A7: Nursing Division | B7: =COUNTIFS(Table1[26],FormulaSheet!$A7,Table1[FILLED&UNFILLED],FormulaSheet!$B5) -> 138 | C7: =COUNTIFS(Table1[26],FormulaSheet!$A7,Table1[FILLED&UNFILLED],FormulaSheet!$C5) -> 3 | D7: =SUM(B7:C7) -> 141 | N7: Nursing Division | O7: =COUNTIFS(Table1[26],FormulaSheet!N7,Table1[Level2],FormulaSheet!O5) -> 42 | P7: =COUNTIFS(Table1[26],FormulaSheet!N7,Table1[GENDER],FormulaSheet!P5,Table1[Level2],FormulaSheet!O5) -> 12 | Q7: =COUNTIFS(Table1[26],FormulaSheet!N7,Table1[GENDER],FormulaSheet!Q5,Table1[Level2],FormulaSheet!O5) -> 30 | R7: =SUM(P7:Q7) -> 42 | T7: Nursing Division | U7: =O7 -> 42 | V7: =O15 -> 99 | W7: 0 | X7: =P7+P15 -> 37 | Y7: =Q7+Q15 -> 101 | Z7: =SUM(X7:Y7) -> 138
A8: Medical Division | B8: =COUNTIFS(Table1[26],FormulaSheet!$A8,Table1[FILLED&UNFILLED],FormulaSheet!$B5) -> 108 | C8: =COUNTIFS(Table1[26],FormulaSheet!$A8,Table1[FILLED&UNFILLED],FormulaSheet!$C5) -> 4 | D8: =SUM(B8:C8) -> 112 | N8: Medical Division | O8: =COUNTIFS(Table1[26],FormulaSheet!N8,Table1[Level2],FormulaSheet!O5) -> 19 | P8: =COUNTIFS(Table1[26],FormulaSheet!N8,Table1[GENDER],FormulaSheet!P5,Table1[Level2],FormulaSheet!O5) -> 8 | Q8: =COUNTIFS(Table1[26],FormulaSheet!N8,Table1[GENDER],FormulaSheet!Q5,Table1[Level2],FormulaSheet!O5) -> 11 | R8: =SUM(P8:Q8) -> 19 | T8: Medical Division | U8: =O8 -> 19 | V8: =O16 -> 91 | W8: =R25 -> 2 | X8: =P8+P16+P24 -> 41 | Y8: =Q8+Q16+Q24 -> 66 | Z8: =SUM(X8:Y8) -> 107
A9: Total | B9: =SUM(B6:B8) -> 298 | C9: =SUM(C6:C8) -> 9 | D9: =SUM(D6:D8) -> 307 | N9: Total | O9: =SUM(O6:O8) -> 94 | P9: =SUM(P6:P8) -> 36 | Q9: =SUM(Q6:Q8) -> 56 | R9: =SUM(R6:R8) -> 92 | T9: Total | U9: =SUM(U6:U8) -> 94 | V9: =SUM(V6:V8) -> 211 | W9: =SUM(W6:W8) -> 2 | X9: =SUM(X6:X8) -> 101 | Y9: =SUM(Y6:Y8) -> 196 | Z9: =SUM(Z6:Z8) -> 297
N12: Divisions | O12: Level | P12: SEX | R12: Total
A13: Divisions | B13: SEX | D13: Total | O13: 2nd | P13: Male | Q13: Female
B14: Male | C14: Female | N14: Hospital Operation and Patient Support Division | O14: =COUNTIFS(Table1[26],FormulaSheet!N14,Table1[Level2],FormulaSheet!O13) -> 21 | P14: =COUNTIFS(Table1[26],FormulaSheet!N14,Table1[GENDER],FormulaSheet!P13,Table1[Level2],FormulaSheet!O13) -> 7 | Q14: =COUNTIFS(Table1[26],FormulaSheet!N14,Table1[GENDER],FormulaSheet!Q13,Table1[Level2],FormulaSheet!O13) -> 14 | R14: =SUM(P14:Q14) -> 21
A15: Hospital Operation and Patient Support Division | B15: =COUNTIFS(Table1[26],FormulaSheet!A15,Table1[GENDER],FormulaSheet!B14) -> 23 | C15: =COUNTIFS(Table1[26],FormulaSheet!A15,Table1[GENDER],FormulaSheet!C14) -> 29 | D15: =SUM(B15:C15) -> 52 | N15: Nursing Division | O15: =COUNTIFS(Table1[26],FormulaSheet!N15,Table1[Level2],FormulaSheet!O13) -> 99 | P15: =COUNTIFS(Table1[26],FormulaSheet!N15,Table1[GENDER],FormulaSheet!P13,Table1[Level2],FormulaSheet!O13) -> 25 | Q15: =COUNTIFS(Table1[26],FormulaSheet!N15,Table1[GENDER],FormulaSheet!Q13,Table1[Level2],FormulaSheet!O13) -> 71 | R15: =SUM(P15:Q15) -> 96
A16: Nursing Division | B16: =COUNTIFS(Table1[26],FormulaSheet!A16,Table1[GENDER],FormulaSheet!B14) -> 37 | C16: =COUNTIFS(Table1[26],FormulaSheet!A16,Table1[GENDER],FormulaSheet!C14) -> 101 | D16: =SUM(B16:C16) -> 138 | N16: Medical Division | O16: =COUNTIFS(Table1[26],FormulaSheet!N16,Table1[Level2],FormulaSheet!O13) -> 91 | P16: =COUNTIFS(Table1[26],FormulaSheet!N16,Table1[GENDER],FormulaSheet!P13,Table1[Level2],FormulaSheet!O13) -> 32 | Q16: =COUNTIFS(Table1[26],FormulaSheet!N16,Table1[GENDER],FormulaSheet!Q13,Table1[Level2],FormulaSheet!O13) -> 54 | R16: =SUM(P16:Q16) -> 86
A17: Medical Division | B17: =COUNTIFS(Table1[26],FormulaSheet!A17,Table1[GENDER],FormulaSheet!B14) -> 41 | C17: =COUNTIFS(Table1[26],FormulaSheet!A17,Table1[GENDER],FormulaSheet!C14) -> 66 | D17: =SUM(B17:C17) -> 107 | N17: Total | O17: =SUM(O14:O16) -> 211 | P17: =SUM(P14:P16) -> 64 | Q17: =SUM(Q14:Q16) -> 139 | R17: =SUM(R14:R16) -> 203
A18: Total | B18: =SUM(B15:B17) -> 101 | C18: =SUM(C15:C17) -> 196 | D18: =SUM(D15:D17) -> 297
N20: Divisions | O20: Level | P20: SEX | R20: Total
O21: 3rd | P21: Male | Q21: Female
N22: Hospital Operation and Patient Support Division | O22: =COUNTIFS(Table1[26],FormulaSheet!N22,Table1[Level2],FormulaSheet!O21) -> 0 | P22: =COUNTIFS(Table1[26],FormulaSheet!N22,Table1[GENDER],FormulaSheet!P21,Table1[Level2],FormulaSheet!O21) -> 0 | Q22: =COUNTIFS(Table1[26],FormulaSheet!N22,Table1[GENDER],FormulaSheet!Q21,Table1[Level2],FormulaSheet!O21) -> 0 | R22: =SUM(P22:Q22) -> 0
A23: Hospital Operation and Patient Support Division | B23: Position | D23: Total | N23: Nursing Division | O23: =COUNTIFS(Table1[26],FormulaSheet!N23,Table1[Level2],FormulaSheet!O22) -> 0 | P23: =COUNTIFS(Table1[26],FormulaSheet!N23,Table1[GENDER],FormulaSheet!P22,Table1[Level2],FormulaSheet!O22) -> 0 | Q23: =COUNTIFS(Table1[26],FormulaSheet!N23,Table1[GENDER],FormulaSheet!Q22,Table1[Level2],FormulaSheet!O22) -> 0 | R23: =SUM(P23:Q23) -> 0
B24: Filled | C24: Unfilled | N24: Medical Division | O24: =COUNTIFS(Table1[26],FormulaSheet!N24,Table1[Level2],FormulaSheet!O21) -> 2 | P24: =COUNTIFS(Table1[26],FormulaSheet!N24,Table1[GENDER],FormulaSheet!P21,Table1[Level2],FormulaSheet!O21) -> 1 | Q24: =COUNTIFS(Table1[26],FormulaSheet!N24,Table1[GENDER],FormulaSheet!Q21,Table1[Level2],FormulaSheet!O21) -> 1 | R24: =SUM(P24:Q24) -> 2
A25: Accountant | B25: =COUNTIFS(Table1[CADRE],FormulaSheet!$A25,Table1[26],FormulaSheet!A23,Table1[FILLED&UNFILLED],FormulaSheet!B$24) -> 2 | C25: =COUNTIFS(Table1[CADRE],FormulaSheet!$A25,Table1[FILLED&UNFILLED],FormulaSheet!C$24) -> 0 | D25: =SUM(B25:C25) -> 2 | N25: Total | O25: =SUM(O22:O24) -> 2 | P25: =SUM(P22:P24) -> 1 | Q25: =SUM(Q22:Q24) -> 1 | R25: =SUM(R22:R24) -> 2
A26: Administrative Aide | B26: =COUNTIFS(Table1[CADRE],FormulaSheet!$A26,Table1[26],FormulaSheet!A23,Table1[FILLED&UNFILLED],FormulaSheet!B$24) -> 15 | C26: =COUNTIFS(Table1[CADRE],FormulaSheet!$A26,Table1[FILLED&UNFILLED],FormulaSheet!C$24) -> 1 | D26: =SUM(B26:C26) -> 16
A27: Administrative Assistant | B27: =COUNTIFS(Table1[CADRE],FormulaSheet!$A27,Table1[26],FormulaSheet!A23,Table1[FILLED&UNFILLED],FormulaSheet!B$24) -> 10 | C27: =COUNTIFS(Table1[CADRE],FormulaSheet!$A27,Table1[FILLED&UNFILLED],FormulaSheet!C$24) -> 1 | D27: =SUM(B27:C27) -> 11
A28: Administrative Officer | B28: =COUNTIFS(Table1[CADRE],FormulaSheet!$A28,Table1[26],FormulaSheet!A23,Table1[FILLED&UNFILLED],FormulaSheet!B$24) -> 15 | C28: =COUNTIFS(Table1[CADRE],FormulaSheet!$A28,Table1[FILLED&UNFILLED],FormulaSheet!C$24) -> 0 | D28: =SUM(B28:C28) -> 15
A29: Computer Maintenance Technologist | B29: =COUNTIFS(Table1[CADRE],FormulaSheet!$A29,Table1[FILLED&UNFILLED],FormulaSheet!B$24) -> 2 | C29: =COUNTIFS(Table1[CADRE],FormulaSheet!$A29,Table1[FILLED&UNFILLED],FormulaSheet!C$24) -> 0 | D29: =SUM(B29:C29) -> 2
A30: Engineer | B30: =COUNTIFS(Table1[CADRE],FormulaSheet!$A30,Table1[FILLED&UNFILLED],FormulaSheet!B$24) -> 2 | C30: =COUNTIFS(Table1[CADRE],FormulaSheet!$A30,Table1[FILLED&UNFILLED],FormulaSheet!C$24) -> 0 | D30: =SUM(B30:C30) -> 2
A31: Hospital Housekeeper | B31: =COUNTIFS(Table1[CADRE],FormulaSheet!$A31,Table1[FILLED&UNFILLED],FormulaSheet!B$24) -> 1 | C31: =COUNTIFS(Table1[CADRE],FormulaSheet!$A31,Table1[FILLED&UNFILLED],FormulaSheet!C$24) -> 0 | D31: =SUM(B31:C31) -> 1
A32: Laundry Worker | B32: =COUNTIFS(Table1[CADRE],FormulaSheet!$A32,Table1[FILLED&UNFILLED],FormulaSheet!B$24) -> 1 | C32: =COUNTIFS(Table1[CADRE],FormulaSheet!$A32,Table1[FILLED&UNFILLED],FormulaSheet!C$24) -> 0 | D32: =SUM(B32:C32) -> 1
A33: Medical Equipment Technician | B33: =COUNTIFS(Table1[CADRE],FormulaSheet!$A33,Table1[FILLED&UNFILLED],FormulaSheet!B$24) -> 2 | C33: =COUNTIFS(Table1[CADRE],FormulaSheet!$A33,Table1[FILLED&UNFILLED],FormulaSheet!C$24) -> 0 | D33: =SUM(B33:C33) -> 2
A34: Seamstress | B34: =COUNTIFS(Table1[CADRE],FormulaSheet!$A34,Table1[FILLED&UNFILLED],FormulaSheet!B$24) -> 1 | C34: =COUNTIFS(Table1[CADRE],FormulaSheet!$A34,Table1[FILLED&UNFILLED],FormulaSheet!C$24) -> 0 | D34: =SUM(B34:C34) -> 1
A35: Warehouseman | B35: =COUNTIFS(Table1[CADRE],FormulaSheet!$A35,Table1[FILLED&UNFILLED],FormulaSheet!B$24) -> 1 | C35: =COUNTIFS(Table1[CADRE],FormulaSheet!$A35,Table1[FILLED&UNFILLED],FormulaSheet!C$24) -> 0 | D35: =SUM(B35:C35) -> 1
A36: Total | B36: =SUM(B25:B35) -> 52 | C36: =SUM(C25:C35) -> 2 | D36: =SUM(D25:D35) -> 54
A39: Medical Division | B39: Position | D39: Total
B40: Filled | C40: Unfilled
A41: Administrative Aide | B41: =COUNTIFS(Table1[CADRE],FormulaSheet!$A41,Table1[26],FormulaSheet!$A39,Table1[FILLED&UNFILLED],FormulaSheet!B$40) -> 2 | C41: =COUNTIFS(Table1[26],FormulaSheet!$A41,Table1[SALARY GRADE],FormulaSheet!$A39,Table1[LAST],FormulaSheet!C$40) -> 0 | D41: =SUM(B41:C41) -> 2
A42: Administrative Assistant | B42: =COUNTIFS(Table1[CADRE],FormulaSheet!$A42,Table1[26],FormulaSheet!$A39,Table1[FILLED&UNFILLED],FormulaSheet!B$40) -> 6 | C42: =COUNTIFS(Table1[CADRE],FormulaSheet!$A42,Table1[26],FormulaSheet!$A39,Table1[FILLED&UNFILLED],FormulaSheet!C$40) -> 0 | D42: =SUM(B42:C42) -> 6
A43: Administrative Officer | B43: =COUNTIFS(Table1[CADRE],FormulaSheet!$A43,Table1[26],FormulaSheet!$A39,Table1[FILLED&UNFILLED],FormulaSheet!B$40) -> 3 | C43: =COUNTIFS(Table1[CADRE],FormulaSheet!$A43,Table1[26],FormulaSheet!$A39,Table1[FILLED&UNFILLED],FormulaSheet!C$40) -> 0 | D43: =SUM(B43:C43) -> 3
A44: Chemist | B44: =COUNTIFS(Table1[CADRE],FormulaSheet!$A44,Table1[FILLED&UNFILLED],FormulaSheet!B$40) -> 1 | C44: =COUNTIFS(Table1[CADRE],FormulaSheet!$A44,Table1[FILLED&UNFILLED],FormulaSheet!C$40) -> 0 | D44: =SUM(B44:C44) -> 1
A45: Cook | B45: =COUNTIFS(Table1[CADRE],FormulaSheet!$A45,Table1[FILLED&UNFILLED],FormulaSheet!B$40) -> 3 | C45: =COUNTIFS(Table1[CADRE],FormulaSheet!$A45,Table1[FILLED&UNFILLED],FormulaSheet!C$40) -> 0 | D45: =SUM(B45:C45) -> 3
A46: Data Controller | B46: =COUNTIFS(Table1[CADRE],FormulaSheet!$A46,Table1[FILLED&UNFILLED],FormulaSheet!B$40) -> 1 | C46: =COUNTIFS(Table1[CADRE],FormulaSheet!$A46,Table1[FILLED&UNFILLED],FormulaSheet!C$40) -> 0 | D46: =SUM(B46:C46) -> 1
A47: Dental Aide | B47: =COUNTIFS(Table1[CADRE],FormulaSheet!$A47,Table1[FILLED&UNFILLED],FormulaSheet!B$40) -> 1 | C47: =COUNTIFS(Table1[CADRE],FormulaSheet!$A47,Table1[FILLED&UNFILLED],FormulaSheet!C$40) -> 0 | D47: =SUM(B47:C47) -> 1
A48: Dentist | B48: =COUNTIFS(Table1[CADRE],FormulaSheet!$A48,Table1[FILLED&UNFILLED],FormulaSheet!B$40) -> 1 | C48: =COUNTIFS(Table1[CADRE],FormulaSheet!$A48,Table1[FILLED&UNFILLED],FormulaSheet!C$40) -> 1 | D48: =SUM(B48:C48) -> 2
A49: Health Education and Promotion Officer | B49: =COUNTIFS(Table1[CADRE],FormulaSheet!$A49,Table1[FILLED&UNFILLED],FormulaSheet!B$40) -> 1 | C49: =COUNTIFS(Table1[CADRE],FormulaSheet!$A49,Table1[FILLED&UNFILLED],FormulaSheet!C$40) -> 0 | D49: =SUM(B49:C49) -> 1
A50: Laboratory Aide | B50: =COUNTIFS(Table1[CADRE],FormulaSheet!$A50,Table1[FILLED&UNFILLED],FormulaSheet!B$40) -> 5 | C50: =COUNTIFS(Table1[CADRE],FormulaSheet!$A50,Table1[FILLED&UNFILLED],FormulaSheet!C$40) -> 0 | D50: =SUM(B50:C50) -> 5
A51: Medical Laboratory Technician | B51: =COUNTIFS(Table1[CADRE],FormulaSheet!$A51,Table1[FILLED&UNFILLED],FormulaSheet!B$40) -> 0 | C51: =COUNTIFS(Table1[CADRE],FormulaSheet!$A51,Table1[FILLED&UNFILLED],FormulaSheet!C$40) -> 0 | D51: =SUM(B51:C51) -> 0
A52: Medical Technologist | B52: =COUNTIFS(Table1[CADRE],FormulaSheet!$A52,Table1[FILLED&UNFILLED],FormulaSheet!B$40) -> 13 | C52: =COUNTIFS(Table1[CADRE],FormulaSheet!$A52,Table1[FILLED&UNFILLED],FormulaSheet!C$40) -> 1 | D52: =SUM(B52:C52) -> 14
A53: Nutritionist-Dietitian | B53: =COUNTIFS(Table1[CADRE],FormulaSheet!$A53,Table1[FILLED&UNFILLED],FormulaSheet!B$40) -> 2 | C53: =COUNTIFS(Table1[CADRE],FormulaSheet!$A53,Table1[FILLED&UNFILLED],FormulaSheet!C$40) -> 0 | D53: =SUM(B53:C53) -> 2
A54: Pharmacist | B54: =COUNTIFS(Table1[CADRE],FormulaSheet!$A54,Table1[FILLED&UNFILLED],FormulaSheet!B$40) -> 6 | C54: =COUNTIFS(Table1[CADRE],FormulaSheet!$A54,Table1[FILLED&UNFILLED],FormulaSheet!C$40) -> 0 | D54: =SUM(B54:C54) -> 6
A55: Physician | B55: =COUNTIFS(Table1[CADRE],FormulaSheet!$A55,Table1[FILLED&UNFILLED],FormulaSheet!B$40) -> 51 | C55: =COUNTIFS(Table1[CADRE],FormulaSheet!$A55,Table1[FILLED&UNFILLED],FormulaSheet!C$40) -> 0 | D55: =SUM(B55:C55) -> 51
... A61: Statistician | B61: =COUNTIFS(Table1[CADRE],FormulaSheet!$A61,Table1[FILLED&UNFILLED],FormulaSheet!B$40) -> 1 | C61: =COUNTIFS(Table1[CADRE],FormulaSheet!$A61,Table1[FILLED&UNFILLED],FormulaSheet!C$40) -> 0 | D61: =SUM(B61:C61) -> 1
A62: Total | B62: =SUM(B41:B61) -> 108 | C62: =SUM(C41:C61) -> 4 | D62: =SUM(D41:D61) -> 112
A65: Nursing Division | B65: Position | D65: Total
B66: Filled | C66: Unfilled
A67: Administrative Aide | B67: =COUNTIFS(Table1[CADRE],FormulaSheet!$A67,Table1[26],FormulaSheet!A65,Table1[FILLED&UNFILLED],FormulaSheet!B$66) -> 1 | C67: =COUNTIFS(Table1[CADRE],FormulaSheet!$A67,Table1[26],FormulaSheet!$A65,Table1[FILLED&UNFILLED],FormulaSheet!C$66) -> 0 | D67: =SUM(B67:C67) -> 1
A68: Midwife | B68: =COUNTIFS(Table1[CADRE],FormulaSheet!$A68,Table1[FILLED&UNFILLED],FormulaSheet!B$66) -> 3 | C68: =COUNTIFS(Table1[CADRE],FormulaSheet!$A68,Table1[FILLED&UNFILLED],FormulaSheet!C$66) -> 0 | D68: =SUM(B68:C68) -> 3
A69: Nurse | B69: =COUNTIFS(Table1[CADRE],FormulaSheet!$A69,Table1[FILLED&UNFILLED],FormulaSheet!B$66) -> 96 | C69: =COUNTIFS(Table1[CADRE],FormulaSheet!$A69,Table1[FILLED&UNFILLED],FormulaSheet!C$66) -> 3 | D69: =SUM(B69:C69) -> 99
A70: Nursing Attendant | B70: =COUNTIFS(Table1[CADRE],FormulaSheet!$A70,Table1[FILLED&UNFILLED],FormulaSheet!B$66) -> 38 | C70: =COUNTIFS(Table1[CADRE],FormulaSheet!$A70,Table1[FILLED&UNFILLED],FormulaSheet!C$66) -> 0 | D70: =SUM(B70:C70) -> 38
A71: Total | B71: =SUM(B67:B70) -> 138 | C71: =SUM(C67:C70) -> 3 | D71: =SUM(D67:D70) -> 141
A75: Division | B75: Age Group | G75: Total
B76: 20-29 | C76: 30-39 | D76: 40-49 | E76: 50-59 | F76: 60 and above
A77: Hospital Operation and Patient Support Division | B77: =COUNTIFS(Table1[26],FormulaSheet!A77,Table1[AGE GROUP],FormulaSheet!B76) -> 10 | C77: =COUNTIFS(Table1[26],FormulaSheet!A77,Table1[AGE GROUP],FormulaSheet!C76) -> 17 | D77: =COUNTIFS(Table1[26],FormulaSheet!A77,Table1[AGE GROUP],FormulaSheet!D76) -> 18 | E77: =COUNTIFS(Table1[26],FormulaSheet!A77,Table1[AGE GROUP],FormulaSheet!E76) -> 5 | F77: =COUNTIFS(Table1[26],FormulaSheet!A77,Table1[AGE GROUP],FormulaSheet!F76) -> 2 | G77: =SUM(B77:F77) -> 52
A78: Nursing Division | B78: =COUNTIFS(Table1[26],FormulaSheet!A78,Table1[AGE GROUP],FormulaSheet!B76) -> 5 | C78: =COUNTIFS(Table1[26],FormulaSheet!A78,Table1[AGE GROUP],FormulaSheet!C76) -> 84 | D78: =COUNTIFS(Table1[26],FormulaSheet!A78,Table1[AGE GROUP],FormulaSheet!D76) -> 38 | E78: =COUNTIFS(Table1[26],FormulaSheet!A78,Table1[AGE GROUP],FormulaSheet!E76) -> 11 | F78: =COUNTIFS(Table1[26],FormulaSheet!A78,Table1[AGE GROUP],FormulaSheet!F76) -> 0 | G78: =SUM(B78:F78) -> 138
A79: Medical Division | B79: =COUNTIFS(Table1[26],FormulaSheet!A79,Table1[AGE GROUP],FormulaSheet!B76) -> 12 | C79: =COUNTIFS(Table1[26],FormulaSheet!A79,Table1[AGE GROUP],FormulaSheet!C76) -> 54 | D79: =COUNTIFS(Table1[26],FormulaSheet!A79,Table1[AGE GROUP],FormulaSheet!D76) -> 21 | E79: =COUNTIFS(Table1[26],FormulaSheet!A79,Table1[AGE GROUP],FormulaSheet!E76) -> 17 | F79: =COUNTIFS(Table1[26],FormulaSheet!A79,Table1[AGE GROUP],FormulaSheet!F76) -> 3 | G79: =SUM(B79:F79) -> 107
A80: Total | B80: =SUM(B77:B79) -> 27 | C80: =SUM(C77:C79) -> 155 | D80: =SUM(D77:D79) -> 77 | E80: =SUM(E77:E79) -> 33 | F80: =SUM(F77:F79) -> 5 | G80: =SUM(B80:F80) -> 297
A89: Hospital Operation and Patient Support Division | B89: Position | D89: Total
B90: Filled | C90: Unfilled
A91: Accountant II | B91: =COUNTIFS(Table1[Parentetical],FormulaSheet!A91,Table1[26],FormulaSheet!A89,Table1[FILLED&UNFILLED],FormulaSheet!B90) -> 1 | C91: =COUNTIFS(Table1[Parentetical],FormulaSheet!A91,Table1[26],FormulaSheet!A89,Table1[FILLED&UNFILLED],FormulaSheet!C90) -> 0 | D91: =B91+C91 -> 1
A92: Accountant III | B92: =COUNTIFS(Table1[Parentetical],FormulaSheet!A92,Table1[26],FormulaSheet!A89,Table1[FILLED&UNFILLED],FormulaSheet!B90) -> 1 | C92: =COUNTIFS(Table1[Parentetical],FormulaSheet!A92,Table1[26],FormulaSheet!A89,Table1[FILLED&UNFILLED],FormulaSheet!C90) -> 0 | D92: =B92+C92 -> 1
A93: Administrative Aide III | B93: =COUNTIFS(Table1[Parentetical],FormulaSheet!A93,Table1[26],FormulaSheet!A89,Table1[FILLED&UNFILLED],FormulaSheet!B90) -> 2 | C93: =COUNTIFS(Table1[Parentetical],FormulaSheet!A93,Table1[26],FormulaSheet!A89,Table1[FILLED&UNFILLED],FormulaSheet!C90) -> 0 | D93: =B93+C93 -> 2
A94: Administrative Aide IV | B94: =COUNTIFS(Table1[Parentetical],FormulaSheet!A94,Table1[26],FormulaSheet!A89,Table1[FILLED&UNFILLED],FormulaSheet!B90) -> 5 | C94: =COUNTIFS(Table1[Parentetical],FormulaSheet!A94,Table1[26],FormulaSheet!A89,Table1[FILLED&UNFILLED],FormulaSheet!C90) -> 1 | D94: =B94+C94 -> 6
A95: Administrative Aide VI | B95: =COUNTIFS(Table1[Parentetical],FormulaSheet!A95,Table1[26],FormulaSheet!A89,Table1[FILLED&UNFILLED],FormulaSheet!B90) -> 8 | C95: =COUNTIFS(Table1[Parentetical],FormulaSheet!A95,Table1[26],FormulaSheet!A89,Table1[FILLED&UNFILLED],FormulaSheet!C90) -> 0 | D95: =B95+C95 -> 8
A96: Administrative Assistant I | B96: =COUNTIFS(Table1[Parentetical],FormulaSheet!A96,Table1[26],FormulaSheet!A89,Table1[FILLED&UNFILLED],FormulaSheet!B90) -> 3 | C96: =COUNTIFS(Table1[Parentetical],FormulaSheet!A96,Table1[26],FormulaSheet!A89,Table1[FILLED&UNFILLED],FormulaSheet!C90) -> 0 | D96: =B96+C96 -> 3
A97: Administrative Assistant II | B97: =COUNTIFS(Table1[Parentetical],FormulaSheet!A97,Table1[26],FormulaSheet!A89,Table1[FILLED&UNFILLED],FormulaSheet!B90) -> 5 | C97: =COUNTIFS(Table1[Parentetical],FormulaSheet!A97,Table1[26],FormulaSheet!A89,Table1[FILLED&UNFILLED],FormulaSheet!C90) -> 1 | D97: =B97+C97 -> 6
A98: Administrative Assistant III | B98: =COUNTIFS(Table1[Parentetical],FormulaSheet!A98,Table1[26],FormulaSheet!A89,Table1[FILLED&UNFILLED],FormulaSheet!B90) -> 2 | C98: =COUNTIFS(Table1[Parentetical],FormulaSheet!A98,Table1[26],FormulaSheet!A89,Table1[FILLED&UNFILLED],FormulaSheet!C90) -> 0 | D98: =B98+C98 -> 2
A99: Administrative Officer I | B99: =COUNTIFS(Table1[Parentetical],FormulaSheet!A99,Table1[26],FormulaSheet!A89,Table1[FILLED&UNFILLED],FormulaSheet!B90) -> 3 | C99: =COUNTIFS(Table1[Parentetical],FormulaSheet!A99,Table1[26],FormulaSheet!A89,Table1[FILLED&UNFILLED],FormulaSheet!C90) -> 0 | D99: =B99+C99 -> 3
A100: Administrative Officer II | B100: =COUNTIFS(Table1[Parentetical],FormulaSheet!A100,Table1[26],FormulaSheet!A89,Table1[FILLED&UNFILLED],FormulaSheet!B90) -> 3 | C100: =COUNTIFS(Table1[Parentetical],FormulaSheet!A100,Table1[26],FormulaSheet!A89,Table1[FILLED&UNFILLED],FormulaSheet!C90) -> 0 | D100: =B100+C100 -> 3
A101: Administrative Officer III | B101: =COUNTIFS(Table1[Parentetical],FormulaSheet!A101,Table1[26],FormulaSheet!A89,Table1[FILLED&UNFILLED],FormulaSheet!B90) -> 1 | C101: =COUNTIFS(Table1[Parentetical],FormulaSheet!A101,Table1[26],FormulaSheet!A89,Table1[FILLED&UNFILLED],FormulaSheet!C90) -> 0 | D101: =B101+C101 -> 1
A102: Administrative Officer IV | B102: =COUNTIFS(Table1[Parentetical],FormulaSheet!A102,Table1[26],FormulaSheet!A89,Table1[FILLED&UNFILLED],FormulaSheet!B90) -> 2 | C102: =COUNTIFS(Table1[Parentetical],FormulaSheet!A102,Table1[26],FormulaSheet!A89,Table1[FILLED&UNFILLED],FormulaSheet!C90) -> 0 | D102: =B102+C102 -> 2
A103: Administrative Officer V | B103: =COUNTIFS(Table1[Parentetical],FormulaSheet!A103,Table1[26],FormulaSheet!A89,Table1[FILLED&UNFILLED],FormulaSheet!B90) -> 5 | C103: =COUNTIFS(Table1[Parentetical],FormulaSheet!A103,Table1[26],FormulaSheet!A89,Table1[FILLED&UNFILLED],FormulaSheet!C90) -> 0 | D103: =B103+C103 -> 5
A104: Computer Maintenance Technologist II | B104: =COUNTIFS(Table1[Parentetical],FormulaSheet!A104,Table1[26],FormulaSheet!A89,Table1[FILLED&UNFILLED],FormulaSheet!B90) -> 1 | C104: =COUNTIFS(Table1[Parentetical],FormulaSheet!A104,Table1[26],FormulaSheet!A90,Table1[FILLED&UNFILLED],FormulaSheet!C91) -> 0 | D104: =B104+C104 -> 1
A105: Computer Maintenance Technologist I | B105: =COUNTIFS(Table1[Parentetical],FormulaSheet!A105,Table1[26],FormulaSheet!A89,Table1[FILLED&UNFILLED],FormulaSheet!B90) -> 1 | C105: =COUNTIFS(Table1[Parentetical],FormulaSheet!A105,Table1[26],FormulaSheet!A89,Table1[FILLED&UNFILLED],FormulaSheet!C90) -> 0 | D105: =B105+C105 -> 1
A106: Engineer II | B106: =COUNTIFS(Table1[Parentetical],FormulaSheet!A106,Table1[26],FormulaSheet!A89,Table1[FILLED&UNFILLED],FormulaSheet!B90) -> 1 | C106: =COUNTIFS(Table1[Parentetical],FormulaSheet!A106,Table1[26],FormulaSheet!A89,Table1[FILLED&UNFILLED],FormulaSheet!C90) -> 0 | D106: =B106+C106 -> 1
A107: Engineer III | B107: =COUNTIFS(Table1[Parentetical],FormulaSheet!A107,Table1[26],FormulaSheet!A89,Table1[FILLED&UNFILLED],FormulaSheet!B90) -> 1 | C107: =COUNTIFS(Table1[Parentetical],FormulaSheet!A107,Table1[26],FormulaSheet!A89,Table1[FILLED&UNFILLED],FormulaSheet!C90) -> 0 | D107: =B107+C107 -> 1
A108: Hospital Housekeeper | B108: =COUNTIFS(Table1[Parentetical],FormulaSheet!A108,Table1[26],FormulaSheet!A89,Table1[FILLED&UNFILLED],FormulaSheet!B90) -> 1 | C108: =COUNTIFS(Table1[Parentetical],FormulaSheet!A108,Table1[26],FormulaSheet!A89,Table1[FILLED&UNFILLED],FormulaSheet!C90) -> 0 | D108: =B108+C108 -> 1
A109: Laundry Worker II | B109: =COUNTIFS(Table1[Parentetical],FormulaSheet!A109,Table1[26],FormulaSheet!A89,Table1[FILLED&UNFILLED],FormulaSheet!B90) -> 1 | C109: =COUNTIFS(Table1[Parentetical],FormulaSheet!A109,Table1[26],FormulaSheet!A89,Table1[FILLED&UNFILLED],FormulaSheet!C90) -> 0 | D109: =B109+C109 -> 1
A110: Medical Equipment Technician II | B110: =COUNTIFS(Table1[Parentetical],FormulaSheet!A110,Table1[26],FormulaSheet!A89,Table1[FILLED&UNFILLED],FormulaSheet!B90) -> 1 | C110: =COUNTIFS(Table1[Parentetical],FormulaSheet!A110,Table1[26],FormulaSheet!A89,Table1[FILLED&UNFILLED],FormulaSheet!C90) -> 0 | D110: =B110+C110 -> 1
A111: Medical Equipment Technician I | B111: =COUNTIFS(Table1[Parentetical],FormulaSheet!A111,Table1[26],FormulaSheet!A89,Table1[FILLED&UNFILLED],FormulaSheet!B90) -> 1 | C111: =COUNTIFS(Table1[Parentetical],FormulaSheet!A111,Table1[26],FormulaSheet!A89,Table1[FILLED&UNFILLED],FormulaSheet!C90) -> 0 | D111: =B111+C111 -> 1
A112: Seamstress | B112: =COUNTIFS(Table1[Parentetical],FormulaSheet!A112,Table1[26],FormulaSheet!A89,Table1[FILLED&UNFILLED],FormulaSheet!B90) -> 1 | C112: =COUNTIFS(Table1[Parentetical],FormulaSheet!A112,Table1[26],FormulaSheet!A89,Table1[FILLED&UNFILLED],FormulaSheet!C90) -> 0 | D112: =B112+C112 -> 1
A113: Supervising Administrative Officer | B113: =COUNTIFS(Table1[Parentetical],FormulaSheet!A113,Table1[26],FormulaSheet!A89,Table1[FILLED&UNFILLED],FormulaSheet!B90) -> 1 | C113: =COUNTIFS(Table1[Parentetical],FormulaSheet!A113,Table1[26],FormulaSheet!A89,Table1[FILLED&UNFILLED],FormulaSheet!C90) -> 0 | D113: =B113+C113 -> 1
A114: Warehouseman II | B114: =COUNTIFS(Table1[Parentetical],FormulaSheet!A114,Table1[26],FormulaSheet!A89,Table1[FILLED&UNFILLED],FormulaSheet!B90) -> 1 | C114: =COUNTIFS(Table1[Parentetical],FormulaSheet!A114,Table1[26],FormulaSheet!A89,Table1[FILLED&UNFILLED],FormulaSheet!C90) -> 0 | D114: =B114+C114 -> 1
A115: Total | B115: =SUM(B91:B114) -> 52 | C115: =SUM(C91:C114) -> 2 | D115: =SUM(D91:D114) -> 54
A118: Medical Division | B118: Position | D118: Total
B119: Filled | C119: Unfilled
A120: Administrative Aide III | B120: =COUNTIFS(Table1[Parentetical],FormulaSheet!A120,Table1[26],FormulaSheet!A118,Table1[FILLED&UNFILLED],FormulaSheet!B119) -> 2 | C120: =COUNTIFS(Table1[Parentetical],FormulaSheet!A120,Table1[26],FormulaSheet!A118,Table1[FILLED&UNFILLED],FormulaSheet!C119) -> 0 | D120: =B120+C120 -> 2
A121: Administrative Assistant I | B121: =COUNTIFS(Table1[Parentetical],FormulaSheet!A121,Table1[26],FormulaSheet!A118,Table1[FILLED&UNFILLED],FormulaSheet!B119) -> 4 | C121: =COUNTIFS(Table1[Parentetical],FormulaSheet!A121,Table1[26],FormulaSheet!A118,Table1[FILLED&UNFILLED],FormulaSheet!C119) -> 0 | D121: =B121+C121 -> 4
A122: Administrative Assistant II | B122: =COUNTIFS(Table1[Parentetical],FormulaSheet!A122,Table1[26],FormulaSheet!A118,Table1[FILLED&UNFILLED],FormulaSheet!B119) -> 2 | C122: =COUNTIFS(Table1[Parentetical],FormulaSheet!A122,Table1[26],FormulaSheet!A118,Table1[FILLED&UNFILLED],FormulaSheet!C119) -> 0 | D122: =B122+C122 -> 2
A123: Administrative Officer I | B123: =COUNTIFS(Table1[Parentetical],FormulaSheet!A123,Table1[26],FormulaSheet!A118,Table1[FILLED&UNFILLED],FormulaSheet!B119) -> 1 | C123: =COUNTIFS(Table1[Parentetical],FormulaSheet!A123,Table1[26],FormulaSheet!A118,Table1[FILLED&UNFILLED],FormulaSheet!C119) -> 0 | D123: =B123+C123 -> 1
A124: Administrative Officer IV | B124: =COUNTIFS(Table1[Parentetical],FormulaSheet!A124,Table1[26],FormulaSheet!A118,Table1[FILLED&UNFILLED],FormulaSheet!B119) -> 1 | C124: =COUNTIFS(Table1[Parentetical],FormulaSheet!A124,Table1[26],FormulaSheet!A118,Table1[FILLED&UNFILLED],FormulaSheet!C119) -> 0 | D124: =B124+C124 -> 1
A125: Administrative Officer V | B125: =COUNTIFS(Table1[Parentetical],FormulaSheet!A125,Table1[26],FormulaSheet!A118,Table1[FILLED&UNFILLED],FormulaSheet!B119) -> 1 | C125: =COUNTIFS(Table1[Parentetical],FormulaSheet!A125,Table1[26],FormulaSheet!A118,Table1[FILLED&UNFILLED],FormulaSheet!C119) -> 0 | D125: =B125+C125 -> 1
A126: Chemist | B126: =COUNTIFS(Table1[Parentetical],FormulaSheet!A126,Table1[26],FormulaSheet!A118,Table1[FILLED&UNFILLED],FormulaSheet!B119) -> 1 | C126: =COUNTIFS(Table1[Parentetical],FormulaSheet!A126,Table1[26],FormulaSheet!A118,Table1[FILLED&UNFILLED],FormulaSheet!C119) -> 0 | D126: =B126+C126 -> 1
A127: CMPS | B127: =COUNTIFS(Table1[Parentetical],FormulaSheet!A127,Table1[26],FormulaSheet!A118,Table1[FILLED&UNFILLED],FormulaSheet!B119) -> 1 | C127: =COUNTIFS(Table1[Parentetical],FormulaSheet!A127,Table1[26],FormulaSheet!A118,Table1[FILLED&UNFILLED],FormulaSheet!C119) -> 0 | D127: =B127+C127 -> 1
A128: Cook II | B128: =COUNTIFS(Table1[Parentetical],FormulaSheet!A128,Table1[26],FormulaSheet!A118,Table1[FILLED&UNFILLED],FormulaSheet!B119) -> 3 | C128: =COUNTIFS(Table1[Parentetical],FormulaSheet!A128,Table1[26],FormulaSheet!A118,Table1[FILLED&UNFILLED],FormulaSheet!C119) -> 0 | D128: =B128+C128 -> 3
...

Sheet DISCONNECTED
B1: LAST | C1: FIRST | D1: MIDDLE | E1: SUFFIX | F1: POSITION | G1: ASSUMPTION | H1: LAST DAY | I1: SALARY GRADE | J1: STEP | K1: BASIC SALARY | L1: CIVIL STATUS | M1: GENDER | N1: mm/dd/yyyy | O1: PLACE OF BIRTH | P1: No., Street, Subd./Village | Q1: Baranggay | R1: City/Municipality | S1: Province | T1: Zip Code | U1: EDUCATIONAL ATTAINMENT | V1: PROGRAM/COURSE | W1: ELIGIBILITY | X1: LICENSE NO. | Y1: VALIDITY | Z1: GSIS | AA1: PAG-IBIG | AB1: PHILHEALTH | AC1: TIN | AD1: MOBILE NO. | AE1: PHONE NO. | AF1: EMAIL ADDRESS | AG1: Remarks
B2: Enaldo | C2: Jim Dember | D2: Tagle | F2: Administrative Aide IV | G2: June 1, 2021 | H2: 44545 | L2: Married | M2: Male | N2: 31804 | O2: Imus City, Cavite | P2: #59 Ilaya Proper | Q2: Pasong Buaya II | R2: Imus City | S2: Cavite | T2: 4103 | U2: Vocational | V2: Assoc. HRM | W2: Driver's License | X2: PROF-N26-07-011011 | Y2: 45318 | Z2: 2004-119-819 | AA2: 1210-5653-2579 | AB2: 1305-0228-1921 | AC2: 302-753-494 | AD2: 0916-225-9532 | AE2: N/A | AF2: jimdember@gmail.com
B3: Marasigan | C3: Roselene Mae | D3: Santos | F3: Nurse I | G3: May 18, 2021 | H3: 44548 | L3: Single | M3: Female | N3: 33448 | O3: Las Piñas City | P3: Unit D B17 L15, Bacolod St., Southern City | Q3: Tanzang Luma 4 | R3: Imus City | S3: Cavite | T3: 4103 | U3: College Graduate | V3: BS Nursing | W3: PRC | X3: 0900083 | Y3: 44406 | Z3: N/A | AA3: 1210-8806-3655 | AB3: 0305-1075-9288 | AC3: 703-799-575 | AD3: 0956-733-7778 | AE3: (046) 431-2908 | AF3: rosemarasigan2015@gmail.com
B4: Baita | C4: Aeron Frank | D4: Tapawan | F4: Nurse I | G4: May 20, 2021 | H4: 44590 | L4: Single | M4: Male | N4: 32177 | O4: Makati City | P4: 257 Arnaldo Highway | Q4: Pasong Camachille I | R4: General Trias City | S4: Cavite | T4: 4107 | U4: College Graduate | V4: BS Nursing | W4: PRC | X4: 0701215 | Y4: 44961 | Z4: N/A | AA4: 1211-1027-6955 | AB4: 0802-5665-6942 | AC4: 283-127-687 | AD4: 0995-976-7886 | AE4: N/A | AF4: aeonfrankb@gmail.com
B5: Bernandino | C5: Jaybee | D5: Julian | F5: Nurse I | G5: May 17, 2021 | H5: 44681 | L5: Single | M5: Male | N5: 33418 | O5: Peñaranda, Nueva Ecija | P5: B5 L37-39 Yakal St., Sagana Remville Homes | Q5: Habay II | R5: Bacoor City | S5: Cavite | T5: 4102 | U5: College Graduate | V5: BS Nursing | W5: PRC | X5: 0723965 | Y5: 44376 | Z5: N/A | AA5: 1211-1011-6484 | AB5: 0205-1043-4278 | AC5: 443-202-731 | AD5: 0977-603-1232 | AE5: N/A | AF5: bernandinojaybee@gmail.com
B6: Atap | C6: Rosalyn | D6: Castardo | F6: Medical Technologist I | G6: June 16, 2021 | H6: 44696 | L6: Single | M6: Female | N6: 34834 | O6: Cebu City | P6: B16 L1 Fuji St., Citilane Subd. | Q6: Malagasang 2F | R6: Imus City | S6: Cavite | T6: 4103 | U6: College Graduate | V6: BS Medical Technologist | W6: PRC | X6: 0075487 | Y6: 45061 | Z6: 2005-291-156 | AA6: 1211-8403-1496 | AB6: 0805-1550-1472 | AC6: 700-798-933 | AD6: 0926-151-6870 | AE6: (046) 454-9235 | AF6: ataprosalyn15@gmail.com
B7: Legaspi | C7: Phol Russel | D7: Lepon | F7: Nurse I | G7: June 16, 2021 | H7: 44742 | L7: Single | M7: Male | N7: 33616 | O7: Dasmariñas City, Cavite | P7: 201 | Q7: Anabu 2-D | R7: Imus City | S7: Cavite | T7: 4103 | U7: College Graduate | V7: BS Nursing | W7: PRC | X7: 0841687 | Y7: 44939 | Z7: 2005-538-708 | AA7: 1212-4057-3749 | AB7: 0802-5790-2408 | AC7: 735-475-197 | AD7: 0927-285-3677 | AE7: (046) 424-3215 | AF7: russel_legaspi13@yahoo.com
B8: Añano | C8: Ailyn | D8: Bagares | F8: Administrative Assistant I | G8: 44319 | H8: 44772 | I8: 7 | J8: 1 | K8: 17899 | L8: Single | M8: Female | N8: 35024 | O8: Guiuan, Eastern Samar | P8: B27 L28, Rovigo Courtyard, Golden Horizon | Q8: Hugo Perez | R8: Trece Martires City | S8: Cavite | T8: 4109 | U8: College Graduate | V8: AB Political Science | W8: CSC - Professional | X8: N/A | Y8: N/A | Z8: 2005911398 | AA8: 1210-8374-2315 | AB8: 2200-0100-7874 | AC8: 433-369-010 | AD8: 0955-078-3441 | AE8: N/A | AF8: aiylnanano@gmail.com
B9: Samala | C9: Kenneth | D9: Gelera | F9: Medical Specialist II | G9: 44417 | H9: 44757 | I9: 23 | J9: 1 | K9: 78455 | L9: Single | M9: Male | N9: 31208 | O9: Cavite City | P9: 311 Mangahan St. | Q9: Binakayan | R9: Kawit | S9: Cavite | T9: 4104 | U9: Doctor of Medicine | V9: Medicine | W9: PRC | X9: 0121459 | Y9: 45087 | Z9: 2004193948 | AA9: 1210-2925-3462 | AB9: 0102-5361-2296 | AC9: 417-468-407 | AD9: 0917-630-2265 | AE9: (046) 476-2765 | AF9: kenn.samala@gmail.com
A10: OSEC-DOHB-MDOF4-270020-2020 | B10: Lagon-Manes | C10: Jowen Anne Marie | D10: Madarang | F10: Medical Officer IV | G10: 44363 | H10: 44813 | I10: 23 | J10: 1 | K10: 78455 | L10: Married | M10: Female | N10: 31646 | O10: Manila | P10: B5 L15 Cannara St., Pontecelli Hills | Q10: Molino IV | R10: Bacoor City | S10: Cavite | T10: 4102 | U10: Doctor of Medicine | V10: Medicine | W10: PRC | X10: 0129483 | Y10: 45526 | Z10: 2005057118 | AA10: 1211-8933-3787 | AB10: 1602-5709-2434 | AC10: 478-007-727 | AD10: 0917-704-5691 | AE10: N/A | AF10: jowen_armski@yahoo.com
A11: OSEC-DOHB-MDOF3-270005-2020 | B11: Elpedes | C11: Wilma | D11: Alpe | F11: Medical Officer III | G11: 44363 | H11: 44880 | I11: 21 | J11: 1 | K11: 62449 | L11: Single | M11: Female | N11: 26371 | O11: Camaligan, Camarines Sur | P11: B9 L5 T. Jefferson Ph. 2, Princeton Heights Subd. | Q11: Mambog IV | R11: Bacoor City | S11: Cavite | T11: 4102 | U11: Doctor of Medicine | V11: Medicine | W11: PRC | X11: 0093215 | Y11: 45364 | Z11: 2002172053 | AA11: 1210-7200-4903 | AB11: 1900-0761-0657 | AC11: 925-934-294 | AD11: 0922-856-1494 | AE11: N/A | AF11: wilmaelpedes@yahoo.com
A12: OSEC-DOHB-MDOF3-270007-2020 | B12: Billones | C12: Alain | D12: Tabarnero | F12: Medical Officer III | G12: 44363 | H12: 44926 | I12: 21 | J12: 1 | K12: 62449 | L12: Single | M12: Male | N12: 32094 | O12: Pasay City | P12: B-A 11 L10 | Q12: Luzviminda I | R12: Dasmariñas City | S12: Cavite | T12: 4114 | U12: Doctor of Medicine | V12: Medicine | W12: PRC | X12: 0137036 | Y12: 45233 | Z12: 2005931479 | AA12: 1010-0101-7367 | AB12: 0105-0762-1533 | AC12: 259-310-116 | AD12: 0977-197-8409 | AE12: (046) 424-0837 | AF12: alainbillones@gmail.com
A13: OSEC-DOHB-MDOF3-270008-2020 | B13: Villafuerte | C13: Andrew Rufino | D13: Martin | F13: Medical Officer III | G13: 44655 | H13: 44926 | I13: 21 | J13: 1 | K13: 62449 | L13: Married | M13: Male | N13: 33783 | O13: San Juan, Metro Manila | P13: B15 L6&7 Saint Rita St., Addas II Village | Q13: Molino II | R13: Bacoor City | S13: Cavite | T13: 4102 | U13: Doctor of Medicine | V13: Medicine | W13: PRC | X13: 0136907 | Y13: 45105 | Z13: 2005561419 | AA13: 1212-3985-2229 | AB13: 0202-6218-7412 | AC13: 712-780-970 | AD13: 0917-169-1221 | AE13: N/A | AF13: andewrufinovillafuerte@gmail.com
A14: OSEC-DOHB-MDSPT3-270005-2021 | B14: De Castro | C14: Jener | D14: Novero | F14: Medical Specialist III (Part-time) (Pulmonologist) | G14: 44844 | H14: 44935 | I14: 24 | J14: 1 | K14: 44205 | L14: Married | M14: Male | N14: 31975 | O14: Alfonso, Cavite | P14: 31 | Q14: San Joaquin | R14: Sto. Tomas | S14: Batangas | T14: 4234 | U14: Doctor of Medicine | V14: Medicine | W14: PRC | X14: 0130138 | Y14: 45490 | Z14: 2004888651 | AA14: 1211-7729-2414 | AB14: 0802-3090-0786 | AC14: 277-601-266 | AD14: 0917-675-1129 | AE14: (046) 522-1121 | AF14: docjenerdecastro@gmail.com
A15: OSEC-DOHB-ADAS1-270040-2020 | B15: De Leon | C15: Erika Anna | D15: Avellaneda | F15: Administrative Assistant I | G15: 44470 | H15: 45014 | I15: 7 | J15: 1 | K15: =LOOKUP(I15,{1,2,3,4,5,6,7,8,9,10,11,12,13,14,15,16,17,18,19,20,21,22,23,24,25,26,27,28,29,30,31,32,33},{13000,13819,14678,15586,16543,17553,18620,19744,21211,23176,27000,29165,31320,33843,36619,39672,43030,46725,51357,57347,63997,71511,80003,90078,102690,116040,131124,148171,167432,189199,278434,331954,419144}) -> 18620 | L15: Single | M15: Female | N15: 34785 | O15: Pasay City | P15: P1 B41 L1 Parklane Country Homes | Q15: San Francisco | R15: General Trias City | S15: Cavite | T15: 4107 | U15: College Graduate | V15: BS Psychology | W15: PRC | X15: 0010291 | Y15: 45012 | Z15: 2005352375 | AA15: 1211-7222-3128 | AB15: 0825-0494-0175 | AC15: 335-507-471 | AD15: 0915-876-2508 | AE15: (046) 413-0346 | AF15: erikaannaadeleon@gmail.com
A16: OSEC-DOHB-NUR1-270106-2020 | B16: Incognito | C16: Kristine Marie | D16: Vicman | F16: Nurse I | G16: 44531 | H16: 44957 | I16: 15 | J16: 1 | K16: =LOOKUP(I16,{1,2,3,4,5,6,7,8,9,10,11,12,13,14,15,16,17,18,19,20,21,22,23,24,25,26,27,28,29,30,31,32,33},{13000,13819,14678,15586,16543,17553,18620,19744,21211,23176,27000,29165,31320,33843,36619,39672,43030,46725,51357,57347,63997,71511,80003,90078,102690,116040,131124,148171,167432,189199,278434,331954,419144}) -> 36619 | L16: Single | M16: Female | N16: 32634 | O16: Alfonso, Cavite | P16: 61 | Q16: Castaños Lejos | R16: Gen. Emilio Aguinaldo | S16: Cavite | T16: 4124 | U16: Master's Degree | V16: BS Nursing/MPH/MPA | W16: PRC | X16: 0626832 | Y16: 45783 | Z16: 2004776988 | AA16: 1210-3862-2187 | AB16: 0302-5185-6997 | AC16: 404-598-609 | AD16: 0906-562-8834 | AE16: N/A | AF16: nursetine.doh4a@gmail.com
A17: OSEC-DOHB-ENG2-270042-2022 | B17: Villalobos | C17: Angelo Anjo | D17: Villarosa | F17: Engineer II | G17: 44867 | H17: 45050 | I17: 16 | J17: 1 | K17: =LOOKUP(I17,{1,2,3,4,5,6,7,8,9,10,11,12,13,14,15,16,17,18,19,20,21,22,23,24,25,26,27,28,29,30,31,32,33},{13000,13819,14678,15586,16543,17553,18620,19744,21211,23176,27000,29165,31320,33843,36619,39672,43030,46725,51357,57347,63997,71511,80003,90078,102690,116040,131124,148171,167432,189199,278434,331954,419144}) -> 39672 | L17: Married | M17: Male | N17: 33524 | O17: Fairview, Quezon City | P17: Blk 3 Lot 29 Grand Cypress Homes | Q17: Tungko | R17: San Jose Del Monte | S17: Bulacan | T17: 3023 | U17: College Graduate | V17: BS Electrical Engineering | W17: PRC | X17: 0052194 | Y17: 45943 | Z17: N/A | AA17: 1211-1134-7459 | AB17: 0205-1033-4230 | AC17: 285-227-810 | AD17: 0968-554-3361 | AE17: N/A | AF17: villalobos1013@gmail.com
A18: OSEC-DOHB-NUR1-270086-2020 | B18: Aliño | C18: Phoebe | D18: Triunfo | F18: Nurse I | G18: 45019 | H18: 45092 | I18: 15 | J18: 1 | K18: =LOOKUP(I18,{1,2,3,4,5,6,7,8,9,10,11,12,13,14,15,16,17,18,19,20,21,22,23,24,25,26,27,28,29,30,31,32,33},{13000,13819,14678,15586,16543,17553,18620,19744,21211,23176,27000,29165,31320,33843,36619,39672,43030,46725,51357,57347,63997,71511,80003,90078,102690,116040,131124,148171,167432,189199,278434,331954,419144}) -> 36619 | L18: Single | M18: Female | N18: 33377 | O18: Sta. Cruz, Manila | P18: Block B2 Lot 2 | Q18: Luzviminda I | R18: Dasmariñas City | S18: Cavite | T18: 4114 | U18: College Graduate | V18: BS Nursing | W18: PRC | X18: 0757036 | Y18: 05/19/2024 | Z18: 2005593835 | AA18: 1211-0132-4302 | AB18: 0802-6008-1164 | AC18: 720-918-690 | AD18: 0977-691-7065 | AE18: N/A | AF18: phoebealino@yahoo.com
A19: OSEC-DOHB-NUR1-270094-2020 | B19: Aragones | C19: Emmanuel | D19: Dela Cruz | E19: Jr. | F19: Nurse I | G19: 44956 | H19: 45143 | I19: 15 | J19: 1 | K19: =LOOKUP(I19,{1,2,3,4,5,6,7,8,9,10,11,12,13,14,15,16,17,18,19,20,21,22,23,24,25,26,27,28,29,30,31,32,33},{13000,13819,14678,15586,16543,17553,18620,19744,21211,23176,27000,29165,31320,33843,36619,39672,43030,46725,51357,57347,63997,71511,80003,90078,102690,116040,131124,148171,167432,189199,278434,331954,419144}) -> 36619 | L19: Married | M19: Male | N19: 32093 | O19: Manila | P19: 275 Taylan Longos | Q19: Zapote 5 | R19: Bacoor City | S19: Cavite | T19: 4102 | U19: College Graduate | V19: BS Nursing | W19: PRC | X19: 0561368 | Y19: 45608 | Z19: N/A | AA19: 1212-3714-2818 | AB19: 0202-5260-8932 | AC19: 228-380-989 | AD19: 0992-209-5790 | AE19: N/A | AF19: macaragones@yahoo.com
A20: OSEC-DOHB-NUR1-270097-2020 | B20: Melchor | C20: Suzette | D20: Fermin | F20: Nurse I | G20: 44336 | H20: 45157 | I20: 15 | J20: 1 | K20: =LOOKUP(I20,{1,2,3,4,5,6,7,8,9,10,11,12,13,14,15,16,17,18,19,20,21,22,23,24,25,26,27,28,29,30,31,32,33},{13000,13819,14678,15586,16543,17553,18620,19744,21211,23176,27000,29165,31320,33843,36619,39672,43030,46725,51357,57347,63997,71511,80003,90078,102690,116040,131124,148171,167432,189199,278434,331954,419144}) -> 36619 | L20: Single | M20: Female | N20: 31347 | O20: Laoag City | P20: Block P L20 RSG Gueventhomes | Q20: Panapaan I | R20: Bacoor City | S20: Cavite | T20: 4102 | U20: College Graduate | V20: BS Nursing | W20: PRC | X20: 0528835 | Y20: 45957 | Z20: 2005911550 | AA20: 1210-9681-2897 | AB20: 0202-5332-5322 | AC20: 429-626-209 | AD20: 0910-223-6062 | AE20: (046) 973-2993 | AF20: zhetsu_143@yahoo.com
B21: Blando-Fuentes | C21: Michelle Margaret | D21: Agustin | F21: 31225 | G21: 44867 | H21: 44867 | I21: 44867 | J21: Married | L21: Zamboanga City | M21: Block 7 Lot 3 Evangeline Pascual, BF Resort Village | N21: Talon Dos | O21: Las Piñas City | P21: Metro Manila | Q21: 1747 | R21: Doctor of Medicine | S21: Medicine | T21: PRC | U21: 0127091 | V21: 45104 | W21: N/A | X21: 1212-3073-9702 | Y21: 1501-1946-6333 | Z21: 163-666-497 | AA21: 0917-835-3706 | AB21: N/A | AC21: mitch_blando@yahoo.com
B22: Caraveo | C22: Julien Nicole | D22: Camba | F22: 32707 | G22: 44363 | H22: 44363 | I22: 44363 | J22: Single | L22: Pasay City | M22: B10 L23 Queen of Pilars St., Queens Row | N22: Queens Row East | O22: Bacoor City | P22: Cavite | Q22: 4102 | R22: Doctor of Medicine | S22: Medicine | T22: PRC | U22: 0140234 | V22: 45491 | W22: 2005931854 | X22: 1212-4065-1759 | Y22: 0802-6536-1726 | Z22: 455-221-418 | AA22: 0906-209-6582 | AB22: (046) 440-9498 | AC22: julien.caraveo@gmail.com
A23: OSEC-DOHB-NURS2-270020-2022 | B23: Jabonero | C23: Kenneth | D23: Candeliña | F23: 31312 | G23: 44382 | H23: 45331 | I23: 16 | J23: 1 | L23: Single | M23: Male | N23: Kabacan, North Cotabato | O23: B7 L5 Solar St., Sunrise Hills Subd. | P23: Sabang | Q23: Dasmariñas City | R23: Cavite | S23: 4114 | T23: College Graduate | U23: BS Nursing | V23: PRC | W23: 0474711 | X23: 45557 | Y23: 2005932069 | Z23: 1211-0626-3313 | AA23: 0802-5612-9462 | AB23: 298-860-228 | AC23: 0927-558-1673 | AD23: N/A | AE23: kencie010@yahoo.com
A25: Item Number | B25: POSITION | C25: SALARY GRADE | D25: AUTHORIZED SALARY | E25: Level | F25: LAST | G25: FIRST | H25: MIDDLE | I25: SUFFIX | J25: DATE OF BIRTH | K25: DATE OF ORIGINAL APPOINTMENT | L25: ASSUMPTION | M25: LATEST PROMOTION | N25: CIVIL STATUS | O25: GENDER | P25: PLACE OF BIRTH | Q25: No., Street, Subd./Village | R25: Baranggay | S25: City/Municipality | T25: Province | U25: Zip Code | V25: EDUCATIONAL ATTAINMENT | W25: PROGRAM/COURSE | X25: ELIGIBILITY | Y25: LICENSE NO. | Z25: VALIDITY | AA25: GSIS | AB25: PAG-IBIG | AC25: PHILHEALTH | AD25: TIN | AE25: MOBILE NO. | AF25: PHONE NO. | AG25: EMAIL ADDRESS | AH25: LAST DAY
A26: OSEC-DOHB-NURS2-270020-2022 | B26: Nurse II | C26: 16 | D26: =LOOKUP(C26,{1,2,3,4,5,6,7,8,9,10,11,12,13,14,15,16,17,18,19,20,21,22,23,24,25,26,27,28,29,30,31,32,33},{13000,13819,14678,15586,16543,17553,18620,19744,21211,23176,27000,29165,31320,33843,36619,39672,43030,46725,51357,57347,63997,71511,80003,90078,102690,116040,131124,148171,167432,189199,278434,331954,419144}) -> 39672 | E26: 2 | F26: Jabonero | G26: Kenneth | H26: Candeliña | J26: 31312 | K26: 44382 | L26: 44382 | M26: 44867 | N26: Single | O26: Male | P26: Kabacan, North Cotabato | Q26: B7 L5 Solar St., Sunrise Hills Subd. | R26: Sabang | S26: Dasmariñas City | T26: Cavite | U26: 4114 | V26: College Graduate | W26: BS Nursing | X26: PRC | Y26: 0474711 | Z26: 45557 | AA26: 2005932069 | AB26: 1211-0626-3313 | AC26: 0802-5612-9462 | AD26: 298-860-228 | AE26: 0927-558-1673 | AF26: N/A | AG26: kencie010@yahoo.com | AH26: 45331
A27: OSEC-DOHB-NUR1-270030-2022 | B27: Nurse I | C27: 15 | D27: =LOOKUP(C27,{1,2,3,4,5,6,7,8,9,10,11,12,13,14,15,16,17,18,19,20,21,22,23,24,25,26,27,28,29,30,31,32,33},{13000,13819,14678,15586,16543,17553,18620,19744,21211,23176,27000,29165,31320,33843,36619,39672,43030,46725,51357,57347,63997,71511,80003,90078,102690,116040,131124,148171,167432,189199,278434,331954,419144}) -> 36619 | E27: 2 | F27: Tagbago | G27: Kerwin | H27: Calixihan | J27: 32878 | K27: 44851 | L27: 44851 | M27: 44851 | N27: Single | O27: Male | P27: Manila | Q27: B6 L7 Pisces Camella Homes | R27: Salinas 3 | S27: Bacoor City | T27: Cavite | U27: 4102 | V27: College Graduate | W27: BS Nursing | X27: PRC | Y27: 0765728 | Z27: 46143 | AA27: N/A | AB27: 1210-7220-8182 | AC27: 0305-1038-1846 | AD27: 312-925-349 | AE27: 0917-304-2709 | AF27: N/A | AG27: kerwintagbago@gmail.com | AH27: 45358
A28: OSEC-DOHB-NATT1-270009-2020 | B28: Nursing Attendant I | C28: 4 | D28: =LOOKUP(C28,{1,2,3,4,5,6,7,8,9,10,11,12,13,14,15,16,17,18,19,20,21,22,23,24,25,26,27,28,29,30,31,32,33},{13000,13819,14678,15586,16543,17553,18620,19744,21211,23176,27000,29165,31320,33843,36619,39672,43030,46725,51357,57347,63997,71511,80003,90078,102690,116040,131124,148171,167432,189199,278434,331954,419144}) -> 15586 | E28: 1 | F28: Intia | G28: Alyssa Mari | H28: Bengusta | J28: 34528 | K28: 45124 | L28: 45124 | M28: 45124 | N28: Married | O28: Female | P28: Valenzuela City | Q28: 54 Gallen Road, Regatta Classics Subd. | R28: Anabu II-B | S28: Imus City | T28: Cavite | U28: 4103 | V28: College Graduate | W28: BA Communication | X28: N/A | Y28: N/A | Z28: N/A | AA28: N/A | AB28: 1211-0260-2472 | AC28: 0805-1363-6834 | AD28: 322-856-054 | AE28: 0968-884-5722 | AF28: (046) 537-2886 | AG28: aintia0725@gmail.com | AH28: 45350
A29: OSEC-DOHB-MDOF4-270022-2020 | B29: Medical Officer IV | C29: 23 | D29: =LOOKUP(C29,{1,2,3,4,5,6,7,8,9,10,11,12,13,14,15,16,17,18,19,20,21,22,23,24,25,26,27,28,29,30,31,32,33},{13000,13819,14678,15586,16543,17553,18620,19744,21211,23176,27000,29165,31320,33843,36619,39672,43030,46725,51357,57347,63997,71511,80003,90078,102690,116040,131124,148171,167432,189199,278434,331954,419144}) -> 80003 | E29: 2 | F29: Andres | G29: Charine | H29: Basul | J29: 32551 | K29: 43439 | L29: 44348 | M29: 44348 | N29: Married | O29: Female | P29: Quezon City | Q29: B23 L28 Stockholm St., Golden City Subd. | R29: Anabu II-E | S29: Imus City | T29: Cavite | U29: 4103 | V29: Doctor of Medicine | W29: Medicine | X29: PRC | Y29: 0129879 | Z29: 45993 | AA29: 2005260554 | AB29: 1212-1007-8230 | AC29: 0302-6194-6870 | AD29: 463-046-419 | AE29: 0919-096-5105 | AF29: N/A | AG29: chel.charine@gmail.com | AH29: 45351 | AL29: 0919-096-5105 | AM29: N/A | AN29: chel.charine@gmail.com
A31: Item Number | B31: POSITION | C31: SALARY GRADE | D31: AUTHORIZED SALARY | E31: Level | F31: FILLED&UNFILLED | G31: LAST | H31: FIRST | I31: MIDDLE | J31: SUFFIX | K31: DATE OF BIRTH | L31: DATE OF ORIGINAL APPOINTMENT | M31: ASSUMPTION | N31: LATEST PROMOTION | O31: CIVIL STATUS | P31: GENDER | Q31: AGE | R31: AGE GROUP | S31: PLACE OF BIRTH | T31: No., Street, Subd./Village | U31: Baranggay | V31: City/Municipality | W31: Province | X31: Zip Code | Y31: EDUCATIONAL ATTAINMENT | Z31: PROGRAM/COURSE | AA31: ELIGIBILITY | AB31: LICENSE NO. | AC31: VALIDITY | AD31: GSIS | AE31: PAG-IBIG | AF31: PHILHEALTH | AG31: TIN | AH31: MOBILE NO. | AI31: PHONE NO. | AJ31: EMAIL ADDRESS | AK31: LAST DAY
A32: OSEC-DOHB-RT1-270014-2022 | B32: Radiologic Technologist I | C32: 11 | D32: 27000 | E32: 2 | F32: Filled | G32: Chu | H32: Fauline Joyce | I32: Beloy | K32: 33772 | L32: 45104 | M32: 45104 | N32: 45104 | O32: Married | P32: Female | Q32: 32 | R32: 30-39 | S32: Pasay City | T32: Block 80 Lot 10 Phase 3, Atis, Mary Chris Complex | U32: Pasong Camachile II | V32: General Trias City | W32: Cavite | X32: 4107 | Y32: College Graduate | Z32: BS Radiologic Technology | AA32: PRC | AB32: 0011009 | AC32: 45825 | AD32: N/A | AE32: 1211-0701-7772 | AF32: 0805-1428-5350 | AG32: 467-868-283 | AH32: 0975-059-3952 | AI32: (046) 527-5329 | AJ32: faulin_12@yahoo.com | AK32: 45460 | AL32: Resigned
A33: OSEC-DOHB-NUR1-270104-2020 | B33: Nurse I | C33: 15 | D33: 36619 | E33: 2 | F33: Filled | G33: Supelana | H33: Alan | I33: Donor | K33: 33439 | L33: 45337 | M33: 45337 | N33: 45337 | O33: Single | P33: Male | Q33: 32 | R33: 30-39 | S33: Jeddah, KSA | T33: 21/5/11 Jara Martinez, Bahayang Pagasa | U33: Molino V | V33: Bacoor City | W33: Cavite | X33: 4102 | Y33: College Graduate | Z33: BS Nursing | AA33: PRC | AB33: 0818765 | AC33: 45858 | AD33: N/A | AE33: 1210-9413-5066 | AF33: 0105-1874-3444 | AG33: 277-974-111 | AH33: 0975-520-6489 | AI33: (046) 437-6349 | AJ33: alansupelana0720@gmail.com | AK33: 45473 | AL33: Resigned
A34: OSEC-DOHB-LABA2-270017-2020 | B34: Laboratory Aide II | C34: 4 | D34: 15586 | E34: 1 | F34: Filled | G34: Pador | H34: Angelica | I34: Relacion | K34: 36139 | L34: 44487 | M34: 44487 | N34: 44487 | O34: Single | P34: Female | Q34: 25 | R34: 20-29 | S34: Apalit, Pampanga | T34: B3 L5 Sampaguita St., Camella Townhomes | U34: Salinas II | V34: Bacoor City | W34: Cavite | X34: 4102 | Y34: College Graduate | Z34: Associate in Computer Technology | AA34: N/A | AB34: N/A | AC34: N/A | AD34: 2005971532 | AE34: 1212-8894-2791 | AF34: 0525-1623-5845 | AG34: 718-668-182 | AH34: 0966-374-1359 | AI34: (046) 456-5512 | AJ34: angelicapador12@gmail.com | AK34: 45480 | AL34: Resigned
A35: OSEC-DOHB-NUR1-270079-2020 | B35: Nurse I | C35: 15 | D35: 36619 | E35: 2 | F35: Filled | G35: Pangilinan | H35: Priscila | I35: Mecua | K35: 21739 | L35: 37258 | M35: 44348 | N35: 44348 | O35: Married | P35: Female | Q35: =DATEDIF(K35,TODAY(),"Y") -> 67 | R35: =IF(ABS(Table1[[#This Row],[AGE]])>59,"60 and above",IF(ABS(Table1[[#This Row],[AGE]])>49,"50-59",IF(ABS(Table1[[#This Row],[AGE]])>39,"40-49",IF(ABS(Table1[[#This Row],[AGE]])>29,"30-39",IF(ABS(Table1[[#This Row],[AGE]])>19,"20-29",""))))) -> 40-49 | S35: Amadeo, Cavite | T35: B2 L7 P1 Akle St., Villa Luisa Homes | U35: San Agustin III | V35: Dasmariñas City | W35: Cavite | X35: 4114 | Y35: College Graduate | Z35: BS Nursing | AA35: PRC | AB35: 0198312 | AC35: 45846 | AD35: 2001397667 | AE35: 1030-0008-8539 | AF35: 0800-0059-2556 | AG35: 225-306-408 | AH35: 0927-498-9782 | AI35: (046) 489-2321 | AJ35: N/A | AK35: 45481 | AL35: Retired
A36: OSEC-DOHB-MDOF3-270006-2020 | B36: Medical Officer III | C36: 21 | D36: =LOOKUP(C36,{1,2,3,4,5,6,7,8,9,10,11,12,13,14,15,16,17,18,19,20,21,22,23,24,25,26,27,28,29,30,31,32,33},{13000,13819,14678,15586,16543,17553,18620,19744,21211,23176,27000,29165,31320,33843,36619,39672,43030,46725,51357,57347,63997,71511,80003,90078,102690,116040,131124,148171,167432,189199,278434,331954,419144}) -> 63997 | E36: 2 | F36: =IF(Table1[[#This Row],[LAST]]="","Unfilled","Filled") -> Filled | G36: Torcuator Jr. | H36: Benjamin | I36: Molina | K36: 21761 | L36: 42639 | M36: 44363 | N36: 44363 | O36: Married | P36: Male | Q36: =DATEDIF(K36,TODAY(),"Y") -> 67 | R36: =IF(ABS(Table1[[#This Row],[AGE]])>59,"60 and above",IF(ABS(Table1[[#This Row],[AGE]])>49,"50-59",IF(ABS(Table1[[#This Row],[AGE]])>39,"40-49",IF(ABS(Table1[[#This Row],[AGE]])>29,"30-39",IF(ABS(Table1[[#This Row],[AGE]])>19,"20-29",""))))) -> 30-39 | S36: Manila | T36: B6 L9 Ph3 Camella Homes | U36: Bucandala | V36: Imus City | W36: Cavite | X36: 4103 | Y36: Doctor of Medicine | Z36: Medicine | AA36: PRC | AB36: 0065430 | AC36: 45503 | AD36: 2000767448 | AE36: 1080-0065-3216 | AF36: 1900-0122-0784 | AG36: 137-923-789 | AH36: 0915-700-1641 | AI36: 881-8192 | AJ36: bentorcuatorjr@yahoo.com | AK36: 45504 | AL36: Retired
A37: OSEC-DOHB-NUR1-270107-2020 | B37: Nurse I | C37: 15 | D37: =LOOKUP(C37,{1,2,3,4,5,6,7,8,9,10,11,12,13,14,15,16,17,18,19,20,21,22,23,24,25,26,27,28,29,30,31,32,33},{13000,13819,14678,15586,16543,17553,18620,19744,21211,23176,27000,29165,31320,33843,36619,39672,43030,46725,51357,57347,63997,71511,80003,90078,102690,116040,131124,148171,167432,189199,278434,331954,419144}) -> 36619 | E37: 2 | F37: =IF(Table1[[#This Row],[LAST]]="","Unfilled","Filled") -> Filled | G37: Unciano | H37: Valerie Anne | I37: Tolentino | K37: 30688 | L37: 45337 | M37: 45337 | N37: 45337 | O37: Single | P37: Female | Q37: =DATEDIF(K37,TODAY(),"Y") -> 42 | R37: =IF(ABS(Table1[[#This Row],[AGE]])>59,"60 and above",IF(ABS(Table1[[#This Row],[AGE]])>49,"50-59",IF(ABS(Table1[[#This Row],[AGE]])>39,"40-49",IF(ABS(Table1[[#This Row],[AGE]])>29,"30-39",IF(ABS(Table1[[#This Row],[AGE]])>19,"20-29",""))))) | S37: Quezon City | T37: Block 23 Lot 10 Area B, Daisy St. | U37: Queen's Row West | V37: Bacoor City | W37: Cavite | X37: 4102 | Y37: College Graduate | Z37: BS Nursing | AA37: PRC | AB37: 0422073 | AC37: 45664 | AD37: N/A | AE37: 1210-7985-5504 | AF37: 0805-1042-1462 | AG37: 291-386-719 | AH37: 0995-937-4242 | AI37: N/A | AJ37: valerie.unciano@gmail.com | AK37: 45504 | AL37: Resigned
A38: OSEC-DOHB-MDSP2-270011-2022 | B38: Medical Specialist II (Anesthesiologist) | C38: 23 | D38: =LOOKUP(C38,{1,2,3,4,5,6,7,8,9,10,11,12,13,14,15,16,17,18,19,20,21,22,23,24,25,26,27,28,29,30,31,32,33},{13000,13819,14678,15586,16543,17553,18620,19744,21211,23176,27000,29165,31320,33843,36619,39672,43030,46725,51357,57347,63997,71511,80003,90078,102690,116040,131124,148171,167432,189199,278434,331954,419144}) -> 80003 | E38: 2 | F38: =IF(Table1[[#This Row],[LAST]]="","Unfilled","Filled") -> Filled | G38: Ang-Chua | H38: Nikki | I38: Robles | K38: 32025 | L38: 45329 | M38: 45329 | N38: 45329 | O38: Married | P38: Female | Q38: =DATEDIF(K38,TODAY(),"Y") -> 38 | R38: =IF(ABS(Table1[[#This Row],[AGE]])>59,"60 and above",IF(ABS(Table1[[#This Row],[AGE]])>49,"50-59",IF(ABS(Table1[[#This Row],[AGE]])>39,"40-49",IF(ABS(Table1[[#This Row],[AGE]])>29,"30-39",IF(ABS(Table1[[#This Row],[AGE]])>19,"20-29",""))))) -> 40-49 | S38: Manila | T38: 48B Cencale Drive, Sanville Subd. | U38: Culiat | V38: Quezon City | W38: Metro Manila | X38: 1114 | Y38: Doctor of Medicine | Z38: Medicine | AA38: PRC | AB38: 0130368 | AC38: 46635 | AD38: 2004888608 | AE38: 1211-7110-2379 | AF38: 0602-5143-7176 | AG38: 474-626-498 | AH38: 0917-537-4377 | AI38: N/A | AJ38: angnikkir@gmail.com | AK38: 45544 | AL38: Resigned
A39: OSEC-DOHB-MDOF3-270003-2020 | B39: Medical Officer III (Pedia) | C39: 21 | D39: =LOOKUP(C39,{1,2,3,4,5,6,7,8,9,10,11,12,13,14,15,16,17,18,19,20,21,22,23,24,25,26,27,28,29,30,31,32,33},{13000,13819,14678,15586,16543,17553,18620,19744,21211,23176,27000,29165,31320,33843,36619,39672,43030,46725,51357,57347,63997,71511,80003,90078,102690,116040,131124,148171,167432,189199,278434,331954,419144}) -> 63997 | E39: 2 | F39: =IF(Table1[[#This Row],[LAST]]="","Unfilled","Filled") -> Filled | G39: Malabaguio | H39: Ma. Jeane | I39: Sardea | K39: 31178 | L39: 44671 | M39: 44671 | N39: 44671 | O39: Single | P39: Female | Q39: =DATEDIF(K39,TODAY(),"Y") -> 41 | R39: =IF(ABS(Table1[[#This Row],[AGE]])>59,"60 and above",IF(ABS(Table1[[#This Row],[AGE]])>49,"50-59",IF(ABS(Table1[[#This Row],[AGE]])>39,"40-49",IF(ABS(Table1[[#This Row],[AGE]])>29,"30-39",IF(ABS(Table1[[#This Row],[AGE]])>19,"20-29",""))))) -> 40-49 | S39: Manila | T39: 5039 GSIS Hills, PVB Subd. | U39: Novaliches | V39: Quezon City | W39: NCR | X39: 1116 | Y39: Doctor of Medicine | Z39: Medicine | AA39: PRC | AB39: 0126641 | AC39: 45057 | AD39: 2004974738 | AE39: 1211-8530-4755 | AF39: 0300-0284-2080 | AG39: 471-526-496 | AH39: 0995-839-5932 | AI39: N/A | AJ39: jeanbaguio@gmail.com | AK39: 45565 | AL39: Resigned
A40: OSEC-DOHB-NUR1-270081-2020 | B40: Nurse I | C40: 15 | D40: =LOOKUP(C40,{1,2,3,4,5,6,7,8,9,10,11,12,13,14,15,16,17,18,19,20,21,22,23,24,25,26,27,28,29,30,31,32,33},{13000,13819,14678,15586,16543,17553,18620,19744,21211,23176,27000,29165,31320,33843,36619,39672,43030,46725,51357,57347,63997,71511,80003,90078,102690,116040,131124,148171,167432,189199,278434,331954,419144}) -> 36619 | E40: 2 | F40: =IF(Table1[[#This Row],[LAST]]="","Unfilled","Filled") -> Filled | G40: Mojica | H40: Mary Keith | I40: Marquilencia | K40: 32001 | L40: 45272 | M40: 45272 | N40: 45272 | O40: Married | P40: Female | Q40: =DATEDIF(K40,TODAY(),"Y") -> 39 | R40: =IF(ABS(Table1[[#This Row],[AGE]])>59,"60 and above",IF(ABS(Table1[[#This Row],[AGE]])>49,"50-59",IF(ABS(Table1[[#This Row],[AGE]])>39,"40-49",IF(ABS(Table1[[#This Row],[AGE]])>29,"30-39",IF(ABS(Table1[[#This Row],[AGE]])>19,"20-29",""))))) -> 30-39 | S40: Mandaluyong City | T40: B12 L4 Thistle St., Park Infina Ph. 2 | U40: Alapan II-A | V40: Imus City | W40: Cavite | X40: 4103 | Y40: College Graduate | Z40: BS Nursing | AA40: PRC | AB40: 0578547 | AC40: 08/12/2025 | AD40: N/A | AE40: 1211-2773-0881 | AF40: 0105-1948-9312 | AG40: 456-715-071 | AH40: 0917-849-3098 | AI40: N/A | AJ40: keith.marqui@gmail.com | AK40: 45550 | AL40: Resigned
A41: OSEC-DOHB-ADAS1-270007-2022 | B41: Administrative Assistant I (Records) | C41: 7 | D41: =LOOKUP(C41,{1,2,3,4,5,6,7,8,9,10,11,12,13,14,15,16,17,18,19,20,21,22,23,24,25,26,27,28,29,30,31,32,33},{13000,13819,14678,15586,16543,17553,18620,19744,21211,23176,27000,29165,31320,33843,36619,39672,43030,46725,51357,57347,63997,71511,80003,90078,102690,116040,131124,148171,167432,189199,278434,331954,419144}) -> 18620 | E41: 1 | F41: =IF(Table1[[#This Row],[LAST]]="","Unfilled","Filled") -> Filled | G41: Gonzales | H41: Marijoie | I41: Arbis | K41: 33086 | L41: 45107 | M41: 45107 | N41: 45107 | O41: Single | P41: Female | Q41: =DATEDIF(K41,TODAY(),"Y") -> 36 | R41: =IF(ABS(Table1[[#This Row],[AGE]])>59,"60 and above",IF(ABS(Table1[[#This Row],[AGE]])>49,"50-59",IF(ABS(Table1[[#This Row],[AGE]])>39,"40-49",IF(ABS(Table1[[#This Row],[AGE]])>29,"30-39",IF(ABS(Table1[[#This Row],[AGE]])>19,"20-29",""))))) -> 30-39 | S41: San Jose Del Monte, Bulacan | T41: Phase 2 Block 1 Lot 65, Boston Heights | U41: Toclong | V41: Kawit | W41: Cavite | X41: 4104 | Y41: College Graduate | Z41: BS HRM | AA41: CSC - Professional | AB41: N/A | AC41: N/A | AD41: 2006346220 | AE41: 1210-2074-7137 | AF41: 0202-5684-1690 | AG41: 420-355-011 | AH41: 0976-013-7577 | AI41: N/A | AJ41: gonzalesmarijoie@gmail.com | AK41: 45582 | AL41: Resigned
